Workbook

Sheet GUIDE
B2: HOW THIS MACHINE-PLANNING PACK WORKS
C3: Six visible tabs, in reading order: MD VIEW → DASHBOARD → LINE PLAN → MC MASTER → EMBELISHMENT → MC MAP. Backstage and hidden: DEMAND BY DATE (the daily engine), WORKINGS (helpers), plus PPC and MACHINE MASTER which are ARCHIVES ONLY — nothing reads them, and updating them changes nothing.
B5: QUICK START — 60 SECONDS
B6: 1. Type the plan | C6: On LINE PLAN, pick a style in each cell of the grid B6:DB31 (26 lines down, 105 dates across). Use the dropdown — it only offers styles that exist. The cell colours itself automatically; you never paint anything.
B7: 2. Watch the check cell | C7: LINE PLAN HA2 must read "ALL PLANNED STYLES CAN BE PRICED". If it turns red it tells you how many cells use a style with no machine recipe — those cells are NOT being costed. Fix before trusting any number.
B8: 3. Pick a date | C8: On DASHBOARD, use the yellow date picker to choose any day. Every number re-prices to that day. MD VIEW does the same at month level.
B9: 4. Read the KPIs | C9: Installed · Required · Utilisation · Groups short · Lines loaded · Output. If "Groups short" is above zero, the plan cannot physically be run that day even if total machines look sufficient.
B10: 5. Buy against the peak | C10: The PEAK MACHINE DEMAND block uses the worst day in the whole plan, not today. Purchase decisions use that table — never the single-day view.
B12: THE ONLY CELLS YOU EVER TYPE IN
B13: LINE PLAN B2 and B3 | C13: THE TWO DATE CONTROLS (yellow). B2 = plan start date. B3 = how many days the plan covers. Change B3 and the horizon extends or shrinks instantly — dates, the grid, the daily engine and both dashboards all follow. Capacity is built to 200 days; do not exceed that number. Month views cover the first four calendar months from the plan start.
B14: LINE PLAN B6:GS31 | C14: THE PLAN ITSELF. One style per line per date, chosen from the dropdown. Days beyond the horizon set in B3 are inert and cost nothing.
B15: LINE PLAN GY36:GY61 | C15: Which thermal style each line runs, when that line has THERMAL days. THERMAL on its own is a category, not a style, so it cannot be priced until you name the variant here.
B16: MC MASTER A3:C28 | C16: How many of each machine we own. This sheet IS our capacity. Machines are keyed by name, so changing a quantity is all that is needed.
B17: EMBELISHMENT | C17: The machine recipe per style — 25 operation rows × 42 style columns. Row 28 is the daily output target. This is the demand side of the model. Fully editable.
B18: MC MAP AG33:AG80 | C18: GARMENT TYPE per style, chosen from the dropdown. Cells reading "NEEDS INPUT" (shaded pink) are still blank.
B19: MC MAP AJ33:AJ43 | C19: THE GARMENT MASTER LIST. The only place garment names are typed. Add a new garment type here FIRST, then it becomes selectable in column AG.
B20: MC MAP K5:M28 / B5:B29 / B120 | C20: The alias table (planner's text → EMBELISHMENT column → category), the operation→machine map, and the month picker for the month view.
B21: DASHBOARD C4 / D4 / E4 / K71 | C21: View switch (DAY / MONTH END / MONTH PEAK), as-of date, month, and the garment picker for the drill-down. MD VIEW D4 is its month picker.
B22: DEMAND BY DATE BS | C22: Working-day calendar, Y or N per date. Days you add by raising B3 default to Y, except Sundays which default to N. Override any day by typing over it.
B23: EVERYTHING ELSE IS LOCKED | C23: Every sheet is now protected. The cells listed above are the only ones that accept typing — every formula in the pack is locked and Excel will refuse to overwrite it. There is no password, so the protection can be lifted from Review › Unprotect Sheet if a structural change is genuinely needed. Treat that as a deliberate act, not a workaround.
B24: Also blocked | C24: Sorting, filtering, and inserting or deleting rows and columns are switched off on every sheet. Sorting the plan grid used to scramble the row references behind it — that can no longer happen by accident.
B26: HOW THE DATA FLOWS
B27: The chain | C27: LINE PLAN typed styles → LINE PLAN resolved grid (expands THERMAL into the actual variant) → MC MAP block 3 pricing matrix (how many of each machine does this style need?) → DEMAND BY DATE (repeat that sum for every line, every day) → DASHBOARD / MD VIEW (compare against MC MASTER installed).
B28: In plain words | C28: Every line runs one style. Every style has a fixed machine recipe. So the machines needed on any day = the sum of 26 recipes. Subtract what we own, group by group, and the shortage or surplus falls out.
B29: Where to debug | C29: MC MAP is the workshop — all joining, translating and adding up happens there in the open where you can audit it. If a DASHBOARD number looks wrong the cause is in MC MAP or LINE PLAN, never on the DASHBOARD itself.
B31: MC MAP — THE WORKSHOP
B32: Block 1 (rows 4-28) | C32: OPERATION → MACHINE. A straight 1:1 join on the machine name, because MC MASTER names its machines exactly as EMBELISHMENT names its operation rows. Column C pulls the Available count from MC MASTER.
B33: Alias table (K5:M28) | C33: Planner's text → EMBELISHMENT recipe column → category. Handles names that differ between sheets, e.g. "4406/10" is held in EMBELISHMENT as "Panty", and "RS 26/27" as "RS-27".
B34: Block 3 (rows 32-80) | C34: STYLE × MACHINE MATRIX — the heart of the pack. 48 style rows × 26 machine groups: all 42 EMBELISHMENT styles plus 6 legacy board names (4300/4301, RS 26/27, 4406/10, RS17, THERMAL, VACCANT). Columns AB:AD are a self-audit — the re-grouped total must equal the EMBELISHMENT sheet total, shown as OK. AE = recipe, AF = category, AG = garment type.
B35: Block 4 (rows 85-112) | C35: LINE × MACHINE GROUP for the as-of date. The 26 lines, each given the style it runs that day, exploded across the 26 groups. The total row IS the factory's machine demand on that date.
B36: Block 7 (rows 119-203) | C36: MONTH VIEW — machine groups and styles down, one month of dates across. Pick the month at B120.
B37: Block 9 (CZ4:EV30) | C37: THE MATRIX, TRANSPOSED — machines down, all 48 styles across. Identical numbers to block 3, just rotated, because the daily engine needs to read a machine group as a row. Nothing to maintain; it follows block 3 automatically. DO NOT DELETE.
B39: HOW TO KEEP IT ALIVE — 5 ROUTINES
B40: Every day | C40: Nothing to do. Type or change styles on LINE PLAN and everything downstream re-prices instantly — there is no decode step any more. Just keep an eye on the check cell at LINE PLAN HA2.
B41: Filling a garment type | C41: Go to MC MAP column AG, find the style's row, and PICK from the dropdown. If the garment you want is not offered, add it to the GARMENT MASTER LIST at AJ33:AJ43 first, then pick it. Do not type free text into AG — the dropdown blocks it, because a typo would split the garment rollup into two half-totals. Pink "NEEDS INPUT" cells are the outstanding ones. This affects ONLY the by-garment breakdown; machine counts are correct either way.
B42: New style introduced | C42: (1) Give it a column in EMBELISHMENT with its machine recipe. (2) If the planner's name differs from the EMBELISHMENT heading, add the pairing to the alias table MC MAP K5:M28. (3) Add one row to MC MAP block 3 by copying the row above, and point column A at the new EMBELISHMENT heading. (4) Add the style to the validation list on LINE PLAN column HE (HE5:HE47). (5) Set its garment type in AG. All 42 current EMBELISHMENT styles are already covered.
B43: Machines bought or sold | C43: Update the Available column in MC MASTER only. Machines are keyed by name, so nothing else needs touching — unless a brand-new machine TYPE is added, in which case the 26-machine width of MC MAP blocks 3, 4, 9 and DEMAND BY DATE must be extended.
B44: Extending the date horizon | C44: ONE CELL. Raise LINE PLAN B3 ("DAYS IN PLAN"). Everything follows automatically: the date row, the plan grid, the resolved grid, the changeover flags, the daily engine, the peak-demand block and both dashboards. To shift the whole plan to a different start, change B2 instead. Capacity is built to 200 days — if you ever need more than that, ask me, because the grid width and the daily engine both have to grow. New days default to working, except Sundays; adjust in DEMAND BY DATE column BS.
B46: SELF-CHECKS — WHERE THE PACK TELLS YOU IT IS BROKEN
B47: LINE PLAN HA2 | C47: Unpriceable styles. Green = every planned cell can be costed. Red = the count of cells using a style with no machine recipe. THIS IS THE MOST IMPORTANT CELL IN THE PACK — a style that cannot be priced plans happily and costs zero machines.
B48: MC MAP AD33:AD80 | C48: Matrix cross-foot. Every row must read OK or n/a. Any number means the re-grouped machine total disagrees with the EMBELISHMENT sheet total for that style.
B49: MC MAP AG33:AG80 | C49: Pink "NEEDS INPUT" = garment type not yet set. Affects the by-garment breakdown only.
B50: DEMAND BY DATE AX | C50: Groups over capacity, per day. Above zero means the plan cannot physically be run that day even if total machines look sufficient.
B51: DEMAND BY DATE AW | C51: Thermal not specified. Counts lines with THERMAL days where no variant has been named in LINE PLAN GY36:GY61. Those lines are costing zero machines.
B53: COLOUR CONVENTIONS
B54: Blue text | C54: Something you type in — an input or a judgement call. Meant to be edited.
B55: Black text | C55: A formula. Do not overwrite with a typed number — it breaks the audit trail.
B56: Green text | C56: A value pulled from another sheet in this workbook.
B57: Light fills on the plan grid | C57: Applied automatically by conditional formatting from the typed style. You never paint a cell.
B58: Red / amber / grey / green flags | C58: DASHBOARD status: SHORT (need more than we own) / TIGHT (under 10% spare, one breakdown stops a line) / IDLE (nothing planned needs it) / OK.
B60: KNOWN GAPS — FLAGGED, NOT HIDDEN
B61: 19 garment types unset | C61: MC MAP AG column: 4222, 4223, RS-52, RS-60, RS-63, RS-92, BW-30, 4359, 4523, 4525, 5200, 5201, 5220, 5500, 5501, 5503, 5543, 5544 and 4110 have no garment type yet. Machine counts are correct; only the by-garment breakdown excludes them.
B62: Style names differ between sheets | C62: EMBELISHMENT does not always use the planner's name — e.g. 4406/10 is held as "Panty", RS 26/27 as "RS-27", 4300/4301 as separate 4300 and 4301 columns. The alias table at MC MAP K5:M28 handles this; no source sheet needs renaming.
B63: Thermal is a category | C63: THERMAL typed on its own cannot be priced — 5520, TH-01, TH-02, TH-04, TH-05 and TH-06 each have their own recipe. Name the variant in LINE PLAN GY36:GY61. Where a line runs a mix, the alias table defaults to the heaviest so capacity is never understated.
B64: PPC and MACHINE MASTER are archives | C64: Both hidden and referenced by nothing. Editing them changes no number in this pack. Kept only as a record of the original colour board and the original asset register.
B65: Horizon capacity is 200 days | C65: Days 1-200 are pre-built. Set the live horizon with LINE PLAN B3 (currently 105). Going beyond 200 needs a structural change on LINE PLAN and DEMAND BY DATE.
B67: Last reviewed | C67: Matrix covers all 48 styles; horizon made adjustable from one cell with 200-day capacity; every sheet protected with only input cells editable; peak requirement 808 machines; zero formula errors workbook-wide.

Sheet MD VIEW
BA1: month idx | BB1: =IFERROR(MATCH($D$4,'DEMAND BY DATE'!$BE$27:$BE$30,0),1) -> 1
B2: MACHINE CAPACITY — MONTHLY DECISION VIEW | BA2: first row | BB2: =INDEX('DEMAND BY DATE'!$BK$27:$BK$30,$BB$1) -> 1
B3: ='LINE PLAN'!$HB$21&" " -> Garment Unit A | BA3: days | BB3: =INDEX('DEMAND BY DATE'!$BL$27:$BL$30,$BB$1) -> 31
B4: MONTH ▾ | D4: August 2026 | BA4: working days | BB4: =INDEX('DEMAND BY DATE'!$BF$27:$BF$30,$BB$1) -> 26
BD5: Group | BE5: Family | BF5: Installed | BG5: Peak | BH5: Gap | BI5: Days short | BJ5: Family spare | BK5: Cover by moving | BL5: Must buy | BM5: rank | BN5: prior claims | BO5: spare rank
B6: Machines installed | D6: Machines required (month peak) | G6: IDLE | J6: Utilisation | M6: Machines to MOVE | P6: Machines to BUY | S6: Days plan won't run | BD6: =INDEX('MC MASTER'!$B$3:$B$28,1) -> SNLS | BE6: =IFERROR(INDEX('MC MAP'!$BX$5:$BX$30,MATCH($BD6,'MC MAP'!$BW$5:$BW$30,0)),"?") -> LOCK-STITCH | BF6: =INDEX('MC MASTER'!$C$3:$C$28,1) -> 185 | BG6: =MAX(OFFSET('DEMAND BY DATE'!$B$4,$BB$2-1,MATCH($BD6,'DEMAND BY DATE'!$B$3:$AA$3,0)-1,$BB$3,1)) -> 152 | BH6: =$BF6-$BG6 -> 33 | BI6: {=SUMPRODUCT((OFFSET('DEMAND BY DATE'!$B$4,$BB$2-1,MATCH($BD6,'DEMAND BY DATE'!$B$3:$AA$3,0)-1,$BB$3,1)>$BF6)*(OFFSET('DEMAND BY DATE'!$BS$4,$BB$2-1,0,$BB$3,1)="Y"))} -> 0 | BJ6: {=SUMPRODUCT(($BE$6:$BE$31=$BE6)*($BH$6:$BH$31>0)*$BH$6:$BH$31)-MAX(0,$BH6)} -> 13 | BK6: =IF($BH6<0,MIN(-$BH6,MAX(0,$BJ6-$BN6)),0) -> 0 | BL6: =IF($BH6<0,-$BH6-$BK6,0) -> 0 | BM6: =$BH6+ROW()/100000 -> 33.00006 | BN6: {=SUMPRODUCT(($BE$6:$BE$31=$BE6)*($BH$6:$BH$31<0)*($BM$6:$BM$31<$BM6)*(-$BH$6:$BH$31))} -> 0 | BO6: =MAX(0,$BH6)-ROW()/100000 -> 32.99994
B7: ='MC MASTER'!$C$29 -> 920 | D7: =INDEX('DEMAND BY DATE'!$BH$27:$BH$30,$BB$1) -> 808 | G7: {=SUMPRODUCT(($BH$6:$BH$31>0)*$BH$6:$BH$31)} -> 121 | J7: =IFERROR($D$7/$B$7,0) -> 0.87826087 | M7: =SUM($BK$6:$BK$31) -> 18.5 | P7: =SUM($BL$6:$BL$31) -> 28 | S7: {=SUMPRODUCT((OFFSET('DEMAND BY DATE'!$AX$4,$BB$2-1,0,$BB$3,1)>0)*1)} -> 26 | BD7: =INDEX('MC MASTER'!$B$3:$B$28,2) -> DNLS | BE7: =IFERROR(INDEX('MC MAP'!$BX$5:$BX$30,MATCH($BD7,'MC MAP'!$BW$5:$BW$30,0)),"?") -> LOCK-STITCH | BF7: =INDEX('MC MASTER'!$C$3:$C$28,2) -> 8 | BG7: =MAX(OFFSET('DEMAND BY DATE'!$B$4,$BB$2-1,MATCH($BD7,'DEMAND BY DATE'!$B$3:$AA$3,0)-1,$BB$3,1)) -> 1 | BH7: =$BF7-$BG7 -> 7 | BI7: {=SUMPRODUCT((OFFSET('DEMAND BY DATE'!$B$4,$BB$2-1,MATCH($BD7,'DEMAND BY DATE'!$B$3:$AA$3,0)-1,$BB$3,1)>$BF7)*(OFFSET('DEMAND BY DATE'!$BS$4,$BB$2-1,0,$BB$3,1)="Y"))} -> 0 | BJ7: {=SUMPRODUCT(($BE$6:$BE$31=$BE7)*($BH$6:$BH$31>0)*$BH$6:$BH$31)-MAX(0,$BH7)} -> 39 | BK7: =IF($BH7<0,MIN(-$BH7,MAX(0,$BJ7-$BN7)),0) -> 0 | BL7: =IF($BH7<0,-$BH7-$BK7,0) -> 0 | BM7: =$BH7+ROW()/100000 -> 7.00007 | BN7: {=SUMPRODUCT(($BE$6:$BE$31=$BE7)*($BH$6:$BH$31<0)*($BM$6:$BM$31<$BM7)*(-$BH$6:$BH$31))} -> 0 | BO7: =MAX(0,$BH7)-ROW()/100000 -> 6.99993
B8: ="In "&$D$4&": peak need "&TEXT($D$7,"#,##0")&" of "&TEXT($B$7,"#,##0")&" machines ("&TEXT($J$7,"0.0%")&"). "&COUNTIF($BH$6:$BH$31,"<0")&" machine types short. Move "&TEXT($M$7,"#,##0.0")&", buy "&TEXT($P$7,"#,##0.0")&". "&TEXT($G$7,"#,##0.0")&" machines idle." -> In August 2026: peak need 808 of 920 machines (87.8%). 6 machine types short. Move 18.5, buy 28.0. 121.0 machines idle. | BD8: =INDEX('MC MASTER'!$B$3:$B$28,3) -> SNLS - Edge cutter | BE8: =IFERROR(INDEX('MC MAP'!$BX$5:$BX$30,MATCH($BD8,'MC MAP'!$BW$5:$BW$30,0)),"?") -> LOCK-STITCH | BF8: =INDEX('MC MASTER'!$C$3:$C$28,3) -> 2 | BG8: =MAX(OFFSET('DEMAND BY DATE'!$B$4,$BB$2-1,MATCH($BD8,'DEMAND BY DATE'!$B$3:$AA$3,0)-1,$BB$3,1)) -> 0 | BH8: =$BF8-$BG8 -> 2 | BI8: {=SUMPRODUCT((OFFSET('DEMAND BY DATE'!$B$4,$BB$2-1,MATCH($BD8,'DEMAND BY DATE'!$B$3:$AA$3,0)-1,$BB$3,1)>$BF8)*(OFFSET('DEMAND BY DATE'!$BS$4,$BB$2-1,0,$BB$3,1)="Y"))} -> 0 | BJ8: {=SUMPRODUCT(($BE$6:$BE$31=$BE8)*($BH$6:$BH$31>0)*$BH$6:$BH$31)-MAX(0,$BH8)} -> 44 | BK8: =IF($BH8<0,MIN(-$BH8,MAX(0,$BJ8-$BN8)),0) -> 0 | BL8: =IF($BH8<0,-$BH8-$BK8,0) -> 0 | BM8: =$BH8+ROW()/100000 -> 2.00008 | BN8: {=SUMPRODUCT(($BE$6:$BE$31=$BE8)*($BH$6:$BH$31<0)*($BM$6:$BM$31<$BM8)*(-$BH$6:$BH$31))} -> 0 | BO8: =MAX(0,$BH8)-ROW()/100000 -> 1.99992
BD9: =INDEX('MC MASTER'!$B$3:$B$28,4) -> Zig - Zag | BE9: =IFERROR(INDEX('MC MAP'!$BX$5:$BX$30,MATCH($BD9,'MC MAP'!$BW$5:$BW$30,0)),"?") -> LOCK-STITCH | BF9: =INDEX('MC MASTER'!$C$3:$C$28,4) -> 8 | BG9: =MAX(OFFSET('DEMAND BY DATE'!$B$4,$BB$2-1,MATCH($BD9,'DEMAND BY DATE'!$B$3:$AA$3,0)-1,$BB$3,1)) -> 4 | BH9: =$BF9-$BG9 -> 4 | BI9: {=SUMPRODUCT((OFFSET('DEMAND BY DATE'!$B$4,$BB$2-1,MATCH($BD9,'DEMAND BY DATE'!$B$3:$AA$3,0)-1,$BB$3,1)>$BF9)*(OFFSET('DEMAND BY DATE'!$BS$4,$BB$2-1,0,$BB$3,1)="Y"))} -> 0 | BJ9: {=SUMPRODUCT(($BE$6:$BE$31=$BE9)*($BH$6:$BH$31>0)*$BH$6:$BH$31)-MAX(0,$BH9)} -> 42 | BK9: =IF($BH9<0,MIN(-$BH9,MAX(0,$BJ9-$BN9)),0) -> 0 | BL9: =IF($BH9<0,-$BH9-$BK9,0) -> 0 | BM9: =$BH9+ROW()/100000 -> 4.00009 | BN9: {=SUMPRODUCT(($BE$6:$BE$31=$BE9)*($BH$6:$BH$31<0)*($BM$6:$BM$31<$BM9)*(-$BH$6:$BH$31))} -> 0 | BO9: =MAX(0,$BH9)-ROW()/100000 -> 3.99991
B10: ="MACHINE CAPACITY - "& TEXT(D4,"mmmm yyyy") -> MACHINE CAPACITY - August 2026 | BD10: =INDEX('MC MASTER'!$B$3:$B$28,5) -> 4th Overlock | BE10: =IFERROR(INDEX('MC MAP'!$BX$5:$BX$30,MATCH($BD10,'MC MAP'!$BW$5:$BW$30,0)),"?") -> OVER-LOCK | BF10: =INDEX('MC MASTER'!$C$3:$C$28,5) -> 279 | BG10: =MAX(OFFSET('DEMAND BY DATE'!$B$4,$BB$2-1,MATCH($BD10,'DEMAND BY DATE'!$B$3:$AA$3,0)-1,$BB$3,1)) -> 291 | BH10: =$BF10-$BG10 -> -12 | BI10: {=SUMPRODUCT((OFFSET('DEMAND BY DATE'!$B$4,$BB$2-1,MATCH($BD10,'DEMAND BY DATE'!$B$3:$AA$3,0)-1,$BB$3,1)>$BF10)*(OFFSET('DEMAND BY DATE'!$BS$4,$BB$2-1,0,$BB$3,1)="Y"))} -> 11 | BJ10: {=SUMPRODUCT(($BE$6:$BE$31=$BE10)*($BH$6:$BH$31>0)*$BH$6:$BH$31)-MAX(0,$BH10)} -> 5 | BK10: =IF($BH10<0,MIN(-$BH10,MAX(0,$BJ10-$BN10)),0) -> 5 | BL10: =IF($BH10<0,-$BH10-$BK10,0) -> 7 | BM10: =$BH10+ROW()/100000 -> -11.9999 | BN10: {=SUMPRODUCT(($BE$6:$BE$31=$BE10)*($BH$6:$BH$31<0)*($BM$6:$BM$31<$BM10)*(-$BH$6:$BH$31))} -> 0 | BO10: =MAX(0,$BH10)-ROW()/100000 -> -0.0001
B11: Category | C11: Machine | D11: Own | E11: =IF(1>$BB$3,"",INDEX('DEMAND BY DATE'!$A$4:$A$203,$BB$2+0)) -> 46235 | F11: =IF(2>$BB$3,"",INDEX('DEMAND BY DATE'!$A$4:$A$203,$BB$2+1)) -> 46236 | G11: =IF(3>$BB$3,"",INDEX('DEMAND BY DATE'!$A$4:$A$203,$BB$2+2)) -> 46237 | H11: =IF(4>$BB$3,"",INDEX('DEMAND BY DATE'!$A$4:$A$203,$BB$2+3)) -> 46238 | I11: =IF(5>$BB$3,"",INDEX('DEMAND BY DATE'!$A$4:$A$203,$BB$2+4)) -> 46239 | J11: =IF(6>$BB$3,"",INDEX('DEMAND BY DATE'!$A$4:$A$203,$BB$2+5)) -> 46240 | K11: =IF(7>$BB$3,"",INDEX('DEMAND BY DATE'!$A$4:$A$203,$BB$2+6)) -> 46241 | L11: =IF(8>$BB$3,"",INDEX('DEMAND BY DATE'!$A$4:$A$203,$BB$2+7)) -> 46242 | M11: =IF(9>$BB$3,"",INDEX('DEMAND BY DATE'!$A$4:$A$203,$BB$2+8)) -> 46243 | N11: =IF(10>$BB$3,"",INDEX('DEMAND BY DATE'!$A$4:$A$203,$BB$2+9)) -> 46244 | O11: =IF(11>$BB$3,"",INDEX('DEMAND BY DATE'!$A$4:$A$203,$BB$2+10)) -> 46245 | P11: =IF(12>$BB$3,"",INDEX('DEMAND BY DATE'!$A$4:$A$203,$BB$2+11)) -> 46246 | Q11: =IF(13>$BB$3,"",INDEX('DEMAND BY DATE'!$A$4:$A$203,$BB$2+12)) -> 46247 | R11: =IF(14>$BB$3,"",INDEX('DEMAND BY DATE'!$A$4:$A$203,$BB$2+13)) -> 46248 | S11: =IF(15>$BB$3,"",INDEX('DEMAND BY DATE'!$A$4:$A$203,$BB$2+14)) -> 46249 | T11: =IF(16>$BB$3,"",INDEX('DEMAND BY DATE'!$A$4:$A$203,$BB$2+15)) -> 46250 | U11: =IF(17>$BB$3,"",INDEX('DEMAND BY DATE'!$A$4:$A$203,$BB$2+16)) -> 46251 | V11: =IF(18>$BB$3,"",INDEX('DEMAND BY DATE'!$A$4:$A$203,$BB$2+17)) -> 46252 | W11: =IF(19>$BB$3,"",INDEX('DEMAND BY DATE'!$A$4:$A$203,$BB$2+18)) -> 46253 | X11: =IF(20>$BB$3,"",INDEX('DEMAND BY DATE'!$A$4:$A$203,$BB$2+19)) -> 46254 | Y11: =IF(21>$BB$3,"",INDEX('DEMAND BY DATE'!$A$4:$A$203,$BB$2+20)) -> 46255 | Z11: =IF(22>$BB$3,"",INDEX('DEMAND BY DATE'!$A$4:$A$203,$BB$2+21)) -> 46256 | AA11: =IF(23>$BB$3,"",INDEX('DEMAND BY DATE'!$A$4:$A$203,$BB$2+22)) -> 46257 | AB11: =IF(24>$BB$3,"",INDEX('DEMAND BY DATE'!$A$4:$A$203,$BB$2+23)) -> 46258 | AC11: =IF(25>$BB$3,"",INDEX('DEMAND BY DATE'!$A$4:$A$203,$BB$2+24)) -> 46259 | AD11: =IF(26>$BB$3,"",INDEX('DEMAND BY DATE'!$A$4:$A$203,$BB$2+25)) -> 46260 | AE11: =IF(27>$BB$3,"",INDEX('DEMAND BY DATE'!$A$4:$A$203,$BB$2+26)) -> 46261 | AF11: =IF(28>$BB$3,"",INDEX('DEMAND BY DATE'!$A$4:$A$203,$BB$2+27)) -> 46262 | AG11: =IF(29>$BB$3,"",INDEX('DEMAND BY DATE'!$A$4:$A$203,$BB$2+28)) -> 46263 | AH11: =IF(30>$BB$3,"",INDEX('DEMAND BY DATE'!$A$4:$A$203,$BB$2+29)) -> 46264 | AI11: =IF(31>$BB$3,"",INDEX('DEMAND BY DATE'!$A$4:$A$203,$BB$2+30)) -> 46265 | BD11: =INDEX('MC MASTER'!$B$3:$B$28,6) -> 3th Overlock (Leg elastic) | BE11: =IFERROR(INDEX('MC MAP'!$BX$5:$BX$30,MATCH($BD11,'MC MAP'!$BW$5:$BW$30,0)),"?") -> OVER-LOCK | BF11: =INDEX('MC MASTER'!$C$3:$C$28,6) -> 30 | BG11: =MAX(OFFSET('DEMAND BY DATE'!$B$4,$BB$2-1,MATCH($BD11,'DEMAND BY DATE'!$B$3:$AA$3,0)-1,$BB$3,1)) -> 31 | BH11: =$BF11-$BG11 -> -1 | BI11: {=SUMPRODUCT((OFFSET('DEMAND BY DATE'!$B$4,$BB$2-1,MATCH($BD11,'DEMAND BY DATE'!$B$3:$AA$3,0)-1,$BB$3,1)>$BF11)*(OFFSET('DEMAND BY DATE'!$BS$4,$BB$2-1,0,$BB$3,1)="Y"))} -> 11 | BJ11: {=SUMPRODUCT(($BE$6:$BE$31=$BE11)*($BH$6:$BH$31>0)*$BH$6:$BH$31)-MAX(0,$BH11)} -> 5 | BK11: =IF($BH11<0,MIN(-$BH11,MAX(0,$BJ11-$BN11)),0) -> 0 | BL11: =IF($BH11<0,-$BH11-$BK11,0) -> 1 | BM11: =$BH11+ROW()/100000 -> -0.99989 | BN11: {=SUMPRODUCT(($BE$6:$BE$31=$BE11)*($BH$6:$BH$31<0)*($BM$6:$BM$31<$BM11)*(-$BH$6:$BH$31))} -> 19 | BO11: =MAX(0,$BH11)-ROW()/100000 -> -0.00011
B12: =IFERROR(INDEX(WORKINGS!$B$116:$B$141,MATCH($C12,WORKINGS!$A$116:$A$141,0)),"") -> LOCK-STITCH | C12: =INDEX(WORKINGS!$A$116:$A$141,MATCH(SMALL(WORKINGS!$D$116:$D$141,1),WORKINGS!$D$116:$D$141,0)) -> SNLS | D12: =IFERROR(INDEX($BF$6:$BF$31,MATCH($C12,$BD$6:$BD$31,0)),0) -> 185 | E12: =IF(E$11="","",IFERROR($D12-INDEX('DEMAND BY DATE'!$B$4:$AA$203,MATCH(E$11,'DEMAND BY DATE'!$A$4:$A$203,0),MATCH($C12,'DEMAND BY DATE'!$B$3:$AA$3,0)),"")) -> 33 | F12: =IF(F$11="","",IFERROR($D12-INDEX('DEMAND BY DATE'!$B$4:$AA$203,MATCH(F$11,'DEMAND BY DATE'!$A$4:$A$203,0),MATCH($C12,'DEMAND BY DATE'!$B$3:$AA$3,0)),"")) -> 33 | G12: =IF(G$11="","",IFERROR($D12-INDEX('DEMAND BY DATE'!$B$4:$AA$203,MATCH(G$11,'DEMAND BY DATE'!$A$4:$A$203,0),MATCH($C12,'DEMAND BY DATE'!$B$3:$AA$3,0)),"")) -> 33 | H12: =IF(H$11="","",IFERROR($D12-INDEX('DEMAND BY DATE'!$B$4:$AA$203,MATCH(H$11,'DEMAND BY DATE'!$A$4:$A$203,0),MATCH($C12,'DEMAND BY DATE'!$B$3:$AA$3,0)),"")) -> 33 | I12: =IF(I$11="","",IFERROR($D12-INDEX('DEMAND BY DATE'!$B$4:$AA$203,MATCH(I$11,'DEMAND BY DATE'!$A$4:$A$203,0),MATCH($C12,'DEMAND BY DATE'!$B$3:$AA$3,0)),"")) -> 33 | J12: =IF(J$11="","",IFERROR($D12-INDEX('DEMAND BY DATE'!$B$4:$AA$203,MATCH(J$11,'DEMAND BY DATE'!$A$4:$A$203,0),MATCH($C12,'DEMAND BY DATE'!$B$3:$AA$3,0)),"")) -> 33 | K12: =IF(K$11="","",IFERROR($D12-INDEX('DEMAND BY DATE'!$B$4:$AA$203,MATCH(K$11,'DEMAND BY DATE'!$A$4:$A$203,0),MATCH($C12,'DEMAND BY DATE'!$B$3:$AA$3,0)),"")) -> 33 | L12: =IF(L$11="","",IFERROR($D12-INDEX('DEMAND BY DATE'!$B$4:$AA$203,MATCH(L$11,'DEMAND BY DATE'!$A$4:$A$203,0),MATCH($C12,'DEMAND BY DATE'!$B$3:$AA$3,0)),"")) -> 33 | ... AI12: =IF(AI$11="","",IFERROR($D12-INDEX('DEMAND BY DATE'!$B$4:$AA$203,MATCH(AI$11,'DEMAND BY DATE'!$A$4:$A$203,0),MATCH($C12,'DEMAND BY DATE'!$B$3:$AA$3,0)),"")) -> 40.5 | BD12: =INDEX('MC MASTER'!$B$3:$B$28,7) -> 5th Overlock | BE12: =IFERROR(INDEX('MC MAP'!$BX$5:$BX$30,MATCH($BD12,'MC MAP'!$BW$5:$BW$30,0)),"?") -> OVER-LOCK | BF12: =INDEX('MC MASTER'!$C$3:$C$28,7) -> 5 | BG12: =MAX(OFFSET('DEMAND BY DATE'!$B$4,$BB$2-1,MATCH($BD12,'DEMAND BY DATE'!$B$3:$AA$3,0)-1,$BB$3,1)) -> 0 | BH12: =$BF12-$BG12 -> 5 | BI12: {=SUMPRODUCT((OFFSET('DEMAND BY DATE'!$B$4,$BB$2-1,MATCH($BD12,'DEMAND BY DATE'!$B$3:$AA$3,0)-1,$BB$3,1)>$BF12)*(OFFSET('DEMAND BY DATE'!$BS$4,$BB$2-1,0,$BB$3,1)="Y"))} -> 0 | BJ12: {=SUMPRODUCT(($BE$6:$BE$31=$BE12)*($BH$6:$BH$31>0)*$BH$6:$BH$31)-MAX(0,$BH12)} -> 0 | BK12: =IF($BH12<0,MIN(-$BH12,MAX(0,$BJ12-$BN12)),0) -> 0 | BL12: =IF($BH12<0,-$BH12-$BK12,0) -> 0 | BM12: =$BH12+ROW()/100000 -> 5.00012 | BN12: {=SUMPRODUCT(($BE$6:$BE$31=$BE12)*($BH$6:$BH$31<0)*($BM$6:$BM$31<$BM12)*(-$BH$6:$BH$31))} -> 20 | BO12: =MAX(0,$BH12)-ROW()/100000 -> 4.99988
B13: =IFERROR(INDEX(WORKINGS!$B$116:$B$141,MATCH($C13,WORKINGS!$A$116:$A$141,0)),"") -> LOCK-STITCH | C13: =INDEX(WORKINGS!$A$116:$A$141,MATCH(SMALL(WORKINGS!$D$116:$D$141,2),WORKINGS!$D$116:$D$141,0)) -> DNLS | D13: =IFERROR(INDEX($BF$6:$BF$31,MATCH($C13,$BD$6:$BD$31,0)),0) -> 8 | E13: =IF(E$11="","",IFERROR($D13-INDEX('DEMAND BY DATE'!$B$4:$AA$203,MATCH(E$11,'DEMAND BY DATE'!$A$4:$A$203,0),MATCH($C13,'DEMAND BY DATE'!$B$3:$AA$3,0)),"")) -> 7 | F13: =IF(F$11="","",IFERROR($D13-INDEX('DEMAND BY DATE'!$B$4:$AA$203,MATCH(F$11,'DEMAND BY DATE'!$A$4:$A$203,0),MATCH($C13,'DEMAND BY DATE'!$B$3:$AA$3,0)),"")) -> 7 | G13: =IF(G$11="","",IFERROR($D13-INDEX('DEMAND BY DATE'!$B$4:$AA$203,MATCH(G$11,'DEMAND BY DATE'!$A$4:$A$203,0),MATCH($C13,'DEMAND BY DATE'!$B$3:$AA$3,0)),"")) -> 7 | H13: =IF(H$11="","",IFERROR($D13-INDEX('DEMAND BY DATE'!$B$4:$AA$203,MATCH(H$11,'DEMAND BY DATE'!$A$4:$A$203,0),MATCH($C13,'DEMAND BY DATE'!$B$3:$AA$3,0)),"")) -> 7 | I13: =IF(I$11="","",IFERROR($D13-INDEX('DEMAND BY DATE'!$B$4:$AA$203,MATCH(I$11,'DEMAND BY DATE'!$A$4:$A$203,0),MATCH($C13,'DEMAND BY DATE'!$B$3:$AA$3,0)),"")) -> 7 | J13: =IF(J$11="","",IFERROR($D13-INDEX('DEMAND BY DATE'!$B$4:$AA$203,MATCH(J$11,'DEMAND BY DATE'!$A$4:$A$203,0),MATCH($C13,'DEMAND BY DATE'!$B$3:$AA$3,0)),"")) -> 7 | K13: =IF(K$11="","",IFERROR($D13-INDEX('DEMAND BY DATE'!$B$4:$AA$203,MATCH(K$11,'DEMAND BY DATE'!$A$4:$A$203,0),MATCH($C13,'DEMAND BY DATE'!$B$3:$AA$3,0)),"")) -> 7 | L13: =IF(L$11="","",IFERROR($D13-INDEX('DEMAND BY DATE'!$B$4:$AA$203,MATCH(L$11,'DEMAND BY DATE'!$A$4:$A$203,0),MATCH($C13,'DEMAND BY DATE'!$B$3:$AA$3,0)),"")) -> 7 | ... AI13: =IF(AI$11="","",IFERROR($D13-INDEX('DEMAND BY DATE'!$B$4:$AA$203,MATCH(AI$11,'DEMAND BY DATE'!$A$4:$A$203,0),MATCH($C13,'DEMAND BY DATE'!$B$3:$AA$3,0)),"")) -> 7 | BD13: =INDEX('MC MASTER'!$B$3:$B$28,8) -> Overlock (Ring Elastic Attach) | BE13: =IFERROR(INDEX('MC MAP'!$BX$5:$BX$30,MATCH($BD13,'MC MAP'!$BW$5:$BW$30,0)),"?") -> OVER-LOCK | BF13: =INDEX('MC MASTER'!$C$3:$C$28,8) -> 29 | BG13: =MAX(OFFSET('DEMAND BY DATE'!$B$4,$BB$2-1,MATCH($BD13,'DEMAND BY DATE'!$B$3:$AA$3,0)-1,$BB$3,1)) -> 36 | BH13: =$BF13-$BG13 -> -7 | BI13: {=SUMPRODUCT((OFFSET('DEMAND BY DATE'!$B$4,$BB$2-1,MATCH($BD13,'DEMAND BY DATE'!$B$3:$AA$3,0)-1,$BB$3,1)>$BF13)*(OFFSET('DEMAND BY DATE'!$BS$4,$BB$2-1,0,$BB$3,1)="Y"))} -> 26 | BJ13: {=SUMPRODUCT(($BE$6:$BE$31=$BE13)*($BH$6:$BH$31>0)*$BH$6:$BH$31)-MAX(0,$BH13)} -> 5 | BK13: =IF($BH13<0,MIN(-$BH13,MAX(0,$BJ13-$BN13)),0) -> 0 | BL13: =IF($BH13<0,-$BH13-$BK13,0) -> 7 | BM13: =$BH13+ROW()/100000 -> -6.99987 | BN13: {=SUMPRODUCT(($BE$6:$BE$31=$BE13)*($BH$6:$BH$31<0)*($BM$6:$BM$31<$BM13)*(-$BH$6:$BH$31))} -> 12 | BO13: =MAX(0,$BH13)-ROW()/100000 -> -0.00013
B14: =IFERROR(INDEX(WORKINGS!$B$116:$B$141,MATCH($C14,WORKINGS!$A$116:$A$141,0)),"") -> LOCK-STITCH | C14: =INDEX(WORKINGS!$A$116:$A$141,MATCH(SMALL(WORKINGS!$D$116:$D$141,3),WORKINGS!$D$116:$D$141,0)) -> SNLS - Edge cutter | D14: =IFERROR(INDEX($BF$6:$BF$31,MATCH($C14,$BD$6:$BD$31,0)),0) -> 2 | E14: =IF(E$11="","",IFERROR($D14-INDEX('DEMAND BY DATE'!$B$4:$AA$203,MATCH(E$11,'DEMAND BY DATE'!$A$4:$A$203,0),MATCH($C14,'DEMAND BY DATE'!$B$3:$AA$3,0)),"")) -> 2 | F14: =IF(F$11="","",IFERROR($D14-INDEX('DEMAND BY DATE'!$B$4:$AA$203,MATCH(F$11,'DEMAND BY DATE'!$A$4:$A$203,0),MATCH($C14,'DEMAND BY DATE'!$B$3:$AA$3,0)),"")) -> 2 | G14: =IF(G$11="","",IFERROR($D14-INDEX('DEMAND BY DATE'!$B$4:$AA$203,MATCH(G$11,'DEMAND BY DATE'!$A$4:$A$203,0),MATCH($C14,'DEMAND BY DATE'!$B$3:$AA$3,0)),"")) -> 2 | H14: =IF(H$11="","",IFERROR($D14-INDEX('DEMAND BY DATE'!$B$4:$AA$203,MATCH(H$11,'DEMAND BY DATE'!$A$4:$A$203,0),MATCH($C14,'DEMAND BY DATE'!$B$3:$AA$3,0)),"")) -> 2 | I14: =IF(I$11="","",IFERROR($D14-INDEX('DEMAND BY DATE'!$B$4:$AA$203,MATCH(I$11,'DEMAND BY DATE'!$A$4:$A$203,0),MATCH($C14,'DEMAND BY DATE'!$B$3:$AA$3,0)),"")) -> 2 | J14: =IF(J$11="","",IFERROR($D14-INDEX('DEMAND BY DATE'!$B$4:$AA$203,MATCH(J$11,'DEMAND BY DATE'!$A$4:$A$203,0),MATCH($C14,'DEMAND BY DATE'!$B$3:$AA$3,0)),"")) -> 2 | K14: =IF(K$11="","",IFERROR($D14-INDEX('DEMAND BY DATE'!$B$4:$AA$203,MATCH(K$11,'DEMAND BY DATE'!$A$4:$A$203,0),MATCH($C14,'DEMAND BY DATE'!$B$3:$AA$3,0)),"")) -> 2 | L14: =IF(L$11="","",IFERROR($D14-INDEX('DEMAND BY DATE'!$B$4:$AA$203,MATCH(L$11,'DEMAND BY DATE'!$A$4:$A$203,0),MATCH($C14,'DEMAND BY DATE'!$B$3:$AA$3,0)),"")) -> 2 | ... AI14: =IF(AI$11="","",IFERROR($D14-INDEX('DEMAND BY DATE'!$B$4:$AA$203,MATCH(AI$11,'DEMAND BY DATE'!$A$4:$A$203,0),MATCH($C14,'DEMAND BY DATE'!$B$3:$AA$3,0)),"")) -> 2 | BD14: =INDEX('MC MASTER'!$B$3:$B$28,9) -> Flatlock Hem | BE14: =IFERROR(INDEX('MC MAP'!$BX$5:$BX$30,MATCH($BD14,'MC MAP'!$BW$5:$BW$30,0)),"?") -> FLAT-LOCK | BF14: =INDEX('MC MASTER'!$C$3:$C$28,9) -> 34 | BG14: =MAX(OFFSET('DEMAND BY DATE'!$B$4,$BB$2-1,MATCH($BD14,'DEMAND BY DATE'!$B$3:$AA$3,0)-1,$BB$3,1)) -> 27.5 | BH14: =$BF14-$BG14 -> 6.5 | BI14: {=SUMPRODUCT((OFFSET('DEMAND BY DATE'!$B$4,$BB$2-1,MATCH($BD14,'DEMAND BY DATE'!$B$3:$AA$3,0)-1,$BB$3,1)>$BF14)*(OFFSET('DEMAND BY DATE'!$BS$4,$BB$2-1,0,$BB$3,1)="Y"))} -> 0 | BJ14: {=SUMPRODUCT(($BE$6:$BE$31=$BE14)*($BH$6:$BH$31>0)*$BH$6:$BH$31)-MAX(0,$BH14)} -> 7 | BK14: =IF($BH14<0,MIN(-$BH14,MAX(0,$BJ14-$BN14)),0) -> 0 | BL14: =IF($BH14<0,-$BH14-$BK14,0) -> 0 | BM14: =$BH14+ROW()/100000 -> 6.50014 | BN14: {=SUMPRODUCT(($BE$6:$BE$31=$BE14)*($BH$6:$BH$31<0)*($BM$6:$BM$31<$BM14)*(-$BH$6:$BH$31))} -> 26.5 | BO14: =MAX(0,$BH14)-ROW()/100000 -> 6.49986
B15: =IFERROR(INDEX(WORKINGS!$B$116:$B$141,MATCH($C15,WORKINGS!$A$116:$A$141,0)),"") -> LOCK-STITCH | C15: =INDEX(WORKINGS!$A$116:$A$141,MATCH(SMALL(WORKINGS!$D$116:$D$141,4),WORKINGS!$D$116:$D$141,0)) -> Zig - Zag | D15: =IFERROR(INDEX($BF$6:$BF$31,MATCH($C15,$BD$6:$BD$31,0)),0) -> 8 | E15: =IF(E$11="","",IFERROR($D15-INDEX('DEMAND BY DATE'!$B$4:$AA$203,MATCH(E$11,'DEMAND BY DATE'!$A$4:$A$203,0),MATCH($C15,'DEMAND BY DATE'!$B$3:$AA$3,0)),"")) -> 4 | F15: =IF(F$11="","",IFERROR($D15-INDEX('DEMAND BY DATE'!$B$4:$AA$203,MATCH(F$11,'DEMAND BY DATE'!$A$4:$A$203,0),MATCH($C15,'DEMAND BY DATE'!$B$3:$AA$3,0)),"")) -> 4 | G15: =IF(G$11="","",IFERROR($D15-INDEX('DEMAND BY DATE'!$B$4:$AA$203,MATCH(G$11,'DEMAND BY DATE'!$A$4:$A$203,0),MATCH($C15,'DEMAND BY DATE'!$B$3:$AA$3,0)),"")) -> 4 | H15: =IF(H$11="","",IFERROR($D15-INDEX('DEMAND BY DATE'!$B$4:$AA$203,MATCH(H$11,'DEMAND BY DATE'!$A$4:$A$203,0),MATCH($C15,'DEMAND BY DATE'!$B$3:$AA$3,0)),"")) -> 4 | I15: =IF(I$11="","",IFERROR($D15-INDEX('DEMAND BY DATE'!$B$4:$AA$203,MATCH(I$11,'DEMAND BY DATE'!$A$4:$A$203,0),MATCH($C15,'DEMAND BY DATE'!$B$3:$AA$3,0)),"")) -> 4 | J15: =IF(J$11="","",IFERROR($D15-INDEX('DEMAND BY DATE'!$B$4:$AA$203,MATCH(J$11,'DEMAND BY DATE'!$A$4:$A$203,0),MATCH($C15,'DEMAND BY DATE'!$B$3:$AA$3,0)),"")) -> 4 | K15: =IF(K$11="","",IFERROR($D15-INDEX('DEMAND BY DATE'!$B$4:$AA$203,MATCH(K$11,'DEMAND BY DATE'!$A$4:$A$203,0),MATCH($C15,'DEMAND BY DATE'!$B$3:$AA$3,0)),"")) -> 4 | L15: =IF(L$11="","",IFERROR($D15-INDEX('DEMAND BY DATE'!$B$4:$AA$203,MATCH(L$11,'DEMAND BY DATE'!$A$4:$A$203,0),MATCH($C15,'DEMAND BY DATE'!$B$3:$AA$3,0)),"")) -> 4 | ... AI15: =IF(AI$11="","",IFERROR($D15-INDEX('DEMAND BY DATE'!$B$4:$AA$203,MATCH(AI$11,'DEMAND BY DATE'!$A$4:$A$203,0),MATCH($C15,'DEMAND BY DATE'!$B$3:$AA$3,0)),"")) -> 4 | BD15: =INDEX('MC MASTER'!$B$3:$B$28,10) -> F/L (Coverseam / Waist COVER SEAM | BE15: =IFERROR(INDEX('MC MAP'!$BX$5:$BX$30,MATCH($BD15,'MC MAP'!$BW$5:$BW$30,0)),"?") -> FLAT-LOCK | BF15: =INDEX('MC MASTER'!$C$3:$C$28,10) -> 13 | BG15: =MAX(OFFSET('DEMAND BY DATE'!$B$4,$BB$2-1,MATCH($BD15,'DEMAND BY DATE'!$B$3:$AA$3,0)-1,$BB$3,1)) -> 12 | BH15: =$BF15-$BG15 -> 1 | BI15: {=SUMPRODUCT((OFFSET('DEMAND BY DATE'!$B$4,$BB$2-1,MATCH($BD15,'DEMAND BY DATE'!$B$3:$AA$3,0)-1,$BB$3,1)>$BF15)*(OFFSET('DEMAND BY DATE'!$BS$4,$BB$2-1,0,$BB$3,1)="Y"))} -> 0 | BJ15: {=SUMPRODUCT(($BE$6:$BE$31=$BE15)*($BH$6:$BH$31>0)*$BH$6:$BH$31)-MAX(0,$BH15)} -> 12.5 | BK15: =IF($BH15<0,MIN(-$BH15,MAX(0,$BJ15-$BN15)),0) -> 0 | BL15: =IF($BH15<0,-$BH15-$BK15,0) -> 0 | BM15: =$BH15+ROW()/100000 -> 1.00015 | BN15: {=SUMPRODUCT(($BE$6:$BE$31=$BE15)*($BH$6:$BH$31<0)*($BM$6:$BM$31<$BM15)*(-$BH$6:$BH$31))} -> 26.5 | BO15: =MAX(0,$BH15)-ROW()/100000 -> 0.99985
B16: =IFERROR(INDEX(WORKINGS!$B$116:$B$141,MATCH($C16,WORKINGS!$A$116:$A$141,0)),"") -> OVER-LOCK | C16: =INDEX(WORKINGS!$A$116:$A$141,MATCH(SMALL(WORKINGS!$D$116:$D$141,5),WORKINGS!$D$116:$D$141,0)) -> 4th Overlock | D16: =IFERROR(INDEX($BF$6:$BF$31,MATCH($C16,$BD$6:$BD$31,0)),0) -> 279 | E16: =IF(E$11="","",IFERROR($D16-INDEX('DEMAND BY DATE'!$B$4:$AA$203,MATCH(E$11,'DEMAND BY DATE'!$A$4:$A$203,0),MATCH($C16,'DEMAND BY DATE'!$B$3:$AA$3,0)),"")) -> -12 | F16: =IF(F$11="","",IFERROR($D16-INDEX('DEMAND BY DATE'!$B$4:$AA$203,MATCH(F$11,'DEMAND BY DATE'!$A$4:$A$203,0),MATCH($C16,'DEMAND BY DATE'!$B$3:$AA$3,0)),"")) -> -12 | G16: =IF(G$11="","",IFERROR($D16-INDEX('DEMAND BY DATE'!$B$4:$AA$203,MATCH(G$11,'DEMAND BY DATE'!$A$4:$A$203,0),MATCH($C16,'DEMAND BY DATE'!$B$3:$AA$3,0)),"")) -> -12 | H16: =IF(H$11="","",IFERROR($D16-INDEX('DEMAND BY DATE'!$B$4:$AA$203,MATCH(H$11,'DEMAND BY DATE'!$A$4:$A$203,0),MATCH($C16,'DEMAND BY DATE'!$B$3:$AA$3,0)),"")) -> -12 | I16: =IF(I$11="","",IFERROR($D16-INDEX('DEMAND BY DATE'!$B$4:$AA$203,MATCH(I$11,'DEMAND BY DATE'!$A$4:$A$203,0),MATCH($C16,'DEMAND BY DATE'!$B$3:$AA$3,0)),"")) -> -12 | J16: =IF(J$11="","",IFERROR($D16-INDEX('DEMAND BY DATE'!$B$4:$AA$203,MATCH(J$11,'DEMAND BY DATE'!$A$4:$A$203,0),MATCH($C16,'DEMAND BY DATE'!$B$3:$AA$3,0)),"")) -> -12 | K16: =IF(K$11="","",IFERROR($D16-INDEX('DEMAND BY DATE'!$B$4:$AA$203,MATCH(K$11,'DEMAND BY DATE'!$A$4:$A$203,0),MATCH($C16,'DEMAND BY DATE'!$B$3:$AA$3,0)),"")) -> -12 | L16: =IF(L$11="","",IFERROR($D16-INDEX('DEMAND BY DATE'!$B$4:$AA$203,MATCH(L$11,'DEMAND BY DATE'!$A$4:$A$203,0),MATCH($C16,'DEMAND BY DATE'!$B$3:$AA$3,0)),"")) -> -12 | ... AI16: =IF(AI$11="","",IFERROR($D16-INDEX('DEMAND BY DATE'!$B$4:$AA$203,MATCH(AI$11,'DEMAND BY DATE'!$A$4:$A$203,0),MATCH($C16,'DEMAND BY DATE'!$B$3:$AA$3,0)),"")) -> 13 | BD16: =INDEX('MC MASTER'!$B$3:$B$28,11) -> F/L (Coverseam )with pullar | BE16: =IFERROR(INDEX('MC MAP'!$BX$5:$BX$30,MATCH($BD16,'MC MAP'!$BW$5:$BW$30,0)),"?") -> FLAT-LOCK | BF16: =INDEX('MC MASTER'!$C$3:$C$28,11) -> 37 | BG16: =MAX(OFFSET('DEMAND BY DATE'!$B$4,$BB$2-1,MATCH($BD16,'DEMAND BY DATE'!$B$3:$AA$3,0)-1,$BB$3,1)) -> 43.5 | BH16: =$BF16-$BG16 -> -6.5 | BI16: {=SUMPRODUCT((OFFSET('DEMAND BY DATE'!$B$4,$BB$2-1,MATCH($BD16,'DEMAND BY DATE'!$B$3:$AA$3,0)-1,$BB$3,1)>$BF16)*(OFFSET('DEMAND BY DATE'!$BS$4,$BB$2-1,0,$BB$3,1)="Y"))} -> 25 | BJ16: {=SUMPRODUCT(($BE$6:$BE$31=$BE16)*($BH$6:$BH$31>0)*$BH$6:$BH$31)-MAX(0,$BH16)} -> 13.5 | BK16: =IF($BH16<0,MIN(-$BH16,MAX(0,$BJ16-$BN16)),0) -> 0 | BL16: =IF($BH16<0,-$BH16-$BK16,0) -> 6.5 | BM16: =$BH16+ROW()/100000 -> -6.49984 | BN16: {=SUMPRODUCT(($BE$6:$BE$31=$BE16)*($BH$6:$BH$31<0)*($BM$6:$BM$31<$BM16)*(-$BH$6:$BH$31))} -> 20 | BO16: =MAX(0,$BH16)-ROW()/100000 -> -0.00016
B17: =IFERROR(INDEX(WORKINGS!$B$116:$B$141,MATCH($C17,WORKINGS!$A$116:$A$141,0)),"") -> OVER-LOCK | C17: =INDEX(WORKINGS!$A$116:$A$141,MATCH(SMALL(WORKINGS!$D$116:$D$141,6),WORKINGS!$D$116:$D$141,0)) -> 3th Overlock (Leg elastic) | D17: =IFERROR(INDEX($BF$6:$BF$31,MATCH($C17,$BD$6:$BD$31,0)),0) -> 30 | E17: =IF(E$11="","",IFERROR($D17-INDEX('DEMAND BY DATE'!$B$4:$AA$203,MATCH(E$11,'DEMAND BY DATE'!$A$4:$A$203,0),MATCH($C17,'DEMAND BY DATE'!$B$3:$AA$3,0)),"")) -> -1 | F17: =IF(F$11="","",IFERROR($D17-INDEX('DEMAND BY DATE'!$B$4:$AA$203,MATCH(F$11,'DEMAND BY DATE'!$A$4:$A$203,0),MATCH($C17,'DEMAND BY DATE'!$B$3:$AA$3,0)),"")) -> -1 | G17: =IF(G$11="","",IFERROR($D17-INDEX('DEMAND BY DATE'!$B$4:$AA$203,MATCH(G$11,'DEMAND BY DATE'!$A$4:$A$203,0),MATCH($C17,'DEMAND BY DATE'!$B$3:$AA$3,0)),"")) -> -1 | H17: =IF(H$11="","",IFERROR($D17-INDEX('DEMAND BY DATE'!$B$4:$AA$203,MATCH(H$11,'DEMAND BY DATE'!$A$4:$A$203,0),MATCH($C17,'DEMAND BY DATE'!$B$3:$AA$3,0)),"")) -> -1 | I17: =IF(I$11="","",IFERROR($D17-INDEX('DEMAND BY DATE'!$B$4:$AA$203,MATCH(I$11,'DEMAND BY DATE'!$A$4:$A$203,0),MATCH($C17,'DEMAND BY DATE'!$B$3:$AA$3,0)),"")) -> -1 | J17: =IF(J$11="","",IFERROR($D17-INDEX('DEMAND BY DATE'!$B$4:$AA$203,MATCH(J$11,'DEMAND BY DATE'!$A$4:$A$203,0),MATCH($C17,'DEMAND BY DATE'!$B$3:$AA$3,0)),"")) -> -1 | K17: =IF(K$11="","",IFERROR($D17-INDEX('DEMAND BY DATE'!$B$4:$AA$203,MATCH(K$11,'DEMAND BY DATE'!$A$4:$A$203,0),MATCH($C17,'DEMAND BY DATE'!$B$3:$AA$3,0)),"")) -> -1 | L17: =IF(L$11="","",IFERROR($D17-INDEX('DEMAND BY DATE'!$B$4:$AA$203,MATCH(L$11,'DEMAND BY DATE'!$A$4:$A$203,0),MATCH($C17,'DEMAND BY DATE'!$B$3:$AA$3,0)),"")) -> -1 | ... AI17: =IF(AI$11="","",IFERROR($D17-INDEX('DEMAND BY DATE'!$B$4:$AA$203,MATCH(AI$11,'DEMAND BY DATE'!$A$4:$A$203,0),MATCH($C17,'DEMAND BY DATE'!$B$3:$AA$3,0)),"")) -> 0 | BD17: =INDEX('MC MASTER'!$B$3:$B$28,12) -> F/L (Coverseam ) | BE17: =IFERROR(INDEX('MC MAP'!$BX$5:$BX$30,MATCH($BD17,'MC MAP'!$BW$5:$BW$30,0)),"?") -> FLAT-LOCK | BF17: =INDEX('MC MASTER'!$C$3:$C$28,12) -> 6 | BG17: =MAX(OFFSET('DEMAND BY DATE'!$B$4,$BB$2-1,MATCH($BD17,'DEMAND BY DATE'!$B$3:$AA$3,0)-1,$BB$3,1)) -> 17 | BH17: =$BF17-$BG17 -> -11 | BI17: {=SUMPRODUCT((OFFSET('DEMAND BY DATE'!$B$4,$BB$2-1,MATCH($BD17,'DEMAND BY DATE'!$B$3:$AA$3,0)-1,$BB$3,1)>$BF17)*(OFFSET('DEMAND BY DATE'!$BS$4,$BB$2-1,0,$BB$3,1)="Y"))} -> 26 | BJ17: {=SUMPRODUCT(($BE$6:$BE$31=$BE17)*($BH$6:$BH$31>0)*$BH$6:$BH$31)-MAX(0,$BH17)} -> 13.5 | BK17: =IF($BH17<0,MIN(-$BH17,MAX(0,$BJ17-$BN17)),0) -> 11 | BL17: =IF($BH17<0,-$BH17-$BK17,0) -> 0 | BM17: =$BH17+ROW()/100000 -> -10.99983 | BN17: {=SUMPRODUCT(($BE$6:$BE$31=$BE17)*($BH$6:$BH$31<0)*($BM$6:$BM$31<$BM17)*(-$BH$6:$BH$31))} -> 0 | BO17: =MAX(0,$BH17)-ROW()/100000 -> -0.00017
B18: =IFERROR(INDEX(WORKINGS!$B$116:$B$141,MATCH($C18,WORKINGS!$A$116:$A$141,0)),"") -> OVER-LOCK | C18: =INDEX(WORKINGS!$A$116:$A$141,MATCH(SMALL(WORKINGS!$D$116:$D$141,7),WORKINGS!$D$116:$D$141,0)) -> 5th Overlock | D18: =IFERROR(INDEX($BF$6:$BF$31,MATCH($C18,$BD$6:$BD$31,0)),0) -> 5 | E18: =IF(E$11="","",IFERROR($D18-INDEX('DEMAND BY DATE'!$B$4:$AA$203,MATCH(E$11,'DEMAND BY DATE'!$A$4:$A$203,0),MATCH($C18,'DEMAND BY DATE'!$B$3:$AA$3,0)),"")) -> 5 | F18: =IF(F$11="","",IFERROR($D18-INDEX('DEMAND BY DATE'!$B$4:$AA$203,MATCH(F$11,'DEMAND BY DATE'!$A$4:$A$203,0),MATCH($C18,'DEMAND BY DATE'!$B$3:$AA$3,0)),"")) -> 5 | G18: =IF(G$11="","",IFERROR($D18-INDEX('DEMAND BY DATE'!$B$4:$AA$203,MATCH(G$11,'DEMAND BY DATE'!$A$4:$A$203,0),MATCH($C18,'DEMAND BY DATE'!$B$3:$AA$3,0)),"")) -> 5 | H18: =IF(H$11="","",IFERROR($D18-INDEX('DEMAND BY DATE'!$B$4:$AA$203,MATCH(H$11,'DEMAND BY DATE'!$A$4:$A$203,0),MATCH($C18,'DEMAND BY DATE'!$B$3:$AA$3,0)),"")) -> 5 | I18: =IF(I$11="","",IFERROR($D18-INDEX('DEMAND BY DATE'!$B$4:$AA$203,MATCH(I$11,'DEMAND BY DATE'!$A$4:$A$203,0),MATCH($C18,'DEMAND BY DATE'!$B$3:$AA$3,0)),"")) -> 5 | J18: =IF(J$11="","",IFERROR($D18-INDEX('DEMAND BY DATE'!$B$4:$AA$203,MATCH(J$11,'DEMAND BY DATE'!$A$4:$A$203,0),MATCH($C18,'DEMAND BY DATE'!$B$3:$AA$3,0)),"")) -> 5 | K18: =IF(K$11="","",IFERROR($D18-INDEX('DEMAND BY DATE'!$B$4:$AA$203,MATCH(K$11,'DEMAND BY DATE'!$A$4:$A$203,0),MATCH($C18,'DEMAND BY DATE'!$B$3:$AA$3,0)),"")) -> 5 | L18: =IF(L$11="","",IFERROR($D18-INDEX('DEMAND BY DATE'!$B$4:$AA$203,MATCH(L$11,'DEMAND BY DATE'!$A$4:$A$203,0),MATCH($C18,'DEMAND BY DATE'!$B$3:$AA$3,0)),"")) -> 5 | ... AI18: =IF(AI$11="","",IFERROR($D18-INDEX('DEMAND BY DATE'!$B$4:$AA$203,MATCH(AI$11,'DEMAND BY DATE'!$A$4:$A$203,0),MATCH($C18,'DEMAND BY DATE'!$B$3:$AA$3,0)),"")) -> 5 | BD18: =INDEX('MC MASTER'!$B$3:$B$28,13) -> Flatlock (Ring Elastic Attach) | BE18: =IFERROR(INDEX('MC MAP'!$BX$5:$BX$30,MATCH($BD18,'MC MAP'!$BW$5:$BW$30,0)),"?") -> OUTER ELASTIC | BF18: =INDEX('MC MASTER'!$C$3:$C$28,13) -> 42 | BG18: =MAX(OFFSET('DEMAND BY DATE'!$B$4,$BB$2-1,MATCH($BD18,'DEMAND BY DATE'!$B$3:$AA$3,0)-1,$BB$3,1)) -> 34.5 | BH18: =$BF18-$BG18 -> 7.5 | BI18: {=SUMPRODUCT((OFFSET('DEMAND BY DATE'!$B$4,$BB$2-1,MATCH($BD18,'DEMAND BY DATE'!$B$3:$AA$3,0)-1,$BB$3,1)>$BF18)*(OFFSET('DEMAND BY DATE'!$BS$4,$BB$2-1,0,$BB$3,1)="Y"))} -> 0 | BJ18: {=SUMPRODUCT(($BE$6:$BE$31=$BE18)*($BH$6:$BH$31>0)*$BH$6:$BH$31)-MAX(0,$BH18)} -> 0 | BK18: =IF($BH18<0,MIN(-$BH18,MAX(0,$BJ18-$BN18)),0) -> 0 | BL18: =IF($BH18<0,-$BH18-$BK18,0) -> 0 | BM18: =$BH18+ROW()/100000 -> 7.50018 | BN18: {=SUMPRODUCT(($BE$6:$BE$31=$BE18)*($BH$6:$BH$31<0)*($BM$6:$BM$31<$BM18)*(-$BH$6:$BH$31))} -> 0 | BO18: =MAX(0,$BH18)-ROW()/100000 -> 7.49982
B19: =IFERROR(INDEX(WORKINGS!$B$116:$B$141,MATCH($C19,WORKINGS!$A$116:$A$141,0)),"") -> OVER-LOCK | C19: =INDEX(WORKINGS!$A$116:$A$141,MATCH(SMALL(WORKINGS!$D$116:$D$141,8),WORKINGS!$D$116:$D$141,0)) -> Overlock (Ring Elastic Attach) | D19: =IFERROR(INDEX($BF$6:$BF$31,MATCH($C19,$BD$6:$BD$31,0)),0) -> 29 | E19: =IF(E$11="","",IFERROR($D19-INDEX('DEMAND BY DATE'!$B$4:$AA$203,MATCH(E$11,'DEMAND BY DATE'!$A$4:$A$203,0),MATCH($C19,'DEMAND BY DATE'!$B$3:$AA$3,0)),"")) -> -7 | F19: =IF(F$11="","",IFERROR($D19-INDEX('DEMAND BY DATE'!$B$4:$AA$203,MATCH(F$11,'DEMAND BY DATE'!$A$4:$A$203,0),MATCH($C19,'DEMAND BY DATE'!$B$3:$AA$3,0)),"")) -> -7 | G19: =IF(G$11="","",IFERROR($D19-INDEX('DEMAND BY DATE'!$B$4:$AA$203,MATCH(G$11,'DEMAND BY DATE'!$A$4:$A$203,0),MATCH($C19,'DEMAND BY DATE'!$B$3:$AA$3,0)),"")) -> -7 | H19: =IF(H$11="","",IFERROR($D19-INDEX('DEMAND BY DATE'!$B$4:$AA$203,MATCH(H$11,'DEMAND BY DATE'!$A$4:$A$203,0),MATCH($C19,'DEMAND BY DATE'!$B$3:$AA$3,0)),"")) -> -7 | I19: =IF(I$11="","",IFERROR($D19-INDEX('DEMAND BY DATE'!$B$4:$AA$203,MATCH(I$11,'DEMAND BY DATE'!$A$4:$A$203,0),MATCH($C19,'DEMAND BY DATE'!$B$3:$AA$3,0)),"")) -> -7 | J19: =IF(J$11="","",IFERROR($D19-INDEX('DEMAND BY DATE'!$B$4:$AA$203,MATCH(J$11,'DEMAND BY DATE'!$A$4:$A$203,0),MATCH($C19,'DEMAND BY DATE'!$B$3:$AA$3,0)),"")) -> -7 | K19: =IF(K$11="","",IFERROR($D19-INDEX('DEMAND BY DATE'!$B$4:$AA$203,MATCH(K$11,'DEMAND BY DATE'!$A$4:$A$203,0),MATCH($C19,'DEMAND BY DATE'!$B$3:$AA$3,0)),"")) -> -7 | L19: =IF(L$11="","",IFERROR($D19-INDEX('DEMAND BY DATE'!$B$4:$AA$203,MATCH(L$11,'DEMAND BY DATE'!$A$4:$A$203,0),MATCH($C19,'DEMAND BY DATE'!$B$3:$AA$3,0)),"")) -> -7 | ... AI19: =IF(AI$11="","",IFERROR($D19-INDEX('DEMAND BY DATE'!$B$4:$AA$203,MATCH(AI$11,'DEMAND BY DATE'!$A$4:$A$203,0),MATCH($C19,'DEMAND BY DATE'!$B$3:$AA$3,0)),"")) -> -7 | BD19: =INDEX('MC MASTER'!$B$3:$B$28,14) -> 3N5T-F/L -BINDING | BE19: =IFERROR(INDEX('MC MAP'!$BX$5:$BX$30,MATCH($BD19,'MC MAP'!$BW$5:$BW$30,0)),"?") -> BINDING | BF19: =INDEX('MC MASTER'!$C$3:$C$28,14) -> 58 | BG19: =MAX(OFFSET('DEMAND BY DATE'!$B$4,$BB$2-1,MATCH($BD19,'DEMAND BY DATE'!$B$3:$AA$3,0)-1,$BB$3,1)) -> 42 | BH19: =$BF19-$BG19 -> 16 | BI19: {=SUMPRODUCT((OFFSET('DEMAND BY DATE'!$B$4,$BB$2-1,MATCH($BD19,'DEMAND BY DATE'!$B$3:$AA$3,0)-1,$BB$3,1)>$BF19)*(OFFSET('DEMAND BY DATE'!$BS$4,$BB$2-1,0,$BB$3,1)="Y"))} -> 0 | BJ19: {=SUMPRODUCT(($BE$6:$BE$31=$BE19)*($BH$6:$BH$31>0)*$BH$6:$BH$31)-MAX(0,$BH19)} -> 0 | BK19: =IF($BH19<0,MIN(-$BH19,MAX(0,$BJ19-$BN19)),0) -> 0 | BL19: =IF($BH19<0,-$BH19-$BK19,0) -> 0 | BM19: =$BH19+ROW()/100000 -> 16.00019 | BN19: {=SUMPRODUCT(($BE$6:$BE$31=$BE19)*($BH$6:$BH$31<0)*($BM$6:$BM$31<$BM19)*(-$BH$6:$BH$31))} -> 0 | BO19: =MAX(0,$BH19)-ROW()/100000 -> 15.99981
B20: =IFERROR(INDEX(WORKINGS!$B$116:$B$141,MATCH($C20,WORKINGS!$A$116:$A$141,0)),"") -> FLAT-LOCK | C20: =INDEX(WORKINGS!$A$116:$A$141,MATCH(SMALL(WORKINGS!$D$116:$D$141,9),WORKINGS!$D$116:$D$141,0)) -> Flatlock Hem | D20: =IFERROR(INDEX($BF$6:$BF$31,MATCH($C20,$BD$6:$BD$31,0)),0) -> 34 | E20: =IF(E$11="","",IFERROR($D20-INDEX('DEMAND BY DATE'!$B$4:$AA$203,MATCH(E$11,'DEMAND BY DATE'!$A$4:$A$203,0),MATCH($C20,'DEMAND BY DATE'!$B$3:$AA$3,0)),"")) -> 11.5 | F20: =IF(F$11="","",IFERROR($D20-INDEX('DEMAND BY DATE'!$B$4:$AA$203,MATCH(F$11,'DEMAND BY DATE'!$A$4:$A$203,0),MATCH($C20,'DEMAND BY DATE'!$B$3:$AA$3,0)),"")) -> 11.5 | G20: =IF(G$11="","",IFERROR($D20-INDEX('DEMAND BY DATE'!$B$4:$AA$203,MATCH(G$11,'DEMAND BY DATE'!$A$4:$A$203,0),MATCH($C20,'DEMAND BY DATE'!$B$3:$AA$3,0)),"")) -> 11.5 | H20: =IF(H$11="","",IFERROR($D20-INDEX('DEMAND BY DATE'!$B$4:$AA$203,MATCH(H$11,'DEMAND BY DATE'!$A$4:$A$203,0),MATCH($C20,'DEMAND BY DATE'!$B$3:$AA$3,0)),"")) -> 11.5 | I20: =IF(I$11="","",IFERROR($D20-INDEX('DEMAND BY DATE'!$B$4:$AA$203,MATCH(I$11,'DEMAND BY DATE'!$A$4:$A$203,0),MATCH($C20,'DEMAND BY DATE'!$B$3:$AA$3,0)),"")) -> 11.5 | J20: =IF(J$11="","",IFERROR($D20-INDEX('DEMAND BY DATE'!$B$4:$AA$203,MATCH(J$11,'DEMAND BY DATE'!$A$4:$A$203,0),MATCH($C20,'DEMAND BY DATE'!$B$3:$AA$3,0)),"")) -> 11.5 | K20: =IF(K$11="","",IFERROR($D20-INDEX('DEMAND BY DATE'!$B$4:$AA$203,MATCH(K$11,'DEMAND BY DATE'!$A$4:$A$203,0),MATCH($C20,'DEMAND BY DATE'!$B$3:$AA$3,0)),"")) -> 11.5 | L20: =IF(L$11="","",IFERROR($D20-INDEX('DEMAND BY DATE'!$B$4:$AA$203,MATCH(L$11,'DEMAND BY DATE'!$A$4:$A$203,0),MATCH($C20,'DEMAND BY DATE'!$B$3:$AA$3,0)),"")) -> 11.5 | ... AI20: =IF(AI$11="","",IFERROR($D20-INDEX('DEMAND BY DATE'!$B$4:$AA$203,MATCH(AI$11,'DEMAND BY DATE'!$A$4:$A$203,0),MATCH($C20,'DEMAND BY DATE'!$B$3:$AA$3,0)),"")) -> 6.5 | BD20: =INDEX('MC MASTER'!$B$3:$B$28,15) -> 3N5T-F/L -( TopStitch) | BE20: =IFERROR(INDEX('MC MAP'!$BX$5:$BX$30,MATCH($BD20,'MC MAP'!$BW$5:$BW$30,0)),"?") -> FLAT-LOCK | BF20: =INDEX('MC MASTER'!$C$3:$C$28,15) -> 54 | BG20: =MAX(OFFSET('DEMAND BY DATE'!$B$4,$BB$2-1,MATCH($BD20,'DEMAND BY DATE'!$B$3:$AA$3,0)-1,$BB$3,1)) -> 63 | BH20: =$BF20-$BG20 -> -9 | BI20: {=SUMPRODUCT((OFFSET('DEMAND BY DATE'!$B$4,$BB$2-1,MATCH($BD20,'DEMAND BY DATE'!$B$3:$AA$3,0)-1,$BB$3,1)>$BF20)*(OFFSET('DEMAND BY DATE'!$BS$4,$BB$2-1,0,$BB$3,1)="Y"))} -> 14 | BJ20: {=SUMPRODUCT(($BE$6:$BE$31=$BE20)*($BH$6:$BH$31>0)*$BH$6:$BH$31)-MAX(0,$BH20)} -> 13.5 | BK20: =IF($BH20<0,MIN(-$BH20,MAX(0,$BJ20-$BN20)),0) -> 2.5 | BL20: =IF($BH20<0,-$BH20-$BK20,0) -> 6.5 | BM20: =$BH20+ROW()/100000 -> -8.9998 | BN20: {=SUMPRODUCT(($BE$6:$BE$31=$BE20)*($BH$6:$BH$31<0)*($BM$6:$BM$31<$BM20)*(-$BH$6:$BH$31))} -> 11 | BO20: =MAX(0,$BH20)-ROW()/100000 -> -0.0002
B21: =IFERROR(INDEX(WORKINGS!$B$116:$B$141,MATCH($C21,WORKINGS!$A$116:$A$141,0)),"") -> FLAT-LOCK | C21: =INDEX(WORKINGS!$A$116:$A$141,MATCH(SMALL(WORKINGS!$D$116:$D$141,10),WORKINGS!$D$116:$D$141,0)) -> F/L (Coverseam / Waist COVER SEAM | D21: =IFERROR(INDEX($BF$6:$BF$31,MATCH($C21,$BD$6:$BD$31,0)),0) -> 13 | E21: =IF(E$11="","",IFERROR($D21-INDEX('DEMAND BY DATE'!$B$4:$AA$203,MATCH(E$11,'DEMAND BY DATE'!$A$4:$A$203,0),MATCH($C21,'DEMAND BY DATE'!$B$3:$AA$3,0)),"")) -> 9 | F21: =IF(F$11="","",IFERROR($D21-INDEX('DEMAND BY DATE'!$B$4:$AA$203,MATCH(F$11,'DEMAND BY DATE'!$A$4:$A$203,0),MATCH($C21,'DEMAND BY DATE'!$B$3:$AA$3,0)),"")) -> 9 | G21: =IF(G$11="","",IFERROR($D21-INDEX('DEMAND BY DATE'!$B$4:$AA$203,MATCH(G$11,'DEMAND BY DATE'!$A$4:$A$203,0),MATCH($C21,'DEMAND BY DATE'!$B$3:$AA$3,0)),"")) -> 9 | H21: =IF(H$11="","",IFERROR($D21-INDEX('DEMAND BY DATE'!$B$4:$AA$203,MATCH(H$11,'DEMAND BY DATE'!$A$4:$A$203,0),MATCH($C21,'DEMAND BY DATE'!$B$3:$AA$3,0)),"")) -> 9 | I21: =IF(I$11="","",IFERROR($D21-INDEX('DEMAND BY DATE'!$B$4:$AA$203,MATCH(I$11,'DEMAND BY DATE'!$A$4:$A$203,0),MATCH($C21,'DEMAND BY DATE'!$B$3:$AA$3,0)),"")) -> 9 | J21: =IF(J$11="","",IFERROR($D21-INDEX('DEMAND BY DATE'!$B$4:$AA$203,MATCH(J$11,'DEMAND BY DATE'!$A$4:$A$203,0),MATCH($C21,'DEMAND BY DATE'!$B$3:$AA$3,0)),"")) -> 9 | K21: =IF(K$11="","",IFERROR($D21-INDEX('DEMAND BY DATE'!$B$4:$AA$203,MATCH(K$11,'DEMAND BY DATE'!$A$4:$A$203,0),MATCH($C21,'DEMAND BY DATE'!$B$3:$AA$3,0)),"")) -> 9 | L21: =IF(L$11="","",IFERROR($D21-INDEX('DEMAND BY DATE'!$B$4:$AA$203,MATCH(L$11,'DEMAND BY DATE'!$A$4:$A$203,0),MATCH($C21,'DEMAND BY DATE'!$B$3:$AA$3,0)),"")) -> 9 | ... AI21: =IF(AI$11="","",IFERROR($D21-INDEX('DEMAND BY DATE'!$B$4:$AA$203,MATCH(AI$11,'DEMAND BY DATE'!$A$4:$A$203,0),MATCH($C21,'DEMAND BY DATE'!$B$3:$AA$3,0)),"")) -> 1 | BD21: =INDEX('MC MASTER'!$B$3:$B$28,16) -> FlatSeamer FS | BE21: =IFERROR(INDEX('MC MAP'!$BX$5:$BX$30,MATCH($BD21,'MC MAP'!$BW$5:$BW$30,0)),"?") -> FS | BF21: =INDEX('MC MASTER'!$C$3:$C$28,16) -> 8 | BG21: =MAX(OFFSET('DEMAND BY DATE'!$B$4,$BB$2-1,MATCH($BD21,'DEMAND BY DATE'!$B$3:$AA$3,0)-1,$BB$3,1)) -> 0 | BH21: =$BF21-$BG21 -> 8 | BI21: {=SUMPRODUCT((OFFSET('DEMAND BY DATE'!$B$4,$BB$2-1,MATCH($BD21,'DEMAND BY DATE'!$B$3:$AA$3,0)-1,$BB$3,1)>$BF21)*(OFFSET('DEMAND BY DATE'!$BS$4,$BB$2-1,0,$BB$3,1)="Y"))} -> 0 | BJ21: {=SUMPRODUCT(($BE$6:$BE$31=$BE21)*($BH$6:$BH$31>0)*$BH$6:$BH$31)-MAX(0,$BH21)} -> 0 | BK21: =IF($BH21<0,MIN(-$BH21,MAX(0,$BJ21-$BN21)),0) -> 0 | BL21: =IF($BH21<0,-$BH21-$BK21,0) -> 0 | BM21: =$BH21+ROW()/100000 -> 8.00021 | BN21: {=SUMPRODUCT(($BE$6:$BE$31=$BE21)*($BH$6:$BH$31<0)*($BM$6:$BM$31<$BM21)*(-$BH$6:$BH$31))} -> 0 | BO21: =MAX(0,$BH21)-ROW()/100000 -> 7.99979
B22: =IFERROR(INDEX(WORKINGS!$B$116:$B$141,MATCH($C22,WORKINGS!$A$116:$A$141,0)),"") -> FLAT-LOCK | C22: =INDEX(WORKINGS!$A$116:$A$141,MATCH(SMALL(WORKINGS!$D$116:$D$141,11),WORKINGS!$D$116:$D$141,0)) -> F/L (Coverseam )with pullar | D22: =IFERROR(INDEX($BF$6:$BF$31,MATCH($C22,$BD$6:$BD$31,0)),0) -> 37 | E22: =IF(E$11="","",IFERROR($D22-INDEX('DEMAND BY DATE'!$B$4:$AA$203,MATCH(E$11,'DEMAND BY DATE'!$A$4:$A$203,0),MATCH($C22,'DEMAND BY DATE'!$B$3:$AA$3,0)),"")) -> -6.5 | F22: =IF(F$11="","",IFERROR($D22-INDEX('DEMAND BY DATE'!$B$4:$AA$203,MATCH(F$11,'DEMAND BY DATE'!$A$4:$A$203,0),MATCH($C22,'DEMAND BY DATE'!$B$3:$AA$3,0)),"")) -> -6.5 | G22: =IF(G$11="","",IFERROR($D22-INDEX('DEMAND BY DATE'!$B$4:$AA$203,MATCH(G$11,'DEMAND BY DATE'!$A$4:$A$203,0),MATCH($C22,'DEMAND BY DATE'!$B$3:$AA$3,0)),"")) -> -6.5 | H22: =IF(H$11="","",IFERROR($D22-INDEX('DEMAND BY DATE'!$B$4:$AA$203,MATCH(H$11,'DEMAND BY DATE'!$A$4:$A$203,0),MATCH($C22,'DEMAND BY DATE'!$B$3:$AA$3,0)),"")) -> -6.5 | I22: =IF(I$11="","",IFERROR($D22-INDEX('DEMAND BY DATE'!$B$4:$AA$203,MATCH(I$11,'DEMAND BY DATE'!$A$4:$A$203,0),MATCH($C22,'DEMAND BY DATE'!$B$3:$AA$3,0)),"")) -> -6.5 | J22: =IF(J$11="","",IFERROR($D22-INDEX('DEMAND BY DATE'!$B$4:$AA$203,MATCH(J$11,'DEMAND BY DATE'!$A$4:$A$203,0),MATCH($C22,'DEMAND BY DATE'!$B$3:$AA$3,0)),"")) -> -6.5 | K22: =IF(K$11="","",IFERROR($D22-INDEX('DEMAND BY DATE'!$B$4:$AA$203,MATCH(K$11,'DEMAND BY DATE'!$A$4:$A$203,0),MATCH($C22,'DEMAND BY DATE'!$B$3:$AA$3,0)),"")) -> -6.5 | L22: =IF(L$11="","",IFERROR($D22-INDEX('DEMAND BY DATE'!$B$4:$AA$203,MATCH(L$11,'DEMAND BY DATE'!$A$4:$A$203,0),MATCH($C22,'DEMAND BY DATE'!$B$3:$AA$3,0)),"")) -> -6.5 | ... AI22: =IF(AI$11="","",IFERROR($D22-INDEX('DEMAND BY DATE'!$B$4:$AA$203,MATCH(AI$11,'DEMAND BY DATE'!$A$4:$A$203,0),MATCH($C22,'DEMAND BY DATE'!$B$3:$AA$3,0)),"")) -> -5.5 | BD22: =INDEX('MC MASTER'!$B$3:$B$28,17) -> Kansai | BE22: =IFERROR(INDEX('MC MAP'!$BX$5:$BX$30,MATCH($BD22,'MC MAP'!$BW$5:$BW$30,0)),"?") -> MULTI-NEEDLE | BF22: =INDEX('MC MASTER'!$C$3:$C$28,17) -> 8 | BG22: =MAX(OFFSET('DEMAND BY DATE'!$B$4,$BB$2-1,MATCH($BD22,'DEMAND BY DATE'!$B$3:$AA$3,0)-1,$BB$3,1)) -> 3 | BH22: =$BF22-$BG22 -> 5 | BI22: {=SUMPRODUCT((OFFSET('DEMAND BY DATE'!$B$4,$BB$2-1,MATCH($BD22,'DEMAND BY DATE'!$B$3:$AA$3,0)-1,$BB$3,1)>$BF22)*(OFFSET('DEMAND BY DATE'!$BS$4,$BB$2-1,0,$BB$3,1)="Y"))} -> 0 | BJ22: {=SUMPRODUCT(($BE$6:$BE$31=$BE22)*($BH$6:$BH$31>0)*$BH$6:$BH$31)-MAX(0,$BH22)} -> 0 | BK22: =IF($BH22<0,MIN(-$BH22,MAX(0,$BJ22-$BN22)),0) -> 0 | BL22: =IF($BH22<0,-$BH22-$BK22,0) -> 0 | BM22: =$BH22+ROW()/100000 -> 5.00022 | BN22: {=SUMPRODUCT(($BE$6:$BE$31=$BE22)*($BH$6:$BH$31<0)*($BM$6:$BM$31<$BM22)*(-$BH$6:$BH$31))} -> 0 | BO22: =MAX(0,$BH22)-ROW()/100000 -> 4.99978
B23: =IFERROR(INDEX(WORKINGS!$B$116:$B$141,MATCH($C23,WORKINGS!$A$116:$A$141,0)),"") -> FLAT-LOCK | C23: =INDEX(WORKINGS!$A$116:$A$141,MATCH(SMALL(WORKINGS!$D$116:$D$141,12),WORKINGS!$D$116:$D$141,0)) -> F/L (Coverseam ) | D23: =IFERROR(INDEX($BF$6:$BF$31,MATCH($C23,$BD$6:$BD$31,0)),0) -> 6 | E23: =IF(E$11="","",IFERROR($D23-INDEX('DEMAND BY DATE'!$B$4:$AA$203,MATCH(E$11,'DEMAND BY DATE'!$A$4:$A$203,0),MATCH($C23,'DEMAND BY DATE'!$B$3:$AA$3,0)),"")) -> -11 | F23: =IF(F$11="","",IFERROR($D23-INDEX('DEMAND BY DATE'!$B$4:$AA$203,MATCH(F$11,'DEMAND BY DATE'!$A$4:$A$203,0),MATCH($C23,'DEMAND BY DATE'!$B$3:$AA$3,0)),"")) -> -11 | G23: =IF(G$11="","",IFERROR($D23-INDEX('DEMAND BY DATE'!$B$4:$AA$203,MATCH(G$11,'DEMAND BY DATE'!$A$4:$A$203,0),MATCH($C23,'DEMAND BY DATE'!$B$3:$AA$3,0)),"")) -> -11 | H23: =IF(H$11="","",IFERROR($D23-INDEX('DEMAND BY DATE'!$B$4:$AA$203,MATCH(H$11,'DEMAND BY DATE'!$A$4:$A$203,0),MATCH($C23,'DEMAND BY DATE'!$B$3:$AA$3,0)),"")) -> -11 | I23: =IF(I$11="","",IFERROR($D23-INDEX('DEMAND BY DATE'!$B$4:$AA$203,MATCH(I$11,'DEMAND BY DATE'!$A$4:$A$203,0),MATCH($C23,'DEMAND BY DATE'!$B$3:$AA$3,0)),"")) -> -11 | J23: =IF(J$11="","",IFERROR($D23-INDEX('DEMAND BY DATE'!$B$4:$AA$203,MATCH(J$11,'DEMAND BY DATE'!$A$4:$A$203,0),MATCH($C23,'DEMAND BY DATE'!$B$3:$AA$3,0)),"")) -> -11 | K23: =IF(K$11="","",IFERROR($D23-INDEX('DEMAND BY DATE'!$B$4:$AA$203,MATCH(K$11,'DEMAND BY DATE'!$A$4:$A$203,0),MATCH($C23,'DEMAND BY DATE'!$B$3:$AA$3,0)),"")) -> -11 | L23: =IF(L$11="","",IFERROR($D23-INDEX('DEMAND BY DATE'!$B$4:$AA$203,MATCH(L$11,'DEMAND BY DATE'!$A$4:$A$203,0),MATCH($C23,'DEMAND BY DATE'!$B$3:$AA$3,0)),"")) -> -11 | ... AI23: =IF(AI$11="","",IFERROR($D23-INDEX('DEMAND BY DATE'!$B$4:$AA$203,MATCH(AI$11,'DEMAND BY DATE'!$A$4:$A$203,0),MATCH($C23,'DEMAND BY DATE'!$B$3:$AA$3,0)),"")) -> -11 | BD23: =INDEX('MC MASTER'!$B$3:$B$28,18) -> Chain stitch | BE23: =IFERROR(INDEX('MC MAP'!$BX$5:$BX$30,MATCH($BD23,'MC MAP'!$BW$5:$BW$30,0)),"?") -> CS-DNLS | BF23: =INDEX('MC MASTER'!$C$3:$C$28,18) -> 2 | BG23: =MAX(OFFSET('DEMAND BY DATE'!$B$4,$BB$2-1,MATCH($BD23,'DEMAND BY DATE'!$B$3:$AA$3,0)-1,$BB$3,1)) -> 0 | BH23: =$BF23-$BG23 -> 2 | BI23: {=SUMPRODUCT((OFFSET('DEMAND BY DATE'!$B$4,$BB$2-1,MATCH($BD23,'DEMAND BY DATE'!$B$3:$AA$3,0)-1,$BB$3,1)>$BF23)*(OFFSET('DEMAND BY DATE'!$BS$4,$BB$2-1,0,$BB$3,1)="Y"))} -> 0 | BJ23: {=SUMPRODUCT(($BE$6:$BE$31=$BE23)*($BH$6:$BH$31>0)*$BH$6:$BH$31)-MAX(0,$BH23)} -> 0 | BK23: =IF($BH23<0,MIN(-$BH23,MAX(0,$BJ23-$BN23)),0) -> 0 | BL23: =IF($BH23<0,-$BH23-$BK23,0) -> 0 | BM23: =$BH23+ROW()/100000 -> 2.00023 | BN23: {=SUMPRODUCT(($BE$6:$BE$31=$BE23)*($BH$6:$BH$31<0)*($BM$6:$BM$31<$BM23)*(-$BH$6:$BH$31))} -> 0 | BO23: =MAX(0,$BH23)-ROW()/100000 -> 1.99977
B24: =IFERROR(INDEX(WORKINGS!$B$116:$B$141,MATCH($C24,WORKINGS!$A$116:$A$141,0)),"") -> FLAT-LOCK | C24: =INDEX(WORKINGS!$A$116:$A$141,MATCH(SMALL(WORKINGS!$D$116:$D$141,13),WORKINGS!$D$116:$D$141,0)) -> 3N5T-F/L -( TopStitch) | D24: =IFERROR(INDEX($BF$6:$BF$31,MATCH($C24,$BD$6:$BD$31,0)),0) -> 54 | E24: =IF(E$11="","",IFERROR($D24-INDEX('DEMAND BY DATE'!$B$4:$AA$203,MATCH(E$11,'DEMAND BY DATE'!$A$4:$A$203,0),MATCH($C24,'DEMAND BY DATE'!$B$3:$AA$3,0)),"")) -> 7 | F24: =IF(F$11="","",IFERROR($D24-INDEX('DEMAND BY DATE'!$B$4:$AA$203,MATCH(F$11,'DEMAND BY DATE'!$A$4:$A$203,0),MATCH($C24,'DEMAND BY DATE'!$B$3:$AA$3,0)),"")) -> 7 | G24: =IF(G$11="","",IFERROR($D24-INDEX('DEMAND BY DATE'!$B$4:$AA$203,MATCH(G$11,'DEMAND BY DATE'!$A$4:$A$203,0),MATCH($C24,'DEMAND BY DATE'!$B$3:$AA$3,0)),"")) -> 7 | H24: =IF(H$11="","",IFERROR($D24-INDEX('DEMAND BY DATE'!$B$4:$AA$203,MATCH(H$11,'DEMAND BY DATE'!$A$4:$A$203,0),MATCH($C24,'DEMAND BY DATE'!$B$3:$AA$3,0)),"")) -> 7 | I24: =IF(I$11="","",IFERROR($D24-INDEX('DEMAND BY DATE'!$B$4:$AA$203,MATCH(I$11,'DEMAND BY DATE'!$A$4:$A$203,0),MATCH($C24,'DEMAND BY DATE'!$B$3:$AA$3,0)),"")) -> 7 | J24: =IF(J$11="","",IFERROR($D24-INDEX('DEMAND BY DATE'!$B$4:$AA$203,MATCH(J$11,'DEMAND BY DATE'!$A$4:$A$203,0),MATCH($C24,'DEMAND BY DATE'!$B$3:$AA$3,0)),"")) -> 7 | K24: =IF(K$11="","",IFERROR($D24-INDEX('DEMAND BY DATE'!$B$4:$AA$203,MATCH(K$11,'DEMAND BY DATE'!$A$4:$A$203,0),MATCH($C24,'DEMAND BY DATE'!$B$3:$AA$3,0)),"")) -> 7 | L24: =IF(L$11="","",IFERROR($D24-INDEX('DEMAND BY DATE'!$B$4:$AA$203,MATCH(L$11,'DEMAND BY DATE'!$A$4:$A$203,0),MATCH($C24,'DEMAND BY DATE'!$B$3:$AA$3,0)),"")) -> 7 | ... AI24: =IF(AI$11="","",IFERROR($D24-INDEX('DEMAND BY DATE'!$B$4:$AA$203,MATCH(AI$11,'DEMAND BY DATE'!$A$4:$A$203,0),MATCH($C24,'DEMAND BY DATE'!$B$3:$AA$3,0)),"")) -> -9 | BD24: =INDEX('MC MASTER'!$B$3:$B$28,19) -> Flatlock (VT) | BE24: =IFERROR(INDEX('MC MAP'!$BX$5:$BX$30,MATCH($BD24,'MC MAP'!$BW$5:$BW$30,0)),"?") -> FLAT-LOCK | BF24: =INDEX('MC MASTER'!$C$3:$C$28,19) -> 21 | BG24: =MAX(OFFSET('DEMAND BY DATE'!$B$4,$BB$2-1,MATCH($BD24,'DEMAND BY DATE'!$B$3:$AA$3,0)-1,$BB$3,1)) -> 15 | BH24: =$BF24-$BG24 -> 6 | BI24: {=SUMPRODUCT((OFFSET('DEMAND BY DATE'!$B$4,$BB$2-1,MATCH($BD24,'DEMAND BY DATE'!$B$3:$AA$3,0)-1,$BB$3,1)>$BF24)*(OFFSET('DEMAND BY DATE'!$BS$4,$BB$2-1,0,$BB$3,1)="Y"))} -> 0 | BJ24: {=SUMPRODUCT(($BE$6:$BE$31=$BE24)*($BH$6:$BH$31>0)*$BH$6:$BH$31)-MAX(0,$BH24)} -> 7.5 | BK24: =IF($BH24<0,MIN(-$BH24,MAX(0,$BJ24-$BN24)),0) -> 0 | BL24: =IF($BH24<0,-$BH24-$BK24,0) -> 0 | BM24: =$BH24+ROW()/100000 -> 6.00024 | BN24: {=SUMPRODUCT(($BE$6:$BE$31=$BE24)*($BH$6:$BH$31<0)*($BM$6:$BM$31<$BM24)*(-$BH$6:$BH$31))} -> 26.5 | BO24: =MAX(0,$BH24)-ROW()/100000 -> 5.99976
B25: =IFERROR(INDEX(WORKINGS!$B$116:$B$141,MATCH($C25,WORKINGS!$A$116:$A$141,0)),"") -> FLAT-LOCK | C25: =INDEX(WORKINGS!$A$116:$A$141,MATCH(SMALL(WORKINGS!$D$116:$D$141,14),WORKINGS!$D$116:$D$141,0)) -> Flatlock (VT) | D25: =IFERROR(INDEX($BF$6:$BF$31,MATCH($C25,$BD$6:$BD$31,0)),0) -> 21 | E25: =IF(E$11="","",IFERROR($D25-INDEX('DEMAND BY DATE'!$B$4:$AA$203,MATCH(E$11,'DEMAND BY DATE'!$A$4:$A$203,0),MATCH($C25,'DEMAND BY DATE'!$B$3:$AA$3,0)),"")) -> 8 | F25: =IF(F$11="","",IFERROR($D25-INDEX('DEMAND BY DATE'!$B$4:$AA$203,MATCH(F$11,'DEMAND BY DATE'!$A$4:$A$203,0),MATCH($C25,'DEMAND BY DATE'!$B$3:$AA$3,0)),"")) -> 8 | G25: =IF(G$11="","",IFERROR($D25-INDEX('DEMAND BY DATE'!$B$4:$AA$203,MATCH(G$11,'DEMAND BY DATE'!$A$4:$A$203,0),MATCH($C25,'DEMAND BY DATE'!$B$3:$AA$3,0)),"")) -> 8 | H25: =IF(H$11="","",IFERROR($D25-INDEX('DEMAND BY DATE'!$B$4:$AA$203,MATCH(H$11,'DEMAND BY DATE'!$A$4:$A$203,0),MATCH($C25,'DEMAND BY DATE'!$B$3:$AA$3,0)),"")) -> 8 | I25: =IF(I$11="","",IFERROR($D25-INDEX('DEMAND BY DATE'!$B$4:$AA$203,MATCH(I$11,'DEMAND BY DATE'!$A$4:$A$203,0),MATCH($C25,'DEMAND BY DATE'!$B$3:$AA$3,0)),"")) -> 8 | J25: =IF(J$11="","",IFERROR($D25-INDEX('DEMAND BY DATE'!$B$4:$AA$203,MATCH(J$11,'DEMAND BY DATE'!$A$4:$A$203,0),MATCH($C25,'DEMAND BY DATE'!$B$3:$AA$3,0)),"")) -> 8 | K25: =IF(K$11="","",IFERROR($D25-INDEX('DEMAND BY DATE'!$B$4:$AA$203,MATCH(K$11,'DEMAND BY DATE'!$A$4:$A$203,0),MATCH($C25,'DEMAND BY DATE'!$B$3:$AA$3,0)),"")) -> 8 | L25: =IF(L$11="","",IFERROR($D25-INDEX('DEMAND BY DATE'!$B$4:$AA$203,MATCH(L$11,'DEMAND BY DATE'!$A$4:$A$203,0),MATCH($C25,'DEMAND BY DATE'!$B$3:$AA$3,0)),"")) -> 8 | ... AI25: =IF(AI$11="","",IFERROR($D25-INDEX('DEMAND BY DATE'!$B$4:$AA$203,MATCH(AI$11,'DEMAND BY DATE'!$A$4:$A$203,0),MATCH($C25,'DEMAND BY DATE'!$B$3:$AA$3,0)),"")) -> 6 | BD25: =INDEX('MC MASTER'!$B$3:$B$28,20) -> Heat Seal | BE25: =IFERROR(INDEX('MC MAP'!$BX$5:$BX$30,MATCH($BD25,'MC MAP'!$BW$5:$BW$30,0)),"?") -> HT | BF25: =INDEX('MC MASTER'!$C$3:$C$28,20) -> 35 | BG25: =MAX(OFFSET('DEMAND BY DATE'!$B$4,$BB$2-1,MATCH($BD25,'DEMAND BY DATE'!$B$3:$AA$3,0)-1,$BB$3,1)) -> 32.5 | BH25: =$BF25-$BG25 -> 2.5 | BI25: {=SUMPRODUCT((OFFSET('DEMAND BY DATE'!$B$4,$BB$2-1,MATCH($BD25,'DEMAND BY DATE'!$B$3:$AA$3,0)-1,$BB$3,1)>$BF25)*(OFFSET('DEMAND BY DATE'!$BS$4,$BB$2-1,0,$BB$3,1)="Y"))} -> 0 | BJ25: {=SUMPRODUCT(($BE$6:$BE$31=$BE25)*($BH$6:$BH$31>0)*$BH$6:$BH$31)-MAX(0,$BH25)} -> 0 | BK25: =IF($BH25<0,MIN(-$BH25,MAX(0,$BJ25-$BN25)),0) -> 0 | BL25: =IF($BH25<0,-$BH25-$BK25,0) -> 0 | BM25: =$BH25+ROW()/100000 -> 2.50025 | BN25: {=SUMPRODUCT(($BE$6:$BE$31=$BE25)*($BH$6:$BH$31<0)*($BM$6:$BM$31<$BM25)*(-$BH$6:$BH$31))} -> 0 | BO25: =MAX(0,$BH25)-ROW()/100000 -> 2.49975
B26: =IFERROR(INDEX(WORKINGS!$B$116:$B$141,MATCH($C26,WORKINGS!$A$116:$A$141,0)),"") -> OUTER ELASTIC | C26: =INDEX(WORKINGS!$A$116:$A$141,MATCH(SMALL(WORKINGS!$D$116:$D$141,15),WORKINGS!$D$116:$D$141,0)) -> Flatlock (Ring Elastic Attach) | D26: =IFERROR(INDEX($BF$6:$BF$31,MATCH($C26,$BD$6:$BD$31,0)),0) -> 42 | E26: =IF(E$11="","",IFERROR($D26-INDEX('DEMAND BY DATE'!$B$4:$AA$203,MATCH(E$11,'DEMAND BY DATE'!$A$4:$A$203,0),MATCH($C26,'DEMAND BY DATE'!$B$3:$AA$3,0)),"")) -> 7.5 | F26: =IF(F$11="","",IFERROR($D26-INDEX('DEMAND BY DATE'!$B$4:$AA$203,MATCH(F$11,'DEMAND BY DATE'!$A$4:$A$203,0),MATCH($C26,'DEMAND BY DATE'!$B$3:$AA$3,0)),"")) -> 7.5 | G26: =IF(G$11="","",IFERROR($D26-INDEX('DEMAND BY DATE'!$B$4:$AA$203,MATCH(G$11,'DEMAND BY DATE'!$A$4:$A$203,0),MATCH($C26,'DEMAND BY DATE'!$B$3:$AA$3,0)),"")) -> 7.5 | H26: =IF(H$11="","",IFERROR($D26-INDEX('DEMAND BY DATE'!$B$4:$AA$203,MATCH(H$11,'DEMAND BY DATE'!$A$4:$A$203,0),MATCH($C26,'DEMAND BY DATE'!$B$3:$AA$3,0)),"")) -> 7.5 | I26: =IF(I$11="","",IFERROR($D26-INDEX('DEMAND BY DATE'!$B$4:$AA$203,MATCH(I$11,'DEMAND BY DATE'!$A$4:$A$203,0),MATCH($C26,'DEMAND BY DATE'!$B$3:$AA$3,0)),"")) -> 7.5 | J26: =IF(J$11="","",IFERROR($D26-INDEX('DEMAND BY DATE'!$B$4:$AA$203,MATCH(J$11,'DEMAND BY DATE'!$A$4:$A$203,0),MATCH($C26,'DEMAND BY DATE'!$B$3:$AA$3,0)),"")) -> 7.5 | K26: =IF(K$11="","",IFERROR($D26-INDEX('DEMAND BY DATE'!$B$4:$AA$203,MATCH(K$11,'DEMAND BY DATE'!$A$4:$A$203,0),MATCH($C26,'DEMAND BY DATE'!$B$3:$AA$3,0)),"")) -> 7.5 | L26: =IF(L$11="","",IFERROR($D26-INDEX('DEMAND BY DATE'!$B$4:$AA$203,MATCH(L$11,'DEMAND BY DATE'!$A$4:$A$203,0),MATCH($C26,'DEMAND BY DATE'!$B$3:$AA$3,0)),"")) -> 7.5 | ... AI26: =IF(AI$11="","",IFERROR($D26-INDEX('DEMAND BY DATE'!$B$4:$AA$203,MATCH(AI$11,'DEMAND BY DATE'!$A$4:$A$203,0),MATCH($C26,'DEMAND BY DATE'!$B$3:$AA$3,0)),"")) -> 13.5 | BD26: =INDEX('MC MASTER'!$B$3:$B$28,21) -> Snap button | BE26: =IFERROR(INDEX('MC MAP'!$BX$5:$BX$30,MATCH($BD26,'MC MAP'!$BW$5:$BW$30,0)),"?") -> ILET | BF26: =INDEX('MC MASTER'!$C$3:$C$28,21) -> 2 | BG26: =MAX(OFFSET('DEMAND BY DATE'!$B$4,$BB$2-1,MATCH($BD26,'DEMAND BY DATE'!$B$3:$AA$3,0)-1,$BB$3,1)) -> 2 | BH26: =$BF26-$BG26 -> 0 | BI26: {=SUMPRODUCT((OFFSET('DEMAND BY DATE'!$B$4,$BB$2-1,MATCH($BD26,'DEMAND BY DATE'!$B$3:$AA$3,0)-1,$BB$3,1)>$BF26)*(OFFSET('DEMAND BY DATE'!$BS$4,$BB$2-1,0,$BB$3,1)="Y"))} -> 0 | BJ26: {=SUMPRODUCT(($BE$6:$BE$31=$BE26)*($BH$6:$BH$31>0)*$BH$6:$BH$31)-MAX(0,$BH26)} -> 0 | BK26: =IF($BH26<0,MIN(-$BH26,MAX(0,$BJ26-$BN26)),0) -> 0 | BL26: =IF($BH26<0,-$BH26-$BK26,0) -> 0 | BM26: =$BH26+ROW()/100000 -> 0.00026 | BN26: {=SUMPRODUCT(($BE$6:$BE$31=$BE26)*($BH$6:$BH$31<0)*($BM$6:$BM$31<$BM26)*(-$BH$6:$BH$31))} -> 0 | BO26: =MAX(0,$BH26)-ROW()/100000 -> -0.00026
B27: =IFERROR(INDEX(WORKINGS!$B$116:$B$141,MATCH($C27,WORKINGS!$A$116:$A$141,0)),"") -> BINDING | C27: =INDEX(WORKINGS!$A$116:$A$141,MATCH(SMALL(WORKINGS!$D$116:$D$141,16),WORKINGS!$D$116:$D$141,0)) -> 3N5T-F/L -BINDING | D27: =IFERROR(INDEX($BF$6:$BF$31,MATCH($C27,$BD$6:$BD$31,0)),0) -> 58 | E27: =IF(E$11="","",IFERROR($D27-INDEX('DEMAND BY DATE'!$B$4:$AA$203,MATCH(E$11,'DEMAND BY DATE'!$A$4:$A$203,0),MATCH($C27,'DEMAND BY DATE'!$B$3:$AA$3,0)),"")) -> 18 | F27: =IF(F$11="","",IFERROR($D27-INDEX('DEMAND BY DATE'!$B$4:$AA$203,MATCH(F$11,'DEMAND BY DATE'!$A$4:$A$203,0),MATCH($C27,'DEMAND BY DATE'!$B$3:$AA$3,0)),"")) -> 18 | G27: =IF(G$11="","",IFERROR($D27-INDEX('DEMAND BY DATE'!$B$4:$AA$203,MATCH(G$11,'DEMAND BY DATE'!$A$4:$A$203,0),MATCH($C27,'DEMAND BY DATE'!$B$3:$AA$3,0)),"")) -> 18 | H27: =IF(H$11="","",IFERROR($D27-INDEX('DEMAND BY DATE'!$B$4:$AA$203,MATCH(H$11,'DEMAND BY DATE'!$A$4:$A$203,0),MATCH($C27,'DEMAND BY DATE'!$B$3:$AA$3,0)),"")) -> 18 | I27: =IF(I$11="","",IFERROR($D27-INDEX('DEMAND BY DATE'!$B$4:$AA$203,MATCH(I$11,'DEMAND BY DATE'!$A$4:$A$203,0),MATCH($C27,'DEMAND BY DATE'!$B$3:$AA$3,0)),"")) -> 18 | J27: =IF(J$11="","",IFERROR($D27-INDEX('DEMAND BY DATE'!$B$4:$AA$203,MATCH(J$11,'DEMAND BY DATE'!$A$4:$A$203,0),MATCH($C27,'DEMAND BY DATE'!$B$3:$AA$3,0)),"")) -> 18 | K27: =IF(K$11="","",IFERROR($D27-INDEX('DEMAND BY DATE'!$B$4:$AA$203,MATCH(K$11,'DEMAND BY DATE'!$A$4:$A$203,0),MATCH($C27,'DEMAND BY DATE'!$B$3:$AA$3,0)),"")) -> 18 | L27: =IF(L$11="","",IFERROR($D27-INDEX('DEMAND BY DATE'!$B$4:$AA$203,MATCH(L$11,'DEMAND BY DATE'!$A$4:$A$203,0),MATCH($C27,'DEMAND BY DATE'!$B$3:$AA$3,0)),"")) -> 18 | ... AI27: =IF(AI$11="","",IFERROR($D27-INDEX('DEMAND BY DATE'!$B$4:$AA$203,MATCH(AI$11,'DEMAND BY DATE'!$A$4:$A$203,0),MATCH($C27,'DEMAND BY DATE'!$B$3:$AA$3,0)),"")) -> 16 | BD27: =INDEX('MC MASTER'!$B$3:$B$28,22) -> Button Hole | BE27: =IFERROR(INDEX('MC MAP'!$BX$5:$BX$30,MATCH($BD27,'MC MAP'!$BW$5:$BW$30,0)),"?") -> BH | BF27: =INDEX('MC MASTER'!$C$3:$C$28,22) -> 3 | BG27: =MAX(OFFSET('DEMAND BY DATE'!$B$4,$BB$2-1,MATCH($BD27,'DEMAND BY DATE'!$B$3:$AA$3,0)-1,$BB$3,1)) -> 2 | BH27: =$BF27-$BG27 -> 1 | BI27: {=SUMPRODUCT((OFFSET('DEMAND BY DATE'!$B$4,$BB$2-1,MATCH($BD27,'DEMAND BY DATE'!$B$3:$AA$3,0)-1,$BB$3,1)>$BF27)*(OFFSET('DEMAND BY DATE'!$BS$4,$BB$2-1,0,$BB$3,1)="Y"))} -> 0 | BJ27: {=SUMPRODUCT(($BE$6:$BE$31=$BE27)*($BH$6:$BH$31>0)*$BH$6:$BH$31)-MAX(0,$BH27)} -> 0 | BK27: =IF($BH27<0,MIN(-$BH27,MAX(0,$BJ27-$BN27)),0) -> 0 | BL27: =IF($BH27<0,-$BH27-$BK27,0) -> 0 | BM27: =$BH27+ROW()/100000 -> 1.00027 | BN27: {=SUMPRODUCT(($BE$6:$BE$31=$BE27)*($BH$6:$BH$31<0)*($BM$6:$BM$31<$BM27)*(-$BH$6:$BH$31))} -> 0 | BO27: =MAX(0,$BH27)-ROW()/100000 -> 0.99973
B28: =IFERROR(INDEX(WORKINGS!$B$116:$B$141,MATCH($C28,WORKINGS!$A$116:$A$141,0)),"") -> FS | C28: =INDEX(WORKINGS!$A$116:$A$141,MATCH(SMALL(WORKINGS!$D$116:$D$141,17),WORKINGS!$D$116:$D$141,0)) -> FlatSeamer FS | D28: =IFERROR(INDEX($BF$6:$BF$31,MATCH($C28,$BD$6:$BD$31,0)),0) -> 8 | E28: =IF(E$11="","",IFERROR($D28-INDEX('DEMAND BY DATE'!$B$4:$AA$203,MATCH(E$11,'DEMAND BY DATE'!$A$4:$A$203,0),MATCH($C28,'DEMAND BY DATE'!$B$3:$AA$3,0)),"")) -> 8 | F28: =IF(F$11="","",IFERROR($D28-INDEX('DEMAND BY DATE'!$B$4:$AA$203,MATCH(F$11,'DEMAND BY DATE'!$A$4:$A$203,0),MATCH($C28,'DEMAND BY DATE'!$B$3:$AA$3,0)),"")) -> 8 | G28: =IF(G$11="","",IFERROR($D28-INDEX('DEMAND BY DATE'!$B$4:$AA$203,MATCH(G$11,'DEMAND BY DATE'!$A$4:$A$203,0),MATCH($C28,'DEMAND BY DATE'!$B$3:$AA$3,0)),"")) -> 8 | H28: =IF(H$11="","",IFERROR($D28-INDEX('DEMAND BY DATE'!$B$4:$AA$203,MATCH(H$11,'DEMAND BY DATE'!$A$4:$A$203,0),MATCH($C28,'DEMAND BY DATE'!$B$3:$AA$3,0)),"")) -> 8 | I28: =IF(I$11="","",IFERROR($D28-INDEX('DEMAND BY DATE'!$B$4:$AA$203,MATCH(I$11,'DEMAND BY DATE'!$A$4:$A$203,0),MATCH($C28,'DEMAND BY DATE'!$B$3:$AA$3,0)),"")) -> 8 | J28: =IF(J$11="","",IFERROR($D28-INDEX('DEMAND BY DATE'!$B$4:$AA$203,MATCH(J$11,'DEMAND BY DATE'!$A$4:$A$203,0),MATCH($C28,'DEMAND BY DATE'!$B$3:$AA$3,0)),"")) -> 8 | K28: =IF(K$11="","",IFERROR($D28-INDEX('DEMAND BY DATE'!$B$4:$AA$203,MATCH(K$11,'DEMAND BY DATE'!$A$4:$A$203,0),MATCH($C28,'DEMAND BY DATE'!$B$3:$AA$3,0)),"")) -> 8 | L28: =IF(L$11="","",IFERROR($D28-INDEX('DEMAND BY DATE'!$B$4:$AA$203,MATCH(L$11,'DEMAND BY DATE'!$A$4:$A$203,0),MATCH($C28,'DEMAND BY DATE'!$B$3:$AA$3,0)),"")) -> 8 | ... AI28: =IF(AI$11="","",IFERROR($D28-INDEX('DEMAND BY DATE'!$B$4:$AA$203,MATCH(AI$11,'DEMAND BY DATE'!$A$4:$A$203,0),MATCH($C28,'DEMAND BY DATE'!$B$3:$AA$3,0)),"")) -> 8 | BD28: =INDEX('MC MASTER'!$B$3:$B$28,23) -> Button Attach | BE28: =IFERROR(INDEX('MC MAP'!$BX$5:$BX$30,MATCH($BD28,'MC MAP'!$BW$5:$BW$30,0)),"?") -> BA | BF28: =INDEX('MC MASTER'!$C$3:$C$28,23) -> 1 | BG28: =MAX(OFFSET('DEMAND BY DATE'!$B$4,$BB$2-1,MATCH($BD28,'DEMAND BY DATE'!$B$3:$AA$3,0)-1,$BB$3,1)) -> 0 | BH28: =$BF28-$BG28 -> 1 | BI28: {=SUMPRODUCT((OFFSET('DEMAND BY DATE'!$B$4,$BB$2-1,MATCH($BD28,'DEMAND BY DATE'!$B$3:$AA$3,0)-1,$BB$3,1)>$BF28)*(OFFSET('DEMAND BY DATE'!$BS$4,$BB$2-1,0,$BB$3,1)="Y"))} -> 0 | BJ28: {=SUMPRODUCT(($BE$6:$BE$31=$BE28)*($BH$6:$BH$31>0)*$BH$6:$BH$31)-MAX(0,$BH28)} -> 0 | BK28: =IF($BH28<0,MIN(-$BH28,MAX(0,$BJ28-$BN28)),0) -> 0 | BL28: =IF($BH28<0,-$BH28-$BK28,0) -> 0 | BM28: =$BH28+ROW()/100000 -> 1.00028 | BN28: {=SUMPRODUCT(($BE$6:$BE$31=$BE28)*($BH$6:$BH$31<0)*($BM$6:$BM$31<$BM28)*(-$BH$6:$BH$31))} -> 0 | BO28: =MAX(0,$BH28)-ROW()/100000 -> 0.99972
B29: =IFERROR(INDEX(WORKINGS!$B$116:$B$141,MATCH($C29,WORKINGS!$A$116:$A$141,0)),"") -> MULTI-NEEDLE | C29: =INDEX(WORKINGS!$A$116:$A$141,MATCH(SMALL(WORKINGS!$D$116:$D$141,18),WORKINGS!$D$116:$D$141,0)) -> Kansai | D29: =IFERROR(INDEX($BF$6:$BF$31,MATCH($C29,$BD$6:$BD$31,0)),0) -> 8 | E29: =IF(E$11="","",IFERROR($D29-INDEX('DEMAND BY DATE'!$B$4:$AA$203,MATCH(E$11,'DEMAND BY DATE'!$A$4:$A$203,0),MATCH($C29,'DEMAND BY DATE'!$B$3:$AA$3,0)),"")) -> 5 | F29: =IF(F$11="","",IFERROR($D29-INDEX('DEMAND BY DATE'!$B$4:$AA$203,MATCH(F$11,'DEMAND BY DATE'!$A$4:$A$203,0),MATCH($C29,'DEMAND BY DATE'!$B$3:$AA$3,0)),"")) -> 5 | G29: =IF(G$11="","",IFERROR($D29-INDEX('DEMAND BY DATE'!$B$4:$AA$203,MATCH(G$11,'DEMAND BY DATE'!$A$4:$A$203,0),MATCH($C29,'DEMAND BY DATE'!$B$3:$AA$3,0)),"")) -> 5 | H29: =IF(H$11="","",IFERROR($D29-INDEX('DEMAND BY DATE'!$B$4:$AA$203,MATCH(H$11,'DEMAND BY DATE'!$A$4:$A$203,0),MATCH($C29,'DEMAND BY DATE'!$B$3:$AA$3,0)),"")) -> 5 | I29: =IF(I$11="","",IFERROR($D29-INDEX('DEMAND BY DATE'!$B$4:$AA$203,MATCH(I$11,'DEMAND BY DATE'!$A$4:$A$203,0),MATCH($C29,'DEMAND BY DATE'!$B$3:$AA$3,0)),"")) -> 5 | J29: =IF(J$11="","",IFERROR($D29-INDEX('DEMAND BY DATE'!$B$4:$AA$203,MATCH(J$11,'DEMAND BY DATE'!$A$4:$A$203,0),MATCH($C29,'DEMAND BY DATE'!$B$3:$AA$3,0)),"")) -> 5 | K29: =IF(K$11="","",IFERROR($D29-INDEX('DEMAND BY DATE'!$B$4:$AA$203,MATCH(K$11,'DEMAND BY DATE'!$A$4:$A$203,0),MATCH($C29,'DEMAND BY DATE'!$B$3:$AA$3,0)),"")) -> 5 | L29: =IF(L$11="","",IFERROR($D29-INDEX('DEMAND BY DATE'!$B$4:$AA$203,MATCH(L$11,'DEMAND BY DATE'!$A$4:$A$203,0),MATCH($C29,'DEMAND BY DATE'!$B$3:$AA$3,0)),"")) -> 5 | ... AI29: =IF(AI$11="","",IFERROR($D29-INDEX('DEMAND BY DATE'!$B$4:$AA$203,MATCH(AI$11,'DEMAND BY DATE'!$A$4:$A$203,0),MATCH($C29,'DEMAND BY DATE'!$B$3:$AA$3,0)),"")) -> 5 | BD29: =INDEX('MC MASTER'!$B$3:$B$28,24) -> Bartack | BE29: =IFERROR(INDEX('MC MAP'!$BX$5:$BX$30,MATCH($BD29,'MC MAP'!$BW$5:$BW$30,0)),"?") -> BTK | BF29: =INDEX('MC MASTER'!$C$3:$C$28,24) -> 13 | BG29: =MAX(OFFSET('DEMAND BY DATE'!$B$4,$BB$2-1,MATCH($BD29,'DEMAND BY DATE'!$B$3:$AA$3,0)-1,$BB$3,1)) -> 7.5 | BH29: =$BF29-$BG29 -> 5.5 | BI29: {=SUMPRODUCT((OFFSET('DEMAND BY DATE'!$B$4,$BB$2-1,MATCH($BD29,'DEMAND BY DATE'!$B$3:$AA$3,0)-1,$BB$3,1)>$BF29)*(OFFSET('DEMAND BY DATE'!$BS$4,$BB$2-1,0,$BB$3,1)="Y"))} -> 0 | BJ29: {=SUMPRODUCT(($BE$6:$BE$31=$BE29)*($BH$6:$BH$31>0)*$BH$6:$BH$31)-MAX(0,$BH29)} -> 0 | BK29: =IF($BH29<0,MIN(-$BH29,MAX(0,$BJ29-$BN29)),0) -> 0 | BL29: =IF($BH29<0,-$BH29-$BK29,0) -> 0 | BM29: =$BH29+ROW()/100000 -> 5.50029 | BN29: {=SUMPRODUCT(($BE$6:$BE$31=$BE29)*($BH$6:$BH$31<0)*($BM$6:$BM$31<$BM29)*(-$BH$6:$BH$31))} -> 0 | BO29: =MAX(0,$BH29)-ROW()/100000 -> 5.49971
B30: =IFERROR(INDEX(WORKINGS!$B$116:$B$141,MATCH($C30,WORKINGS!$A$116:$A$141,0)),"") -> CS-DNLS | C30: =INDEX(WORKINGS!$A$116:$A$141,MATCH(SMALL(WORKINGS!$D$116:$D$141,19),WORKINGS!$D$116:$D$141,0)) -> Chain stitch | D30: =IFERROR(INDEX($BF$6:$BF$31,MATCH($C30,$BD$6:$BD$31,0)),0) -> 2 | E30: =IF(E$11="","",IFERROR($D30-INDEX('DEMAND BY DATE'!$B$4:$AA$203,MATCH(E$11,'DEMAND BY DATE'!$A$4:$A$203,0),MATCH($C30,'DEMAND BY DATE'!$B$3:$AA$3,0)),"")) -> 2 | F30: =IF(F$11="","",IFERROR($D30-INDEX('DEMAND BY DATE'!$B$4:$AA$203,MATCH(F$11,'DEMAND BY DATE'!$A$4:$A$203,0),MATCH($C30,'DEMAND BY DATE'!$B$3:$AA$3,0)),"")) -> 2 | G30: =IF(G$11="","",IFERROR($D30-INDEX('DEMAND BY DATE'!$B$4:$AA$203,MATCH(G$11,'DEMAND BY DATE'!$A$4:$A$203,0),MATCH($C30,'DEMAND BY DATE'!$B$3:$AA$3,0)),"")) -> 2 | H30: =IF(H$11="","",IFERROR($D30-INDEX('DEMAND BY DATE'!$B$4:$AA$203,MATCH(H$11,'DEMAND BY DATE'!$A$4:$A$203,0),MATCH($C30,'DEMAND BY DATE'!$B$3:$AA$3,0)),"")) -> 2 | I30: =IF(I$11="","",IFERROR($D30-INDEX('DEMAND BY DATE'!$B$4:$AA$203,MATCH(I$11,'DEMAND BY DATE'!$A$4:$A$203,0),MATCH($C30,'DEMAND BY DATE'!$B$3:$AA$3,0)),"")) -> 2 | J30: =IF(J$11="","",IFERROR($D30-INDEX('DEMAND BY DATE'!$B$4:$AA$203,MATCH(J$11,'DEMAND BY DATE'!$A$4:$A$203,0),MATCH($C30,'DEMAND BY DATE'!$B$3:$AA$3,0)),"")) -> 2 | K30: =IF(K$11="","",IFERROR($D30-INDEX('DEMAND BY DATE'!$B$4:$AA$203,MATCH(K$11,'DEMAND BY DATE'!$A$4:$A$203,0),MATCH($C30,'DEMAND BY DATE'!$B$3:$AA$3,0)),"")) -> 2 | L30: =IF(L$11="","",IFERROR($D30-INDEX('DEMAND BY DATE'!$B$4:$AA$203,MATCH(L$11,'DEMAND BY DATE'!$A$4:$A$203,0),MATCH($C30,'DEMAND BY DATE'!$B$3:$AA$3,0)),"")) -> 2 | ... AI30: =IF(AI$11="","",IFERROR($D30-INDEX('DEMAND BY DATE'!$B$4:$AA$203,MATCH(AI$11,'DEMAND BY DATE'!$A$4:$A$203,0),MATCH($C30,'DEMAND BY DATE'!$B$3:$AA$3,0)),"")) -> 2 | BD30: =INDEX('MC MASTER'!$B$3:$B$28,25) -> Bartack Pattern tacker (LABEL ATTACH ) | BE30: =IFERROR(INDEX('MC MAP'!$BX$5:$BX$30,MATCH($BD30,'MC MAP'!$BW$5:$BW$30,0)),"?") -> PATTERN-TACKER | BF30: =INDEX('MC MASTER'!$C$3:$C$28,25) -> 2 | BG30: =MAX(OFFSET('DEMAND BY DATE'!$B$4,$BB$2-1,MATCH($BD30,'DEMAND BY DATE'!$B$3:$AA$3,0)-1,$BB$3,1)) -> 0 | BH30: =$BF30-$BG30 -> 2 | BI30: {=SUMPRODUCT((OFFSET('DEMAND BY DATE'!$B$4,$BB$2-1,MATCH($BD30,'DEMAND BY DATE'!$B$3:$AA$3,0)-1,$BB$3,1)>$BF30)*(OFFSET('DEMAND BY DATE'!$BS$4,$BB$2-1,0,$BB$3,1)="Y"))} -> 0 | BJ30: {=SUMPRODUCT(($BE$6:$BE$31=$BE30)*($BH$6:$BH$31>0)*$BH$6:$BH$31)-MAX(0,$BH30)} -> 6 | BK30: =IF($BH30<0,MIN(-$BH30,MAX(0,$BJ30-$BN30)),0) -> 0 | BL30: =IF($BH30<0,-$BH30-$BK30,0) -> 0 | BM30: =$BH30+ROW()/100000 -> 2.0003 | BN30: {=SUMPRODUCT(($BE$6:$BE$31=$BE30)*($BH$6:$BH$31<0)*($BM$6:$BM$31<$BM30)*(-$BH$6:$BH$31))} -> 0 | BO30: =MAX(0,$BH30)-ROW()/100000 -> 1.9997
B31: =IFERROR(INDEX(WORKINGS!$B$116:$B$141,MATCH($C31,WORKINGS!$A$116:$A$141,0)),"") -> HT | C31: =INDEX(WORKINGS!$A$116:$A$141,MATCH(SMALL(WORKINGS!$D$116:$D$141,20),WORKINGS!$D$116:$D$141,0)) -> Heat Seal | D31: =IFERROR(INDEX($BF$6:$BF$31,MATCH($C31,$BD$6:$BD$31,0)),0) -> 35 | E31: =IF(E$11="","",IFERROR($D31-INDEX('DEMAND BY DATE'!$B$4:$AA$203,MATCH(E$11,'DEMAND BY DATE'!$A$4:$A$203,0),MATCH($C31,'DEMAND BY DATE'!$B$3:$AA$3,0)),"")) -> 4 | F31: =IF(F$11="","",IFERROR($D31-INDEX('DEMAND BY DATE'!$B$4:$AA$203,MATCH(F$11,'DEMAND BY DATE'!$A$4:$A$203,0),MATCH($C31,'DEMAND BY DATE'!$B$3:$AA$3,0)),"")) -> 4 | G31: =IF(G$11="","",IFERROR($D31-INDEX('DEMAND BY DATE'!$B$4:$AA$203,MATCH(G$11,'DEMAND BY DATE'!$A$4:$A$203,0),MATCH($C31,'DEMAND BY DATE'!$B$3:$AA$3,0)),"")) -> 4 | H31: =IF(H$11="","",IFERROR($D31-INDEX('DEMAND BY DATE'!$B$4:$AA$203,MATCH(H$11,'DEMAND BY DATE'!$A$4:$A$203,0),MATCH($C31,'DEMAND BY DATE'!$B$3:$AA$3,0)),"")) -> 4 | I31: =IF(I$11="","",IFERROR($D31-INDEX('DEMAND BY DATE'!$B$4:$AA$203,MATCH(I$11,'DEMAND BY DATE'!$A$4:$A$203,0),MATCH($C31,'DEMAND BY DATE'!$B$3:$AA$3,0)),"")) -> 4 | J31: =IF(J$11="","",IFERROR($D31-INDEX('DEMAND BY DATE'!$B$4:$AA$203,MATCH(J$11,'DEMAND BY DATE'!$A$4:$A$203,0),MATCH($C31,'DEMAND BY DATE'!$B$3:$AA$3,0)),"")) -> 4 | K31: =IF(K$11="","",IFERROR($D31-INDEX('DEMAND BY DATE'!$B$4:$AA$203,MATCH(K$11,'DEMAND BY DATE'!$A$4:$A$203,0),MATCH($C31,'DEMAND BY DATE'!$B$3:$AA$3,0)),"")) -> 4 | L31: =IF(L$11="","",IFERROR($D31-INDEX('DEMAND BY DATE'!$B$4:$AA$203,MATCH(L$11,'DEMAND BY DATE'!$A$4:$A$203,0),MATCH($C31,'DEMAND BY DATE'!$B$3:$AA$3,0)),"")) -> 4 | ... AI31: =IF(AI$11="","",IFERROR($D31-INDEX('DEMAND BY DATE'!$B$4:$AA$203,MATCH(AI$11,'DEMAND BY DATE'!$A$4:$A$203,0),MATCH($C31,'DEMAND BY DATE'!$B$3:$AA$3,0)),"")) -> 2.5 | BD31: =INDEX('MC MASTER'!$B$3:$B$28,26) -> Bartack Pattern tacker | BE31: =IFERROR(INDEX('MC MAP'!$BX$5:$BX$30,MATCH($BD31,'MC MAP'!$BW$5:$BW$30,0)),"?") -> PATTERN-TACKER | BF31: =INDEX('MC MASTER'!$C$3:$C$28,26) -> 35 | BG31: =MAX(OFFSET('DEMAND BY DATE'!$B$4,$BB$2-1,MATCH($BD31,'DEMAND BY DATE'!$B$3:$AA$3,0)-1,$BB$3,1)) -> 29 | BH31: =$BF31-$BG31 -> 6 | BI31: {=SUMPRODUCT((OFFSET('DEMAND BY DATE'!$B$4,$BB$2-1,MATCH($BD31,'DEMAND BY DATE'!$B$3:$AA$3,0)-1,$BB$3,1)>$BF31)*(OFFSET('DEMAND BY DATE'!$BS$4,$BB$2-1,0,$BB$3,1)="Y"))} -> 0 | BJ31: {=SUMPRODUCT(($BE$6:$BE$31=$BE31)*($BH$6:$BH$31>0)*$BH$6:$BH$31)-MAX(0,$BH31)} -> 2 | BK31: =IF($BH31<0,MIN(-$BH31,MAX(0,$BJ31-$BN31)),0) -> 0 | BL31: =IF($BH31<0,-$BH31-$BK31,0) -> 0 | BM31: =$BH31+ROW()/100000 -> 6.00031 | BN31: {=SUMPRODUCT(($BE$6:$BE$31=$BE31)*($BH$6:$BH$31<0)*($BM$6:$BM$31<$BM31)*(-$BH$6:$BH$31))} -> 0 | BO31: =MAX(0,$BH31)-ROW()/100000 -> 5.99969
B32: =IFERROR(INDEX(WORKINGS!$B$116:$B$141,MATCH($C32,WORKINGS!$A$116:$A$141,0)),"") -> ILET | C32: =INDEX(WORKINGS!$A$116:$A$141,MATCH(SMALL(WORKINGS!$D$116:$D$141,21),WORKINGS!$D$116:$D$141,0)) -> Snap button | D32: =IFERROR(INDEX($BF$6:$BF$31,MATCH($C32,$BD$6:$BD$31,0)),0) -> 2 | E32: =IF(E$11="","",IFERROR($D32-INDEX('DEMAND BY DATE'!$B$4:$AA$203,MATCH(E$11,'DEMAND BY DATE'!$A$4:$A$203,0),MATCH($C32,'DEMAND BY DATE'!$B$3:$AA$3,0)),"")) -> 0 | F32: =IF(F$11="","",IFERROR($D32-INDEX('DEMAND BY DATE'!$B$4:$AA$203,MATCH(F$11,'DEMAND BY DATE'!$A$4:$A$203,0),MATCH($C32,'DEMAND BY DATE'!$B$3:$AA$3,0)),"")) -> 0 | G32: =IF(G$11="","",IFERROR($D32-INDEX('DEMAND BY DATE'!$B$4:$AA$203,MATCH(G$11,'DEMAND BY DATE'!$A$4:$A$203,0),MATCH($C32,'DEMAND BY DATE'!$B$3:$AA$3,0)),"")) -> 0 | H32: =IF(H$11="","",IFERROR($D32-INDEX('DEMAND BY DATE'!$B$4:$AA$203,MATCH(H$11,'DEMAND BY DATE'!$A$4:$A$203,0),MATCH($C32,'DEMAND BY DATE'!$B$3:$AA$3,0)),"")) -> 0 | I32: =IF(I$11="","",IFERROR($D32-INDEX('DEMAND BY DATE'!$B$4:$AA$203,MATCH(I$11,'DEMAND BY DATE'!$A$4:$A$203,0),MATCH($C32,'DEMAND BY DATE'!$B$3:$AA$3,0)),"")) -> 0 | J32: =IF(J$11="","",IFERROR($D32-INDEX('DEMAND BY DATE'!$B$4:$AA$203,MATCH(J$11,'DEMAND BY DATE'!$A$4:$A$203,0),MATCH($C32,'DEMAND BY DATE'!$B$3:$AA$3,0)),"")) -> 0 | K32: =IF(K$11="","",IFERROR($D32-INDEX('DEMAND BY DATE'!$B$4:$AA$203,MATCH(K$11,'DEMAND BY DATE'!$A$4:$A$203,0),MATCH($C32,'DEMAND BY DATE'!$B$3:$AA$3,0)),"")) -> 0 | L32: =IF(L$11="","",IFERROR($D32-INDEX('DEMAND BY DATE'!$B$4:$AA$203,MATCH(L$11,'DEMAND BY DATE'!$A$4:$A$203,0),MATCH($C32,'DEMAND BY DATE'!$B$3:$AA$3,0)),"")) -> 0 | ... AI32: =IF(AI$11="","",IFERROR($D32-INDEX('DEMAND BY DATE'!$B$4:$AA$203,MATCH(AI$11,'DEMAND BY DATE'!$A$4:$A$203,0),MATCH($C32,'DEMAND BY DATE'!$B$3:$AA$3,0)),"")) -> 0
B33: =IFERROR(INDEX(WORKINGS!$B$116:$B$141,MATCH($C33,WORKINGS!$A$116:$A$141,0)),"") -> BH | C33: =INDEX(WORKINGS!$A$116:$A$141,MATCH(SMALL(WORKINGS!$D$116:$D$141,22),WORKINGS!$D$116:$D$141,0)) -> Button Hole | D33: =IFERROR(INDEX($BF$6:$BF$31,MATCH($C33,$BD$6:$BD$31,0)),0) -> 3 | E33: =IF(E$11="","",IFERROR($D33-INDEX('DEMAND BY DATE'!$B$4:$AA$203,MATCH(E$11,'DEMAND BY DATE'!$A$4:$A$203,0),MATCH($C33,'DEMAND BY DATE'!$B$3:$AA$3,0)),"")) -> 1 | F33: =IF(F$11="","",IFERROR($D33-INDEX('DEMAND BY DATE'!$B$4:$AA$203,MATCH(F$11,'DEMAND BY DATE'!$A$4:$A$203,0),MATCH($C33,'DEMAND BY DATE'!$B$3:$AA$3,0)),"")) -> 1 | G33: =IF(G$11="","",IFERROR($D33-INDEX('DEMAND BY DATE'!$B$4:$AA$203,MATCH(G$11,'DEMAND BY DATE'!$A$4:$A$203,0),MATCH($C33,'DEMAND BY DATE'!$B$3:$AA$3,0)),"")) -> 1 | H33: =IF(H$11="","",IFERROR($D33-INDEX('DEMAND BY DATE'!$B$4:$AA$203,MATCH(H$11,'DEMAND BY DATE'!$A$4:$A$203,0),MATCH($C33,'DEMAND BY DATE'!$B$3:$AA$3,0)),"")) -> 1 | I33: =IF(I$11="","",IFERROR($D33-INDEX('DEMAND BY DATE'!$B$4:$AA$203,MATCH(I$11,'DEMAND BY DATE'!$A$4:$A$203,0),MATCH($C33,'DEMAND BY DATE'!$B$3:$AA$3,0)),"")) -> 1 | J33: =IF(J$11="","",IFERROR($D33-INDEX('DEMAND BY DATE'!$B$4:$AA$203,MATCH(J$11,'DEMAND BY DATE'!$A$4:$A$203,0),MATCH($C33,'DEMAND BY DATE'!$B$3:$AA$3,0)),"")) -> 1 | K33: =IF(K$11="","",IFERROR($D33-INDEX('DEMAND BY DATE'!$B$4:$AA$203,MATCH(K$11,'DEMAND BY DATE'!$A$4:$A$203,0),MATCH($C33,'DEMAND BY DATE'!$B$3:$AA$3,0)),"")) -> 1 | L33: =IF(L$11="","",IFERROR($D33-INDEX('DEMAND BY DATE'!$B$4:$AA$203,MATCH(L$11,'DEMAND BY DATE'!$A$4:$A$203,0),MATCH($C33,'DEMAND BY DATE'!$B$3:$AA$3,0)),"")) -> 1 | ... AI33: =IF(AI$11="","",IFERROR($D33-INDEX('DEMAND BY DATE'!$B$4:$AA$203,MATCH(AI$11,'DEMAND BY DATE'!$A$4:$A$203,0),MATCH($C33,'DEMAND BY DATE'!$B$3:$AA$3,0)),"")) -> 1
B34: =IFERROR(INDEX(WORKINGS!$B$116:$B$141,MATCH($C34,WORKINGS!$A$116:$A$141,0)),"") -> BA | C34: =INDEX(WORKINGS!$A$116:$A$141,MATCH(SMALL(WORKINGS!$D$116:$D$141,23),WORKINGS!$D$116:$D$141,0)) -> Button Attach | D34: =IFERROR(INDEX($BF$6:$BF$31,MATCH($C34,$BD$6:$BD$31,0)),0) -> 1 | E34: =IF(E$11="","",IFERROR($D34-INDEX('DEMAND BY DATE'!$B$4:$AA$203,MATCH(E$11,'DEMAND BY DATE'!$A$4:$A$203,0),MATCH($C34,'DEMAND BY DATE'!$B$3:$AA$3,0)),"")) -> 1 | F34: =IF(F$11="","",IFERROR($D34-INDEX('DEMAND BY DATE'!$B$4:$AA$203,MATCH(F$11,'DEMAND BY DATE'!$A$4:$A$203,0),MATCH($C34,'DEMAND BY DATE'!$B$3:$AA$3,0)),"")) -> 1 | G34: =IF(G$11="","",IFERROR($D34-INDEX('DEMAND BY DATE'!$B$4:$AA$203,MATCH(G$11,'DEMAND BY DATE'!$A$4:$A$203,0),MATCH($C34,'DEMAND BY DATE'!$B$3:$AA$3,0)),"")) -> 1 | H34: =IF(H$11="","",IFERROR($D34-INDEX('DEMAND BY DATE'!$B$4:$AA$203,MATCH(H$11,'DEMAND BY DATE'!$A$4:$A$203,0),MATCH($C34,'DEMAND BY DATE'!$B$3:$AA$3,0)),"")) -> 1 | I34: =IF(I$11="","",IFERROR($D34-INDEX('DEMAND BY DATE'!$B$4:$AA$203,MATCH(I$11,'DEMAND BY DATE'!$A$4:$A$203,0),MATCH($C34,'DEMAND BY DATE'!$B$3:$AA$3,0)),"")) -> 1 | J34: =IF(J$11="","",IFERROR($D34-INDEX('DEMAND BY DATE'!$B$4:$AA$203,MATCH(J$11,'DEMAND BY DATE'!$A$4:$A$203,0),MATCH($C34,'DEMAND BY DATE'!$B$3:$AA$3,0)),"")) -> 1 | K34: =IF(K$11="","",IFERROR($D34-INDEX('DEMAND BY DATE'!$B$4:$AA$203,MATCH(K$11,'DEMAND BY DATE'!$A$4:$A$203,0),MATCH($C34,'DEMAND BY DATE'!$B$3:$AA$3,0)),"")) -> 1 | L34: =IF(L$11="","",IFERROR($D34-INDEX('DEMAND BY DATE'!$B$4:$AA$203,MATCH(L$11,'DEMAND BY DATE'!$A$4:$A$203,0),MATCH($C34,'DEMAND BY DATE'!$B$3:$AA$3,0)),"")) -> 1 | ... AI34: =IF(AI$11="","",IFERROR($D34-INDEX('DEMAND BY DATE'!$B$4:$AA$203,MATCH(AI$11,'DEMAND BY DATE'!$A$4:$A$203,0),MATCH($C34,'DEMAND BY DATE'!$B$3:$AA$3,0)),"")) -> 1
B35: =IFERROR(INDEX(WORKINGS!$B$116:$B$141,MATCH($C35,WORKINGS!$A$116:$A$141,0)),"") -> BTK | C35: =INDEX(WORKINGS!$A$116:$A$141,MATCH(SMALL(WORKINGS!$D$116:$D$141,24),WORKINGS!$D$116:$D$141,0)) -> Bartack | D35: =IFERROR(INDEX($BF$6:$BF$31,MATCH($C35,$BD$6:$BD$31,0)),0) -> 13 | E35: =IF(E$11="","",IFERROR($D35-INDEX('DEMAND BY DATE'!$B$4:$AA$203,MATCH(E$11,'DEMAND BY DATE'!$A$4:$A$203,0),MATCH($C35,'DEMAND BY DATE'!$B$3:$AA$3,0)),"")) -> 8.5 | F35: =IF(F$11="","",IFERROR($D35-INDEX('DEMAND BY DATE'!$B$4:$AA$203,MATCH(F$11,'DEMAND BY DATE'!$A$4:$A$203,0),MATCH($C35,'DEMAND BY DATE'!$B$3:$AA$3,0)),"")) -> 8.5 | G35: =IF(G$11="","",IFERROR($D35-INDEX('DEMAND BY DATE'!$B$4:$AA$203,MATCH(G$11,'DEMAND BY DATE'!$A$4:$A$203,0),MATCH($C35,'DEMAND BY DATE'!$B$3:$AA$3,0)),"")) -> 8.5 | H35: =IF(H$11="","",IFERROR($D35-INDEX('DEMAND BY DATE'!$B$4:$AA$203,MATCH(H$11,'DEMAND BY DATE'!$A$4:$A$203,0),MATCH($C35,'DEMAND BY DATE'!$B$3:$AA$3,0)),"")) -> 8.5 | I35: =IF(I$11="","",IFERROR($D35-INDEX('DEMAND BY DATE'!$B$4:$AA$203,MATCH(I$11,'DEMAND BY DATE'!$A$4:$A$203,0),MATCH($C35,'DEMAND BY DATE'!$B$3:$AA$3,0)),"")) -> 8.5 | J35: =IF(J$11="","",IFERROR($D35-INDEX('DEMAND BY DATE'!$B$4:$AA$203,MATCH(J$11,'DEMAND BY DATE'!$A$4:$A$203,0),MATCH($C35,'DEMAND BY DATE'!$B$3:$AA$3,0)),"")) -> 8.5 | K35: =IF(K$11="","",IFERROR($D35-INDEX('DEMAND BY DATE'!$B$4:$AA$203,MATCH(K$11,'DEMAND BY DATE'!$A$4:$A$203,0),MATCH($C35,'DEMAND BY DATE'!$B$3:$AA$3,0)),"")) -> 8.5 | L35: =IF(L$11="","",IFERROR($D35-INDEX('DEMAND BY DATE'!$B$4:$AA$203,MATCH(L$11,'DEMAND BY DATE'!$A$4:$A$203,0),MATCH($C35,'DEMAND BY DATE'!$B$3:$AA$3,0)),"")) -> 8.5 | ... AI35: =IF(AI$11="","",IFERROR($D35-INDEX('DEMAND BY DATE'!$B$4:$AA$203,MATCH(AI$11,'DEMAND BY DATE'!$A$4:$A$203,0),MATCH($C35,'DEMAND BY DATE'!$B$3:$AA$3,0)),"")) -> 5.5
B36: =IFERROR(INDEX(WORKINGS!$B$116:$B$141,MATCH($C36,WORKINGS!$A$116:$A$141,0)),"") -> PATTERN-TACKER | C36: =INDEX(WORKINGS!$A$116:$A$141,MATCH(SMALL(WORKINGS!$D$116:$D$141,25),WORKINGS!$D$116:$D$141,0)) -> Bartack Pattern tacker (LABEL ATTACH ) | D36: =IFERROR(INDEX($BF$6:$BF$31,MATCH($C36,$BD$6:$BD$31,0)),0) -> 2 | E36: =IF(E$11="","",IFERROR($D36-INDEX('DEMAND BY DATE'!$B$4:$AA$203,MATCH(E$11,'DEMAND BY DATE'!$A$4:$A$203,0),MATCH($C36,'DEMAND BY DATE'!$B$3:$AA$3,0)),"")) -> 2 | F36: =IF(F$11="","",IFERROR($D36-INDEX('DEMAND BY DATE'!$B$4:$AA$203,MATCH(F$11,'DEMAND BY DATE'!$A$4:$A$203,0),MATCH($C36,'DEMAND BY DATE'!$B$3:$AA$3,0)),"")) -> 2 | G36: =IF(G$11="","",IFERROR($D36-INDEX('DEMAND BY DATE'!$B$4:$AA$203,MATCH(G$11,'DEMAND BY DATE'!$A$4:$A$203,0),MATCH($C36,'DEMAND BY DATE'!$B$3:$AA$3,0)),"")) -> 2 | H36: =IF(H$11="","",IFERROR($D36-INDEX('DEMAND BY DATE'!$B$4:$AA$203,MATCH(H$11,'DEMAND BY DATE'!$A$4:$A$203,0),MATCH($C36,'DEMAND BY DATE'!$B$3:$AA$3,0)),"")) -> 2 | I36: =IF(I$11="","",IFERROR($D36-INDEX('DEMAND BY DATE'!$B$4:$AA$203,MATCH(I$11,'DEMAND BY DATE'!$A$4:$A$203,0),MATCH($C36,'DEMAND BY DATE'!$B$3:$AA$3,0)),"")) -> 2 | J36: =IF(J$11="","",IFERROR($D36-INDEX('DEMAND BY DATE'!$B$4:$AA$203,MATCH(J$11,'DEMAND BY DATE'!$A$4:$A$203,0),MATCH($C36,'DEMAND BY DATE'!$B$3:$AA$3,0)),"")) -> 2 | K36: =IF(K$11="","",IFERROR($D36-INDEX('DEMAND BY DATE'!$B$4:$AA$203,MATCH(K$11,'DEMAND BY DATE'!$A$4:$A$203,0),MATCH($C36,'DEMAND BY DATE'!$B$3:$AA$3,0)),"")) -> 2 | L36: =IF(L$11="","",IFERROR($D36-INDEX('DEMAND BY DATE'!$B$4:$AA$203,MATCH(L$11,'DEMAND BY DATE'!$A$4:$A$203,0),MATCH($C36,'DEMAND BY DATE'!$B$3:$AA$3,0)),"")) -> 2 | ... AI36: =IF(AI$11="","",IFERROR($D36-INDEX('DEMAND BY DATE'!$B$4:$AA$203,MATCH(AI$11,'DEMAND BY DATE'!$A$4:$A$203,0),MATCH($C36,'DEMAND BY DATE'!$B$3:$AA$3,0)),"")) -> 2
B37: =IFERROR(INDEX(WORKINGS!$B$116:$B$141,MATCH($C37,WORKINGS!$A$116:$A$141,0)),"") -> PATTERN-TACKER | C37: =INDEX(WORKINGS!$A$116:$A$141,MATCH(SMALL(WORKINGS!$D$116:$D$141,26),WORKINGS!$D$116:$D$141,0)) -> Bartack Pattern tacker | D37: =IFERROR(INDEX($BF$6:$BF$31,MATCH($C37,$BD$6:$BD$31,0)),0) -> 35 | E37: =IF(E$11="","",IFERROR($D37-INDEX('DEMAND BY DATE'!$B$4:$AA$203,MATCH(E$11,'DEMAND BY DATE'!$A$4:$A$203,0),MATCH($C37,'DEMAND BY DATE'!$B$3:$AA$3,0)),"")) -> 6 | F37: =IF(F$11="","",IFERROR($D37-INDEX('DEMAND BY DATE'!$B$4:$AA$203,MATCH(F$11,'DEMAND BY DATE'!$A$4:$A$203,0),MATCH($C37,'DEMAND BY DATE'!$B$3:$AA$3,0)),"")) -> 6 | G37: =IF(G$11="","",IFERROR($D37-INDEX('DEMAND BY DATE'!$B$4:$AA$203,MATCH(G$11,'DEMAND BY DATE'!$A$4:$A$203,0),MATCH($C37,'DEMAND BY DATE'!$B$3:$AA$3,0)),"")) -> 6 | H37: =IF(H$11="","",IFERROR($D37-INDEX('DEMAND BY DATE'!$B$4:$AA$203,MATCH(H$11,'DEMAND BY DATE'!$A$4:$A$203,0),MATCH($C37,'DEMAND BY DATE'!$B$3:$AA$3,0)),"")) -> 6 | I37: =IF(I$11="","",IFERROR($D37-INDEX('DEMAND BY DATE'!$B$4:$AA$203,MATCH(I$11,'DEMAND BY DATE'!$A$4:$A$203,0),MATCH($C37,'DEMAND BY DATE'!$B$3:$AA$3,0)),"")) -> 6 | J37: =IF(J$11="","",IFERROR($D37-INDEX('DEMAND BY DATE'!$B$4:$AA$203,MATCH(J$11,'DEMAND BY DATE'!$A$4:$A$203,0),MATCH($C37,'DEMAND BY DATE'!$B$3:$AA$3,0)),"")) -> 6 | K37: =IF(K$11="","",IFERROR($D37-INDEX('DEMAND BY DATE'!$B$4:$AA$203,MATCH(K$11,'DEMAND BY DATE'!$A$4:$A$203,0),MATCH($C37,'DEMAND BY DATE'!$B$3:$AA$3,0)),"")) -> 6 | L37: =IF(L$11="","",IFERROR($D37-INDEX('DEMAND BY DATE'!$B$4:$AA$203,MATCH(L$11,'DEMAND BY DATE'!$A$4:$A$203,0),MATCH($C37,'DEMAND BY DATE'!$B$3:$AA$3,0)),"")) -> 6 | ... AI37: =IF(AI$11="","",IFERROR($D37-INDEX('DEMAND BY DATE'!$B$4:$AA$203,MATCH(AI$11,'DEMAND BY DATE'!$A$4:$A$203,0),MATCH($C37,'DEMAND BY DATE'!$B$3:$AA$3,0)),"")) -> 10
B38: TOTAL MACHINES NEEDED (all machines) | D38: ='MC MASTER'!$C$29 -> 920 | E38: =IF(E$11="","",INDEX('DEMAND BY DATE'!$AB$4:$AB$203,MATCH(E$11,'DEMAND BY DATE'!$A$4:$A$203,0))) -> 808 | F38: =IF(F$11="","",INDEX('DEMAND BY DATE'!$AB$4:$AB$203,MATCH(F$11,'DEMAND BY DATE'!$A$4:$A$203,0))) -> 808 | G38: =IF(G$11="","",INDEX('DEMAND BY DATE'!$AB$4:$AB$203,MATCH(G$11,'DEMAND BY DATE'!$A$4:$A$203,0))) -> 808 | H38: =IF(H$11="","",INDEX('DEMAND BY DATE'!$AB$4:$AB$203,MATCH(H$11,'DEMAND BY DATE'!$A$4:$A$203,0))) -> 808 | I38: =IF(I$11="","",INDEX('DEMAND BY DATE'!$AB$4:$AB$203,MATCH(I$11,'DEMAND BY DATE'!$A$4:$A$203,0))) -> 808 | J38: =IF(J$11="","",INDEX('DEMAND BY DATE'!$AB$4:$AB$203,MATCH(J$11,'DEMAND BY DATE'!$A$4:$A$203,0))) -> 808 | K38: =IF(K$11="","",INDEX('DEMAND BY DATE'!$AB$4:$AB$203,MATCH(K$11,'DEMAND BY DATE'!$A$4:$A$203,0))) -> 808 | L38: =IF(L$11="","",INDEX('DEMAND BY DATE'!$AB$4:$AB$203,MATCH(L$11,'DEMAND BY DATE'!$A$4:$A$203,0))) -> 808 | ... AI38: =IF(AI$11="","",INDEX('DEMAND BY DATE'!$AB$4:$AB$203,MATCH(AI$11,'DEMAND BY DATE'!$A$4:$A$203,0))) -> 801
B39: Machine types over capacity | E39: =IF(E$11="","",IFERROR(INDEX('DEMAND BY DATE'!$AX$4:$AX$203,MATCH(E$11,'DEMAND BY DATE'!$A$4:$A$203,0)),"")) -> 5 | F39: =IF(F$11="","",IFERROR(INDEX('DEMAND BY DATE'!$AX$4:$AX$203,MATCH(F$11,'DEMAND BY DATE'!$A$4:$A$203,0)),"")) -> 0 | G39: =IF(G$11="","",IFERROR(INDEX('DEMAND BY DATE'!$AX$4:$AX$203,MATCH(G$11,'DEMAND BY DATE'!$A$4:$A$203,0)),"")) -> 5 | H39: =IF(H$11="","",IFERROR(INDEX('DEMAND BY DATE'!$AX$4:$AX$203,MATCH(H$11,'DEMAND BY DATE'!$A$4:$A$203,0)),"")) -> 5 | I39: =IF(I$11="","",IFERROR(INDEX('DEMAND BY DATE'!$AX$4:$AX$203,MATCH(I$11,'DEMAND BY DATE'!$A$4:$A$203,0)),"")) -> 5 | J39: =IF(J$11="","",IFERROR(INDEX('DEMAND BY DATE'!$AX$4:$AX$203,MATCH(J$11,'DEMAND BY DATE'!$A$4:$A$203,0)),"")) -> 5 | K39: =IF(K$11="","",IFERROR(INDEX('DEMAND BY DATE'!$AX$4:$AX$203,MATCH(K$11,'DEMAND BY DATE'!$A$4:$A$203,0)),"")) -> 5 | L39: =IF(L$11="","",IFERROR(INDEX('DEMAND BY DATE'!$AX$4:$AX$203,MATCH(L$11,'DEMAND BY DATE'!$A$4:$A$203,0)),"")) -> 5 | ... AI39: =IF(AI$11="","",IFERROR(INDEX('DEMAND BY DATE'!$AX$4:$AX$203,MATCH(AI$11,'DEMAND BY DATE'!$A$4:$A$203,0)),"")) -> 4
B40: Working day? | E40: =IF(E$11="","",IFERROR(INDEX('DEMAND BY DATE'!$BS$4:$BS$203,MATCH(E$11,'DEMAND BY DATE'!$A$4:$A$203,0)),"")) -> Y | F40: =IF(F$11="","",IFERROR(INDEX('DEMAND BY DATE'!$BS$4:$BS$203,MATCH(F$11,'DEMAND BY DATE'!$A$4:$A$203,0)),"")) -> N | G40: =IF(G$11="","",IFERROR(INDEX('DEMAND BY DATE'!$BS$4:$BS$203,MATCH(G$11,'DEMAND BY DATE'!$A$4:$A$203,0)),"")) -> Y | H40: =IF(H$11="","",IFERROR(INDEX('DEMAND BY DATE'!$BS$4:$BS$203,MATCH(H$11,'DEMAND BY DATE'!$A$4:$A$203,0)),"")) -> Y | I40: =IF(I$11="","",IFERROR(INDEX('DEMAND BY DATE'!$BS$4:$BS$203,MATCH(I$11,'DEMAND BY DATE'!$A$4:$A$203,0)),"")) -> Y | J40: =IF(J$11="","",IFERROR(INDEX('DEMAND BY DATE'!$BS$4:$BS$203,MATCH(J$11,'DEMAND BY DATE'!$A$4:$A$203,0)),"")) -> Y | K40: =IF(K$11="","",IFERROR(INDEX('DEMAND BY DATE'!$BS$4:$BS$203,MATCH(K$11,'DEMAND BY DATE'!$A$4:$A$203,0)),"")) -> Y | L40: =IF(L$11="","",IFERROR(INDEX('DEMAND BY DATE'!$BS$4:$BS$203,MATCH(L$11,'DEMAND BY DATE'!$A$4:$A$203,0)),"")) -> Y | ... AI40: =IF(AI$11="","",IFERROR(INDEX('DEMAND BY DATE'!$BS$4:$BS$203,MATCH(AI$11,'DEMAND BY DATE'!$A$4:$A$203,0)),"")) -> Y
B43: ="ACTION LIST FOR "&UPPER($D$4)&" — move first, buy only what cannot be covered" -> ACTION LIST FOR AUGUST 2026 — move first, buy only what cannot be covered
B44: Machine group | C44: Family | D44: Own | E44: Need | F44: Short | G44: Days | H44: Move | I44: Buy | J44: DECISION
B45: =IFERROR(IF(SMALL($BM$6:$BM$31,1)>=0,"",INDEX($BD$6:$BD$31,MATCH(SMALL($BM$6:$BM$31,1),$BM$6:$BM$31,0))),"") -> 4th Overlock | C45: =IF($B45="","",INDEX($BE$6:$BE$31,MATCH($B45,$BD$6:$BD$31,0))) -> OVER-LOCK | D45: =IF($B45="","",INDEX($BF$6:$BF$31,MATCH($B45,$BD$6:$BD$31,0))) -> 279 | E45: =IF($B45="","",INDEX($BG$6:$BG$31,MATCH($B45,$BD$6:$BD$31,0))) -> 291 | F45: =IF($B45="","",$E45-$D45) -> 12 | G45: =IF($B45="","",INDEX($BI$6:$BI$31,MATCH($B45,$BD$6:$BD$31,0))) -> 11 | H45: =IF($B45="","",INDEX($BK$6:$BK$31,MATCH($B45,$BD$6:$BD$31,0))) -> 5 | I45: =IF($B45="","",INDEX($BL$6:$BL$31,MATCH($B45,$BD$6:$BD$31,0))) -> 7 | J45: =IF($B45="","",IF($H45>0,"MOVE "&TEXT($H45,"#,##0.0")&" from "&$C45&" family"&IF($I45>0,", then BUY "&TEXT($I45,"#,##0.0"),""),"BUY / HIRE "&TEXT($I45,"#,##0.0")&" — no spare in "&$C45)) -> MOVE 5.0 from OVER-LOCK family, then BUY 7.0
B46: =IFERROR(IF(SMALL($BM$6:$BM$31,2)>=0,"",INDEX($BD$6:$BD$31,MATCH(SMALL($BM$6:$BM$31,2),$BM$6:$BM$31,0))),"") -> F/L (Coverseam ) | C46: =IF($B46="","",INDEX($BE$6:$BE$31,MATCH($B46,$BD$6:$BD$31,0))) -> FLAT-LOCK | D46: =IF($B46="","",INDEX($BF$6:$BF$31,MATCH($B46,$BD$6:$BD$31,0))) -> 6 | E46: =IF($B46="","",INDEX($BG$6:$BG$31,MATCH($B46,$BD$6:$BD$31,0))) -> 17 | F46: =IF($B46="","",$E46-$D46) -> 11 | G46: =IF($B46="","",INDEX($BI$6:$BI$31,MATCH($B46,$BD$6:$BD$31,0))) -> 26 | H46: =IF($B46="","",INDEX($BK$6:$BK$31,MATCH($B46,$BD$6:$BD$31,0))) -> 11 | I46: =IF($B46="","",INDEX($BL$6:$BL$31,MATCH($B46,$BD$6:$BD$31,0))) -> 0 | J46: =IF($B46="","",IF($H46>0,"MOVE "&TEXT($H46,"#,##0.0")&" from "&$C46&" family"&IF($I46>0,", then BUY "&TEXT($I46,"#,##0.0"),""),"BUY / HIRE "&TEXT($I46,"#,##0.0")&" — no spare in "&$C46)) -> MOVE 11.0 from FLAT-LOCK family
B47: =IFERROR(IF(SMALL($BM$6:$BM$31,3)>=0,"",INDEX($BD$6:$BD$31,MATCH(SMALL($BM$6:$BM$31,3),$BM$6:$BM$31,0))),"") -> 3N5T-F/L -( TopStitch) | C47: =IF($B47="","",INDEX($BE$6:$BE$31,MATCH($B47,$BD$6:$BD$31,0))) -> FLAT-LOCK | D47: =IF($B47="","",INDEX($BF$6:$BF$31,MATCH($B47,$BD$6:$BD$31,0))) -> 54 | E47: =IF($B47="","",INDEX($BG$6:$BG$31,MATCH($B47,$BD$6:$BD$31,0))) -> 63 | F47: =IF($B47="","",$E47-$D47) -> 9 | G47: =IF($B47="","",INDEX($BI$6:$BI$31,MATCH($B47,$BD$6:$BD$31,0))) -> 14 | H47: =IF($B47="","",INDEX($BK$6:$BK$31,MATCH($B47,$BD$6:$BD$31,0))) -> 2.5 | I47: =IF($B47="","",INDEX($BL$6:$BL$31,MATCH($B47,$BD$6:$BD$31,0))) -> 6.5 | J47: =IF($B47="","",IF($H47>0,"MOVE "&TEXT($H47,"#,##0.0")&" from "&$C47&" family"&IF($I47>0,", then BUY "&TEXT($I47,"#,##0.0"),""),"BUY / HIRE "&TEXT($I47,"#,##0.0")&" — no spare in "&$C47)) -> MOVE 2.5 from FLAT-LOCK family, then BUY 6.5
B48: =IFERROR(IF(SMALL($BM$6:$BM$31,4)>=0,"",INDEX($BD$6:$BD$31,MATCH(SMALL($BM$6:$BM$31,4),$BM$6:$BM$31,0))),"") -> Overlock (Ring Elastic Attach) | C48: =IF($B48="","",INDEX($BE$6:$BE$31,MATCH($B48,$BD$6:$BD$31,0))) -> OVER-LOCK | D48: =IF($B48="","",INDEX($BF$6:$BF$31,MATCH($B48,$BD$6:$BD$31,0))) -> 29 | E48: =IF($B48="","",INDEX($BG$6:$BG$31,MATCH($B48,$BD$6:$BD$31,0))) -> 36 | F48: =IF($B48="","",$E48-$D48) -> 7 | G48: =IF($B48="","",INDEX($BI$6:$BI$31,MATCH($B48,$BD$6:$BD$31,0))) -> 26 | H48: =IF($B48="","",INDEX($BK$6:$BK$31,MATCH($B48,$BD$6:$BD$31,0))) -> 0 | I48: =IF($B48="","",INDEX($BL$6:$BL$31,MATCH($B48,$BD$6:$BD$31,0))) -> 7 | J48: =IF($B48="","",IF($H48>0,"MOVE "&TEXT($H48,"#,##0.0")&" from "&$C48&" family"&IF($I48>0,", then BUY "&TEXT($I48,"#,##0.0"),""),"BUY / HIRE "&TEXT($I48,"#,##0.0")&" — no spare in "&$C48)) -> BUY / HIRE 7.0 — no spare in OVER-LOCK
B49: =IFERROR(IF(SMALL($BM$6:$BM$31,5)>=0,"",INDEX($BD$6:$BD$31,MATCH(SMALL($BM$6:$BM$31,5),$BM$6:$BM$31,0))),"") -> F/L (Coverseam )with pullar | C49: =IF($B49="","",INDEX($BE$6:$BE$31,MATCH($B49,$BD$6:$BD$31,0))) -> FLAT-LOCK | D49: =IF($B49="","",INDEX($BF$6:$BF$31,MATCH($B49,$BD$6:$BD$31,0))) -> 37 | E49: =IF($B49="","",INDEX($BG$6:$BG$31,MATCH($B49,$BD$6:$BD$31,0))) -> 43.5 | F49: =IF($B49="","",$E49-$D49) -> 6.5 | G49: =IF($B49="","",INDEX($BI$6:$BI$31,MATCH($B49,$BD$6:$BD$31,0))) -> 25 | H49: =IF($B49="","",INDEX($BK$6:$BK$31,MATCH($B49,$BD$6:$BD$31,0))) -> 0 | I49: =IF($B49="","",INDEX($BL$6:$BL$31,MATCH($B49,$BD$6:$BD$31,0))) -> 6.5 | J49: =IF($B49="","",IF($H49>0,"MOVE "&TEXT($H49,"#,##0.0")&" from "&$C49&" family"&IF($I49>0,", then BUY "&TEXT($I49,"#,##0.0"),""),"BUY / HIRE "&TEXT($I49,"#,##0.0")&" — no spare in "&$C49)) -> BUY / HIRE 6.5 — no spare in FLAT-LOCK
B50: =IFERROR(IF(SMALL($BM$6:$BM$31,6)>=0,"",INDEX($BD$6:$BD$31,MATCH(SMALL($BM$6:$BM$31,6),$BM$6:$BM$31,0))),"") -> 3th Overlock (Leg elastic) | C50: =IF($B50="","",INDEX($BE$6:$BE$31,MATCH($B50,$BD$6:$BD$31,0))) -> OVER-LOCK | D50: =IF($B50="","",INDEX($BF$6:$BF$31,MATCH($B50,$BD$6:$BD$31,0))) -> 30 | E50: =IF($B50="","",INDEX($BG$6:$BG$31,MATCH($B50,$BD$6:$BD$31,0))) -> 31 | F50: =IF($B50="","",$E50-$D50) -> 1 | G50: =IF($B50="","",INDEX($BI$6:$BI$31,MATCH($B50,$BD$6:$BD$31,0))) -> 11 | H50: =IF($B50="","",INDEX($BK$6:$BK$31,MATCH($B50,$BD$6:$BD$31,0))) -> 0 | I50: =IF($B50="","",INDEX($BL$6:$BL$31,MATCH($B50,$BD$6:$BD$31,0))) -> 1 | J50: =IF($B50="","",IF($H50>0,"MOVE "&TEXT($H50,"#,##0.0")&" from "&$C50&" family"&IF($I50>0,", then BUY "&TEXT($I50,"#,##0.0"),""),"BUY / HIRE "&TEXT($I50,"#,##0.0")&" — no spare in "&$C50)) -> BUY / HIRE 1.0 — no spare in OVER-LOCK
B51: =IFERROR(IF(SMALL($BM$6:$BM$31,7)>=0,"",INDEX($BD$6:$BD$31,MATCH(SMALL($BM$6:$BM$31,7),$BM$6:$BM$31,0))),"") | C51: =IF($B51="","",INDEX($BE$6:$BE$31,MATCH($B51,$BD$6:$BD$31,0))) | D51: =IF($B51="","",INDEX($BF$6:$BF$31,MATCH($B51,$BD$6:$BD$31,0))) | E51: =IF($B51="","",INDEX($BG$6:$BG$31,MATCH($B51,$BD$6:$BD$31,0))) | F51: =IF($B51="","",$E51-$D51) | G51: =IF($B51="","",INDEX($BI$6:$BI$31,MATCH($B51,$BD$6:$BD$31,0))) | H51: =IF($B51="","",INDEX($BK$6:$BK$31,MATCH($B51,$BD$6:$BD$31,0))) | I51: =IF($B51="","",INDEX($BL$6:$BL$31,MATCH($B51,$BD$6:$BD$31,0))) | J51: =IF($B51="","",IF($H51>0,"MOVE "&TEXT($H51,"#,##0.0")&" from "&$C51&" family"&IF($I51>0,", then BUY "&TEXT($I51,"#,##0.0"),""),"BUY / HIRE "&TEXT($I51,"#,##0.0")&" — no spare in "&$C51))
B52: =IFERROR(IF(SMALL($BM$6:$BM$31,8)>=0,"",INDEX($BD$6:$BD$31,MATCH(SMALL($BM$6:$BM$31,8),$BM$6:$BM$31,0))),"") | C52: =IF($B52="","",INDEX($BE$6:$BE$31,MATCH($B52,$BD$6:$BD$31,0))) | D52: =IF($B52="","",INDEX($BF$6:$BF$31,MATCH($B52,$BD$6:$BD$31,0))) | E52: =IF($B52="","",INDEX($BG$6:$BG$31,MATCH($B52,$BD$6:$BD$31,0))) | F52: =IF($B52="","",$E52-$D52) | G52: =IF($B52="","",INDEX($BI$6:$BI$31,MATCH($B52,$BD$6:$BD$31,0))) | H52: =IF($B52="","",INDEX($BK$6:$BK$31,MATCH($B52,$BD$6:$BD$31,0))) | I52: =IF($B52="","",INDEX($BL$6:$BL$31,MATCH($B52,$BD$6:$BD$31,0))) | J52: =IF($B52="","",IF($H52>0,"MOVE "&TEXT($H52,"#,##0.0")&" from "&$C52&" family"&IF($I52>0,", then BUY "&TEXT($I52,"#,##0.0"),""),"BUY / HIRE "&TEXT($I52,"#,##0.0")&" — no spare in "&$C52))
B53: =IFERROR(IF(SMALL($BM$6:$BM$31,9)>=0,"",INDEX($BD$6:$BD$31,MATCH(SMALL($BM$6:$BM$31,9),$BM$6:$BM$31,0))),"") | C53: =IF($B53="","",INDEX($BE$6:$BE$31,MATCH($B53,$BD$6:$BD$31,0))) | D53: =IF($B53="","",INDEX($BF$6:$BF$31,MATCH($B53,$BD$6:$BD$31,0))) | E53: =IF($B53="","",INDEX($BG$6:$BG$31,MATCH($B53,$BD$6:$BD$31,0))) | F53: =IF($B53="","",$E53-$D53) | G53: =IF($B53="","",INDEX($BI$6:$BI$31,MATCH($B53,$BD$6:$BD$31,0))) | H53: =IF($B53="","",INDEX($BK$6:$BK$31,MATCH($B53,$BD$6:$BD$31,0))) | I53: =IF($B53="","",INDEX($BL$6:$BL$31,MATCH($B53,$BD$6:$BD$31,0))) | J53: =IF($B53="","",IF($H53>0,"MOVE "&TEXT($H53,"#,##0.0")&" from "&$C53&" family"&IF($I53>0,", then BUY "&TEXT($I53,"#,##0.0"),""),"BUY / HIRE "&TEXT($I53,"#,##0.0")&" — no spare in "&$C53))
B54: =IFERROR(IF(SMALL($BM$6:$BM$31,10)>=0,"",INDEX($BD$6:$BD$31,MATCH(SMALL($BM$6:$BM$31,10),$BM$6:$BM$31,0))),"") | C54: =IF($B54="","",INDEX($BE$6:$BE$31,MATCH($B54,$BD$6:$BD$31,0))) | D54: =IF($B54="","",INDEX($BF$6:$BF$31,MATCH($B54,$BD$6:$BD$31,0))) | E54: =IF($B54="","",INDEX($BG$6:$BG$31,MATCH($B54,$BD$6:$BD$31,0))) | F54: =IF($B54="","",$E54-$D54) | G54: =IF($B54="","",INDEX($BI$6:$BI$31,MATCH($B54,$BD$6:$BD$31,0))) | H54: =IF($B54="","",INDEX($BK$6:$BK$31,MATCH($B54,$BD$6:$BD$31,0))) | I54: =IF($B54="","",INDEX($BL$6:$BL$31,MATCH($B54,$BD$6:$BD$31,0))) | J54: =IF($B54="","",IF($H54>0,"MOVE "&TEXT($H54,"#,##0.0")&" from "&$C54&" family"&IF($I54>0,", then BUY "&TEXT($I54,"#,##0.0"),""),"BUY / HIRE "&TEXT($I54,"#,##0.0")&" — no spare in "&$C54))
B57: ="IDLE & SPARE MACHINES — "&UPPER($D$4) -> IDLE & SPARE MACHINES — AUGUST 2026
B58: Machine group | C58: Family | D58: Own | E58: Used | F58: SPARE | H58: Status | J58: Can it help a shortage?
B59: =IFERROR(IF(LARGE($BO$6:$BO$31,1)<=0,"",INDEX($BD$6:$BD$31,MATCH(LARGE($BO$6:$BO$31,1),$BO$6:$BO$31,0))),"") -> SNLS | C59: =IF($B59="","",INDEX($BE$6:$BE$31,MATCH($B59,$BD$6:$BD$31,0))) -> LOCK-STITCH | D59: =IF($B59="","",INDEX($BF$6:$BF$31,MATCH($B59,$BD$6:$BD$31,0))) -> 185 | E59: =IF($B59="","",INDEX($BG$6:$BG$31,MATCH($B59,$BD$6:$BD$31,0))) -> 152 | F59: =IF($B59="","",$D59-$E59) -> 33 | H59: =IF($B59="","",IF($E59=0,"NEVER USED","PART USED")) -> PART USED | J59: {=IF($B59="","",IF(SUMPRODUCT(($BE$6:$BE$31=$C59)*($BH$6:$BH$31<0))>0,"YES — "&$C59&" family has a shortage","no — nothing short in "&$C59))} -> no — nothing short in LOCK-STITCH
B60: =IFERROR(IF(LARGE($BO$6:$BO$31,2)<=0,"",INDEX($BD$6:$BD$31,MATCH(LARGE($BO$6:$BO$31,2),$BO$6:$BO$31,0))),"") -> 3N5T-F/L -BINDING | C60: =IF($B60="","",INDEX($BE$6:$BE$31,MATCH($B60,$BD$6:$BD$31,0))) -> BINDING | D60: =IF($B60="","",INDEX($BF$6:$BF$31,MATCH($B60,$BD$6:$BD$31,0))) -> 58 | E60: =IF($B60="","",INDEX($BG$6:$BG$31,MATCH($B60,$BD$6:$BD$31,0))) -> 42 | F60: =IF($B60="","",$D60-$E60) -> 16 | H60: =IF($B60="","",IF($E60=0,"NEVER USED","PART USED")) -> PART USED | J60: {=IF($B60="","",IF(SUMPRODUCT(($BE$6:$BE$31=$C60)*($BH$6:$BH$31<0))>0,"YES — "&$C60&" family has a shortage","no — nothing short in "&$C60))} -> no — nothing short in BINDING
B61: =IFERROR(IF(LARGE($BO$6:$BO$31,3)<=0,"",INDEX($BD$6:$BD$31,MATCH(LARGE($BO$6:$BO$31,3),$BO$6:$BO$31,0))),"") -> FlatSeamer FS | C61: =IF($B61="","",INDEX($BE$6:$BE$31,MATCH($B61,$BD$6:$BD$31,0))) -> FS | D61: =IF($B61="","",INDEX($BF$6:$BF$31,MATCH($B61,$BD$6:$BD$31,0))) -> 8 | E61: =IF($B61="","",INDEX($BG$6:$BG$31,MATCH($B61,$BD$6:$BD$31,0))) -> 0 | F61: =IF($B61="","",$D61-$E61) -> 8 | H61: =IF($B61="","",IF($E61=0,"NEVER USED","PART USED")) -> NEVER USED | J61: {=IF($B61="","",IF(SUMPRODUCT(($BE$6:$BE$31=$C61)*($BH$6:$BH$31<0))>0,"YES — "&$C61&" family has a shortage","no — nothing short in "&$C61))} -> no — nothing short in FS
B62: =IFERROR(IF(LARGE($BO$6:$BO$31,4)<=0,"",INDEX($BD$6:$BD$31,MATCH(LARGE($BO$6:$BO$31,4),$BO$6:$BO$31,0))),"") -> Flatlock (Ring Elastic Attach) | C62: =IF($B62="","",INDEX($BE$6:$BE$31,MATCH($B62,$BD$6:$BD$31,0))) -> OUTER ELASTIC | D62: =IF($B62="","",INDEX($BF$6:$BF$31,MATCH($B62,$BD$6:$BD$31,0))) -> 42 | E62: =IF($B62="","",INDEX($BG$6:$BG$31,MATCH($B62,$BD$6:$BD$31,0))) -> 34.5 | F62: =IF($B62="","",$D62-$E62) -> 7.5 | H62: =IF($B62="","",IF($E62=0,"NEVER USED","PART USED")) -> PART USED | J62: {=IF($B62="","",IF(SUMPRODUCT(($BE$6:$BE$31=$C62)*($BH$6:$BH$31<0))>0,"YES — "&$C62&" family has a shortage","no — nothing short in "&$C62))} -> no — nothing short in OUTER ELASTIC
B63: =IFERROR(IF(LARGE($BO$6:$BO$31,5)<=0,"",INDEX($BD$6:$BD$31,MATCH(LARGE($BO$6:$BO$31,5),$BO$6:$BO$31,0))),"") -> DNLS | C63: =IF($B63="","",INDEX($BE$6:$BE$31,MATCH($B63,$BD$6:$BD$31,0))) -> LOCK-STITCH | D63: =IF($B63="","",INDEX($BF$6:$BF$31,MATCH($B63,$BD$6:$BD$31,0))) -> 8 | E63: =IF($B63="","",INDEX($BG$6:$BG$31,MATCH($B63,$BD$6:$BD$31,0))) -> 1 | F63: =IF($B63="","",$D63-$E63) -> 7 | H63: =IF($B63="","",IF($E63=0,"NEVER USED","PART USED")) -> PART USED | J63: {=IF($B63="","",IF(SUMPRODUCT(($BE$6:$BE$31=$C63)*($BH$6:$BH$31<0))>0,"YES — "&$C63&" family has a shortage","no — nothing short in "&$C63))} -> no — nothing short in LOCK-STITCH
B64: =IFERROR(IF(LARGE($BO$6:$BO$31,6)<=0,"",INDEX($BD$6:$BD$31,MATCH(LARGE($BO$6:$BO$31,6),$BO$6:$BO$31,0))),"") -> Flatlock Hem | C64: =IF($B64="","",INDEX($BE$6:$BE$31,MATCH($B64,$BD$6:$BD$31,0))) -> FLAT-LOCK | D64: =IF($B64="","",INDEX($BF$6:$BF$31,MATCH($B64,$BD$6:$BD$31,0))) -> 34 | E64: =IF($B64="","",INDEX($BG$6:$BG$31,MATCH($B64,$BD$6:$BD$31,0))) -> 27.5 | F64: =IF($B64="","",$D64-$E64) -> 6.5 | H64: =IF($B64="","",IF($E64=0,"NEVER USED","PART USED")) -> PART USED | J64: {=IF($B64="","",IF(SUMPRODUCT(($BE$6:$BE$31=$C64)*($BH$6:$BH$31<0))>0,"YES — "&$C64&" family has a shortage","no — nothing short in "&$C64))} -> YES — FLAT-LOCK family has a shortage
B65: =IFERROR(IF(LARGE($BO$6:$BO$31,7)<=0,"",INDEX($BD$6:$BD$31,MATCH(LARGE($BO$6:$BO$31,7),$BO$6:$BO$31,0))),"") -> Flatlock (VT) | C65: =IF($B65="","",INDEX($BE$6:$BE$31,MATCH($B65,$BD$6:$BD$31,0))) -> FLAT-LOCK | D65: =IF($B65="","",INDEX($BF$6:$BF$31,MATCH($B65,$BD$6:$BD$31,0))) -> 21 | E65: =IF($B65="","",INDEX($BG$6:$BG$31,MATCH($B65,$BD$6:$BD$31,0))) -> 15 | F65: =IF($B65="","",$D65-$E65) -> 6 | H65: =IF($B65="","",IF($E65=0,"NEVER USED","PART USED")) -> PART USED | J65: {=IF($B65="","",IF(SUMPRODUCT(($BE$6:$BE$31=$C65)*($BH$6:$BH$31<0))>0,"YES — "&$C65&" family has a shortage","no — nothing short in "&$C65))} -> YES — FLAT-LOCK family has a shortage
B66: =IFERROR(IF(LARGE($BO$6:$BO$31,8)<=0,"",INDEX($BD$6:$BD$31,MATCH(LARGE($BO$6:$BO$31,8),$BO$6:$BO$31,0))),"") -> Bartack Pattern tacker | C66: =IF($B66="","",INDEX($BE$6:$BE$31,MATCH($B66,$BD$6:$BD$31,0))) -> PATTERN-TACKER | D66: =IF($B66="","",INDEX($BF$6:$BF$31,MATCH($B66,$BD$6:$BD$31,0))) -> 35 | E66: =IF($B66="","",INDEX($BG$6:$BG$31,MATCH($B66,$BD$6:$BD$31,0))) -> 29 | F66: =IF($B66="","",$D66-$E66) -> 6 | H66: =IF($B66="","",IF($E66=0,"NEVER USED","PART USED")) -> PART USED | J66: {=IF($B66="","",IF(SUMPRODUCT(($BE$6:$BE$31=$C66)*($BH$6:$BH$31<0))>0,"YES — "&$C66&" family has a shortage","no — nothing short in "&$C66))} -> no — nothing short in PATTERN-TACKER
B67: =IFERROR(IF(LARGE($BO$6:$BO$31,9)<=0,"",INDEX($BD$6:$BD$31,MATCH(LARGE($BO$6:$BO$31,9),$BO$6:$BO$31,0))),"") -> Bartack | C67: =IF($B67="","",INDEX($BE$6:$BE$31,MATCH($B67,$BD$6:$BD$31,0))) -> BTK | D67: =IF($B67="","",INDEX($BF$6:$BF$31,MATCH($B67,$BD$6:$BD$31,0))) -> 13 | E67: =IF($B67="","",INDEX($BG$6:$BG$31,MATCH($B67,$BD$6:$BD$31,0))) -> 7.5 | F67: =IF($B67="","",$D67-$E67) -> 5.5 | H67: =IF($B67="","",IF($E67=0,"NEVER USED","PART USED")) -> PART USED | J67: {=IF($B67="","",IF(SUMPRODUCT(($BE$6:$BE$31=$C67)*($BH$6:$BH$31<0))>0,"YES — "&$C67&" family has a shortage","no — nothing short in "&$C67))} -> no — nothing short in BTK
B68: =IFERROR(IF(LARGE($BO$6:$BO$31,10)<=0,"",INDEX($BD$6:$BD$31,MATCH(LARGE($BO$6:$BO$31,10),$BO$6:$BO$31,0))),"") -> 5th Overlock | C68: =IF($B68="","",INDEX($BE$6:$BE$31,MATCH($B68,$BD$6:$BD$31,0))) -> OVER-LOCK | D68: =IF($B68="","",INDEX($BF$6:$BF$31,MATCH($B68,$BD$6:$BD$31,0))) -> 5 | E68: =IF($B68="","",INDEX($BG$6:$BG$31,MATCH($B68,$BD$6:$BD$31,0))) -> 0 | F68: =IF($B68="","",$D68-$E68) -> 5 | H68: =IF($B68="","",IF($E68=0,"NEVER USED","PART USED")) -> NEVER USED | J68: {=IF($B68="","",IF(SUMPRODUCT(($BE$6:$BE$31=$C68)*($BH$6:$BH$31<0))>0,"YES — "&$C68&" family has a shortage","no — nothing short in "&$C68))} -> YES — OVER-LOCK family has a shortage
B69: =IFERROR(IF(LARGE($BO$6:$BO$31,11)<=0,"",INDEX($BD$6:$BD$31,MATCH(LARGE($BO$6:$BO$31,11),$BO$6:$BO$31,0))),"") -> Kansai | C69: =IF($B69="","",INDEX($BE$6:$BE$31,MATCH($B69,$BD$6:$BD$31,0))) -> MULTI-NEEDLE | D69: =IF($B69="","",INDEX($BF$6:$BF$31,MATCH($B69,$BD$6:$BD$31,0))) -> 8 | E69: =IF($B69="","",INDEX($BG$6:$BG$31,MATCH($B69,$BD$6:$BD$31,0))) -> 3 | F69: =IF($B69="","",$D69-$E69) -> 5 | H69: =IF($B69="","",IF($E69=0,"NEVER USED","PART USED")) -> PART USED | J69: {=IF($B69="","",IF(SUMPRODUCT(($BE$6:$BE$31=$C69)*($BH$6:$BH$31<0))>0,"YES — "&$C69&" family has a shortage","no — nothing short in "&$C69))} -> no — nothing short in MULTI-NEEDLE
B70: =IFERROR(IF(LARGE($BO$6:$BO$31,12)<=0,"",INDEX($BD$6:$BD$31,MATCH(LARGE($BO$6:$BO$31,12),$BO$6:$BO$31,0))),"") -> Zig - Zag | C70: =IF($B70="","",INDEX($BE$6:$BE$31,MATCH($B70,$BD$6:$BD$31,0))) -> LOCK-STITCH | D70: =IF($B70="","",INDEX($BF$6:$BF$31,MATCH($B70,$BD$6:$BD$31,0))) -> 8 | E70: =IF($B70="","",INDEX($BG$6:$BG$31,MATCH($B70,$BD$6:$BD$31,0))) -> 4 | F70: =IF($B70="","",$D70-$E70) -> 4 | H70: =IF($B70="","",IF($E70=0,"NEVER USED","PART USED")) -> PART USED | J70: {=IF($B70="","",IF(SUMPRODUCT(($BE$6:$BE$31=$C70)*($BH$6:$BH$31<0))>0,"YES — "&$C70&" family has a shortage","no — nothing short in "&$C70))} -> no — nothing short in LOCK-STITCH
B71: =IFERROR(IF(LARGE($BO$6:$BO$31,13)<=0,"",INDEX($BD$6:$BD$31,MATCH(LARGE($BO$6:$BO$31,13),$BO$6:$BO$31,0))),"") -> Heat Seal | C71: =IF($B71="","",INDEX($BE$6:$BE$31,MATCH($B71,$BD$6:$BD$31,0))) -> HT | D71: =IF($B71="","",INDEX($BF$6:$BF$31,MATCH($B71,$BD$6:$BD$31,0))) -> 35 | E71: =IF($B71="","",INDEX($BG$6:$BG$31,MATCH($B71,$BD$6:$BD$31,0))) -> 32.5 | F71: =IF($B71="","",$D71-$E71) -> 2.5 | H71: =IF($B71="","",IF($E71=0,"NEVER USED","PART USED")) -> PART USED | J71: {=IF($B71="","",IF(SUMPRODUCT(($BE$6:$BE$31=$C71)*($BH$6:$BH$31<0))>0,"YES — "&$C71&" family has a shortage","no — nothing short in "&$C71))} -> no — nothing short in HT
B72: =IFERROR(IF(LARGE($BO$6:$BO$31,14)<=0,"",INDEX($BD$6:$BD$31,MATCH(LARGE($BO$6:$BO$31,14),$BO$6:$BO$31,0))),"") -> SNLS - Edge cutter | C72: =IF($B72="","",INDEX($BE$6:$BE$31,MATCH($B72,$BD$6:$BD$31,0))) -> LOCK-STITCH | D72: =IF($B72="","",INDEX($BF$6:$BF$31,MATCH($B72,$BD$6:$BD$31,0))) -> 2 | E72: =IF($B72="","",INDEX($BG$6:$BG$31,MATCH($B72,$BD$6:$BD$31,0))) -> 0 | F72: =IF($B72="","",$D72-$E72) -> 2 | H72: =IF($B72="","",IF($E72=0,"NEVER USED","PART USED")) -> NEVER USED | J72: {=IF($B72="","",IF(SUMPRODUCT(($BE$6:$BE$31=$C72)*($BH$6:$BH$31<0))>0,"YES — "&$C72&" family has a shortage","no — nothing short in "&$C72))} -> no — nothing short in LOCK-STITCH
B73: =IFERROR(IF(LARGE($BO$6:$BO$31,15)<=0,"",INDEX($BD$6:$BD$31,MATCH(LARGE($BO$6:$BO$31,15),$BO$6:$BO$31,0))),"") -> Chain stitch | C73: =IF($B73="","",INDEX($BE$6:$BE$31,MATCH($B73,$BD$6:$BD$31,0))) -> CS-DNLS | D73: =IF($B73="","",INDEX($BF$6:$BF$31,MATCH($B73,$BD$6:$BD$31,0))) -> 2 | E73: =IF($B73="","",INDEX($BG$6:$BG$31,MATCH($B73,$BD$6:$BD$31,0))) -> 0 | F73: =IF($B73="","",$D73-$E73) -> 2 | H73: =IF($B73="","",IF($E73=0,"NEVER USED","PART USED")) -> NEVER USED | J73: {=IF($B73="","",IF(SUMPRODUCT(($BE$6:$BE$31=$C73)*($BH$6:$BH$31<0))>0,"YES — "&$C73&" family has a shortage","no — nothing short in "&$C73))} -> no — nothing short in CS-DNLS
B74: =IFERROR(IF(LARGE($BO$6:$BO$31,16)<=0,"",INDEX($BD$6:$BD$31,MATCH(LARGE($BO$6:$BO$31,16),$BO$6:$BO$31,0))),"") -> Bartack Pattern tacker (LABEL ATTACH ) | C74: =IF($B74="","",INDEX($BE$6:$BE$31,MATCH($B74,$BD$6:$BD$31,0))) -> PATTERN-TACKER | D74: =IF($B74="","",INDEX($BF$6:$BF$31,MATCH($B74,$BD$6:$BD$31,0))) -> 2 | E74: =IF($B74="","",INDEX($BG$6:$BG$31,MATCH($B74,$BD$6:$BD$31,0))) -> 0 | F74: =IF($B74="","",$D74-$E74) -> 2 | H74: =IF($B74="","",IF($E74=0,"NEVER USED","PART USED")) -> NEVER USED | J74: {=IF($B74="","",IF(SUMPRODUCT(($BE$6:$BE$31=$C74)*($BH$6:$BH$31<0))>0,"YES — "&$C74&" family has a shortage","no — nothing short in "&$C74))} -> no — nothing short in PATTERN-TACKER
B75: =IFERROR(IF(LARGE($BO$6:$BO$31,17)<=0,"",INDEX($BD$6:$BD$31,MATCH(LARGE($BO$6:$BO$31,17),$BO$6:$BO$31,0))),"") -> F/L (Coverseam / Waist COVER SEAM | C75: =IF($B75="","",INDEX($BE$6:$BE$31,MATCH($B75,$BD$6:$BD$31,0))) -> FLAT-LOCK | D75: =IF($B75="","",INDEX($BF$6:$BF$31,MATCH($B75,$BD$6:$BD$31,0))) -> 13 | E75: =IF($B75="","",INDEX($BG$6:$BG$31,MATCH($B75,$BD$6:$BD$31,0))) -> 12 | F75: =IF($B75="","",$D75-$E75) -> 1 | H75: =IF($B75="","",IF($E75=0,"NEVER USED","PART USED")) -> PART USED | J75: {=IF($B75="","",IF(SUMPRODUCT(($BE$6:$BE$31=$C75)*($BH$6:$BH$31<0))>0,"YES — "&$C75&" family has a shortage","no — nothing short in "&$C75))} -> YES — FLAT-LOCK family has a shortage

Sheet DASHBOARD
B2: MACHINE DEPLOYMENT DASHBOARD
B3: ='LINE PLAN'!$HB$21&" | Machines vs. style embellishment requirement | Plan start: "&TEXT('LINE PLAN'!$HB$22,"d-mmm-yyyy") -> Garment Unit A | Machines vs. style embellishment requirement | Plan start: 1-Aug-2026
B4: AS-OF DATE ▾ | C4: DAY | D4: 46242 | E4: August 2026 | F4: =IF($C$4="DAY","Plan day "&MATCH(WORKINGS!$B$75,'LINE PLAN'!$B$35:$GS$35,0)&" of "&'LINE PLAN'!$B$3&" | "&INDEX('DEMAND BY DATE'!$AC$4:$AC$203,MATCH(WORKINGS!$B$75,'LINE PLAN'!$B$35:$GS$35,0))&" lines planned",$C$4&" OF "&UPPER($E$4)&" = "&TEXT(WORKINGS!$B$75,"ddd d-mmm")&" | month: "&TEXT(WORKINGS!$B$76,"#,##0")&" working days, avg "&TEXT(WORKINGS!$B$77,"#,##0")&", peak "&TEXT(WORKINGS!$B$78,"#,##0")&" m/c") -> Plan day 8 of 105 | 26 lines planned
B5: Machines installed | D5: Machines required | F5: Idle machines (this date) | H5: Utilisation | J5: Machine groups short | L5: Planned output pcs/day
B6: ='MC MASTER'!C29 -> 920 | D6: ='MC MAP'!AD113 -> 808 | F6: =SUMIF($E$12:$E$37,">0") -> 149.5 | H6: =IFERROR($D$6/$B$6,0) -> 0.87826087 | J6: =COUNTIF($F$12:$F$37,"SHORT") -> 5 | L6: ='MC MAP'!AE113 -> 81700
B9: MACHINE GROUP: INSTALLED vs. REQUIRED BY CURRENT STYLE MIX | I9: ="TOP 6 BOTTLENECKS OF "&$J$6&" SHORT GROUPS (buy / hire / re-balance)" -> TOP 6 BOTTLENECKS OF 5 SHORT GROUPS (buy / hire / re-balance)
B11: Machine (grouped by category) | C11: Installed | D11: Required | E11: Surplus / (Short) | F11: Status | G11: Utilisation | H11: Category / can it be covered by moving? | I11: Machine group | J11: Gap | K11: Installed | L11: Required
B12: =INDEX(WORKINGS!$A$116:$A$141,MATCH(SMALL(WORKINGS!$D$116:$D$141,1),WORKINGS!$D$116:$D$141,0)) -> SNLS | C12: =IFERROR(INDEX('MC MASTER'!$C$3:$C$28,MATCH($B12,'MC MASTER'!$B$3:$B$28,0)),0) -> 185 | D12: =IFERROR(INDEX('MC MAP'!$D$113:$AC$113,MATCH($B12,'MC MAP'!$D$86:$AC$86,0)),0) -> 152 | E12: =C12-D12 -> 33 | F12: =IF($D12=0,"IDLE",IF($E12<0,"SHORT",IF($E12/$C12<=0.1,"TIGHT","OK"))) -> OK | G12: =IFERROR($D12/$C12,"") -> 0.82162162 | H12: =IF($E12>=0,WORKINGS!$N12,IF(WORKINGS!$Q12<=0,WORKINGS!$N12&" — no spare, BUY "&TEXT(WORKINGS!$R12,"#,##0.0"),IF(WORKINGS!$R12<=0,WORKINGS!$N12&" — MOVE "&TEXT(WORKINGS!$Q12,"#,##0.0"),WORKINGS!$N12&" — MOVE "&TEXT(WORKINGS!$Q12,"#,##0.0")&", BUY "&TEXT(WORKINGS!$R12,"#,##0.0")))) -> LOCK-STITCH | I12: =IFERROR(IF(SMALL(WORKINGS!$M$12:$M$37,ROW()-11)>=0,"",INDEX($B$12:$B$37,MATCH(SMALL(WORKINGS!$M$12:$M$37,ROW()-11),WORKINGS!$M$12:$M$37,0))),"") -> 4th Overlock | J12: =IF($I12="","",INDEX($E$12:$E$37,MATCH($I12,$B$12:$B$37,0))) -> -12 | K12: =IF($I12="","",INDEX($C$12:$C$37,MATCH($I12,$B$12:$B$37,0))) -> 279 | L12: =IF($I12="","",INDEX($D$12:$D$37,MATCH($I12,$B$12:$B$37,0))) -> 291
B13: =INDEX(WORKINGS!$A$116:$A$141,MATCH(SMALL(WORKINGS!$D$116:$D$141,2),WORKINGS!$D$116:$D$141,0)) -> DNLS | C13: =IFERROR(INDEX('MC MASTER'!$C$3:$C$28,MATCH($B13,'MC MASTER'!$B$3:$B$28,0)),0) -> 8 | D13: =IFERROR(INDEX('MC MAP'!$D$113:$AC$113,MATCH($B13,'MC MAP'!$D$86:$AC$86,0)),0) -> 1 | E13: =C13-D13 -> 7 | F13: =IF($D13=0,"IDLE",IF($E13<0,"SHORT",IF($E13/$C13<=0.1,"TIGHT","OK"))) -> OK | G13: =IFERROR($D13/$C13,"") -> 0.125 | H13: =IF($E13>=0,WORKINGS!$N13,IF(WORKINGS!$Q13<=0,WORKINGS!$N13&" — no spare, BUY "&TEXT(WORKINGS!$R13,"#,##0.0"),IF(WORKINGS!$R13<=0,WORKINGS!$N13&" — MOVE "&TEXT(WORKINGS!$Q13,"#,##0.0"),WORKINGS!$N13&" — MOVE "&TEXT(WORKINGS!$Q13,"#,##0.0")&", BUY "&TEXT(WORKINGS!$R13,"#,##0.0")))) -> LOCK-STITCH | I13: =IFERROR(IF(SMALL(WORKINGS!$M$12:$M$37,ROW()-11)>=0,"",INDEX($B$12:$B$37,MATCH(SMALL(WORKINGS!$M$12:$M$37,ROW()-11),WORKINGS!$M$12:$M$37,0))),"") -> F/L (Coverseam ) | J13: =IF($I13="","",INDEX($E$12:$E$37,MATCH($I13,$B$12:$B$37,0))) -> -11 | K13: =IF($I13="","",INDEX($C$12:$C$37,MATCH($I13,$B$12:$B$37,0))) -> 6 | L13: =IF($I13="","",INDEX($D$12:$D$37,MATCH($I13,$B$12:$B$37,0))) -> 17
B14: =INDEX(WORKINGS!$A$116:$A$141,MATCH(SMALL(WORKINGS!$D$116:$D$141,3),WORKINGS!$D$116:$D$141,0)) -> SNLS - Edge cutter | C14: =IFERROR(INDEX('MC MASTER'!$C$3:$C$28,MATCH($B14,'MC MASTER'!$B$3:$B$28,0)),0) -> 2 | D14: =IFERROR(INDEX('MC MAP'!$D$113:$AC$113,MATCH($B14,'MC MAP'!$D$86:$AC$86,0)),0) -> 0 | E14: =C14-D14 -> 2 | F14: =IF($D14=0,"IDLE",IF($E14<0,"SHORT",IF($E14/$C14<=0.1,"TIGHT","OK"))) -> IDLE | G14: =IFERROR($D14/$C14,"") -> 0 | H14: =IF($E14>=0,WORKINGS!$N14,IF(WORKINGS!$Q14<=0,WORKINGS!$N14&" — no spare, BUY "&TEXT(WORKINGS!$R14,"#,##0.0"),IF(WORKINGS!$R14<=0,WORKINGS!$N14&" — MOVE "&TEXT(WORKINGS!$Q14,"#,##0.0"),WORKINGS!$N14&" — MOVE "&TEXT(WORKINGS!$Q14,"#,##0.0")&", BUY "&TEXT(WORKINGS!$R14,"#,##0.0")))) -> LOCK-STITCH | I14: =IFERROR(IF(SMALL(WORKINGS!$M$12:$M$37,ROW()-11)>=0,"",INDEX($B$12:$B$37,MATCH(SMALL(WORKINGS!$M$12:$M$37,ROW()-11),WORKINGS!$M$12:$M$37,0))),"") -> Overlock (Ring Elastic Attach) | J14: =IF($I14="","",INDEX($E$12:$E$37,MATCH($I14,$B$12:$B$37,0))) -> -7 | K14: =IF($I14="","",INDEX($C$12:$C$37,MATCH($I14,$B$12:$B$37,0))) -> 29 | L14: =IF($I14="","",INDEX($D$12:$D$37,MATCH($I14,$B$12:$B$37,0))) -> 36
B15: =INDEX(WORKINGS!$A$116:$A$141,MATCH(SMALL(WORKINGS!$D$116:$D$141,4),WORKINGS!$D$116:$D$141,0)) -> Zig - Zag | C15: =IFERROR(INDEX('MC MASTER'!$C$3:$C$28,MATCH($B15,'MC MASTER'!$B$3:$B$28,0)),0) -> 8 | D15: =IFERROR(INDEX('MC MAP'!$D$113:$AC$113,MATCH($B15,'MC MAP'!$D$86:$AC$86,0)),0) -> 4 | E15: =C15-D15 -> 4 | F15: =IF($D15=0,"IDLE",IF($E15<0,"SHORT",IF($E15/$C15<=0.1,"TIGHT","OK"))) -> OK | G15: =IFERROR($D15/$C15,"") -> 0.5 | H15: =IF($E15>=0,WORKINGS!$N15,IF(WORKINGS!$Q15<=0,WORKINGS!$N15&" — no spare, BUY "&TEXT(WORKINGS!$R15,"#,##0.0"),IF(WORKINGS!$R15<=0,WORKINGS!$N15&" — MOVE "&TEXT(WORKINGS!$Q15,"#,##0.0"),WORKINGS!$N15&" — MOVE "&TEXT(WORKINGS!$Q15,"#,##0.0")&", BUY "&TEXT(WORKINGS!$R15,"#,##0.0")))) -> LOCK-STITCH | I15: =IFERROR(IF(SMALL(WORKINGS!$M$12:$M$37,ROW()-11)>=0,"",INDEX($B$12:$B$37,MATCH(SMALL(WORKINGS!$M$12:$M$37,ROW()-11),WORKINGS!$M$12:$M$37,0))),"") -> F/L (Coverseam )with pullar | J15: =IF($I15="","",INDEX($E$12:$E$37,MATCH($I15,$B$12:$B$37,0))) -> -6.5 | K15: =IF($I15="","",INDEX($C$12:$C$37,MATCH($I15,$B$12:$B$37,0))) -> 37 | L15: =IF($I15="","",INDEX($D$12:$D$37,MATCH($I15,$B$12:$B$37,0))) -> 43.5
B16: =INDEX(WORKINGS!$A$116:$A$141,MATCH(SMALL(WORKINGS!$D$116:$D$141,5),WORKINGS!$D$116:$D$141,0)) -> 4th Overlock | C16: =IFERROR(INDEX('MC MASTER'!$C$3:$C$28,MATCH($B16,'MC MASTER'!$B$3:$B$28,0)),0) -> 279 | D16: =IFERROR(INDEX('MC MAP'!$D$113:$AC$113,MATCH($B16,'MC MAP'!$D$86:$AC$86,0)),0) -> 291 | E16: =C16-D16 -> -12 | F16: =IF($D16=0,"IDLE",IF($E16<0,"SHORT",IF($E16/$C16<=0.1,"TIGHT","OK"))) -> SHORT | G16: =IFERROR($D16/$C16,"") -> 1.0430108 | H16: =IF($E16>=0,WORKINGS!$N16,IF(WORKINGS!$Q16<=0,WORKINGS!$N16&" — no spare, BUY "&TEXT(WORKINGS!$R16,"#,##0.0"),IF(WORKINGS!$R16<=0,WORKINGS!$N16&" — MOVE "&TEXT(WORKINGS!$Q16,"#,##0.0"),WORKINGS!$N16&" — MOVE "&TEXT(WORKINGS!$Q16,"#,##0.0")&", BUY "&TEXT(WORKINGS!$R16,"#,##0.0")))) -> OVER-LOCK — MOVE 5.0, BUY 7.0 | I16: =IFERROR(IF(SMALL(WORKINGS!$M$12:$M$37,ROW()-11)>=0,"",INDEX($B$12:$B$37,MATCH(SMALL(WORKINGS!$M$12:$M$37,ROW()-11),WORKINGS!$M$12:$M$37,0))),"") -> 3th Overlock (Leg elastic) | J16: =IF($I16="","",INDEX($E$12:$E$37,MATCH($I16,$B$12:$B$37,0))) -> -1 | K16: =IF($I16="","",INDEX($C$12:$C$37,MATCH($I16,$B$12:$B$37,0))) -> 30 | L16: =IF($I16="","",INDEX($D$12:$D$37,MATCH($I16,$B$12:$B$37,0))) -> 31
B17: =INDEX(WORKINGS!$A$116:$A$141,MATCH(SMALL(WORKINGS!$D$116:$D$141,6),WORKINGS!$D$116:$D$141,0)) -> 3th Overlock (Leg elastic) | C17: =IFERROR(INDEX('MC MASTER'!$C$3:$C$28,MATCH($B17,'MC MASTER'!$B$3:$B$28,0)),0) -> 30 | D17: =IFERROR(INDEX('MC MAP'!$D$113:$AC$113,MATCH($B17,'MC MAP'!$D$86:$AC$86,0)),0) -> 31 | E17: =C17-D17 -> -1 | F17: =IF($D17=0,"IDLE",IF($E17<0,"SHORT",IF($E17/$C17<=0.1,"TIGHT","OK"))) -> SHORT | G17: =IFERROR($D17/$C17,"") -> 1.0333333 | H17: =IF($E17>=0,WORKINGS!$N17,IF(WORKINGS!$Q17<=0,WORKINGS!$N17&" — no spare, BUY "&TEXT(WORKINGS!$R17,"#,##0.0"),IF(WORKINGS!$R17<=0,WORKINGS!$N17&" — MOVE "&TEXT(WORKINGS!$Q17,"#,##0.0"),WORKINGS!$N17&" — MOVE "&TEXT(WORKINGS!$Q17,"#,##0.0")&", BUY "&TEXT(WORKINGS!$R17,"#,##0.0")))) -> OVER-LOCK — no spare, BUY 1.0 | I17: =IFERROR(IF(SMALL(WORKINGS!$M$12:$M$37,ROW()-11)>=0,"",INDEX($B$12:$B$37,MATCH(SMALL(WORKINGS!$M$12:$M$37,ROW()-11),WORKINGS!$M$12:$M$37,0))),"") | J17: =IF($I17="","",INDEX($E$12:$E$37,MATCH($I17,$B$12:$B$37,0))) | K17: =IF($I17="","",INDEX($C$12:$C$37,MATCH($I17,$B$12:$B$37,0))) | L17: =IF($I17="","",INDEX($D$12:$D$37,MATCH($I17,$B$12:$B$37,0)))
B18: =INDEX(WORKINGS!$A$116:$A$141,MATCH(SMALL(WORKINGS!$D$116:$D$141,7),WORKINGS!$D$116:$D$141,0)) -> 5th Overlock | C18: =IFERROR(INDEX('MC MASTER'!$C$3:$C$28,MATCH($B18,'MC MASTER'!$B$3:$B$28,0)),0) -> 5 | D18: =IFERROR(INDEX('MC MAP'!$D$113:$AC$113,MATCH($B18,'MC MAP'!$D$86:$AC$86,0)),0) -> 0 | E18: =C18-D18 -> 5 | F18: =IF($D18=0,"IDLE",IF($E18<0,"SHORT",IF($E18/$C18<=0.1,"TIGHT","OK"))) -> IDLE | G18: =IFERROR($D18/$C18,"") -> 0 | H18: =IF($E18>=0,WORKINGS!$N18,IF(WORKINGS!$Q18<=0,WORKINGS!$N18&" — no spare, BUY "&TEXT(WORKINGS!$R18,"#,##0.0"),IF(WORKINGS!$R18<=0,WORKINGS!$N18&" — MOVE "&TEXT(WORKINGS!$Q18,"#,##0.0"),WORKINGS!$N18&" — MOVE "&TEXT(WORKINGS!$Q18,"#,##0.0")&", BUY "&TEXT(WORKINGS!$R18,"#,##0.0")))) -> OVER-LOCK
B19: =INDEX(WORKINGS!$A$116:$A$141,MATCH(SMALL(WORKINGS!$D$116:$D$141,8),WORKINGS!$D$116:$D$141,0)) -> Overlock (Ring Elastic Attach) | C19: =IFERROR(INDEX('MC MASTER'!$C$3:$C$28,MATCH($B19,'MC MASTER'!$B$3:$B$28,0)),0) -> 29 | D19: =IFERROR(INDEX('MC MAP'!$D$113:$AC$113,MATCH($B19,'MC MAP'!$D$86:$AC$86,0)),0) -> 36 | E19: =C19-D19 -> -7 | F19: =IF($D19=0,"IDLE",IF($E19<0,"SHORT",IF($E19/$C19<=0.1,"TIGHT","OK"))) -> SHORT | G19: =IFERROR($D19/$C19,"") -> 1.2413793 | H19: =IF($E19>=0,WORKINGS!$N19,IF(WORKINGS!$Q19<=0,WORKINGS!$N19&" — no spare, BUY "&TEXT(WORKINGS!$R19,"#,##0.0"),IF(WORKINGS!$R19<=0,WORKINGS!$N19&" — MOVE "&TEXT(WORKINGS!$Q19,"#,##0.0"),WORKINGS!$N19&" — MOVE "&TEXT(WORKINGS!$Q19,"#,##0.0")&", BUY "&TEXT(WORKINGS!$R19,"#,##0.0")))) -> OVER-LOCK — no spare, BUY 7.0 | I19: ="IDLE & AVAILABLE CAPACITY ON "&UPPER(TEXT(WORKINGS!$B$75,"ddd d-mmm")) -> IDLE & AVAILABLE CAPACITY ON SAT 8-AUG
B20: =INDEX(WORKINGS!$A$116:$A$141,MATCH(SMALL(WORKINGS!$D$116:$D$141,9),WORKINGS!$D$116:$D$141,0)) -> Flatlock Hem | C20: =IFERROR(INDEX('MC MASTER'!$C$3:$C$28,MATCH($B20,'MC MASTER'!$B$3:$B$28,0)),0) -> 34 | D20: =IFERROR(INDEX('MC MAP'!$D$113:$AC$113,MATCH($B20,'MC MAP'!$D$86:$AC$86,0)),0) -> 22.5 | E20: =C20-D20 -> 11.5 | F20: =IF($D20=0,"IDLE",IF($E20<0,"SHORT",IF($E20/$C20<=0.1,"TIGHT","OK"))) -> OK | G20: =IFERROR($D20/$C20,"") -> 0.66176471 | H20: =IF($E20>=0,WORKINGS!$N20,IF(WORKINGS!$Q20<=0,WORKINGS!$N20&" — no spare, BUY "&TEXT(WORKINGS!$R20,"#,##0.0"),IF(WORKINGS!$R20<=0,WORKINGS!$N20&" — MOVE "&TEXT(WORKINGS!$Q20,"#,##0.0"),WORKINGS!$N20&" — MOVE "&TEXT(WORKINGS!$Q20,"#,##0.0")&", BUY "&TEXT(WORKINGS!$R20,"#,##0.0")))) -> FLAT-LOCK | I20: Free to redeploy | J20: spare in groups that are working | L20: =SUMIF($E$12:$E$37,">0")-$L$22 -> 145.5
B21: =INDEX(WORKINGS!$A$116:$A$141,MATCH(SMALL(WORKINGS!$D$116:$D$141,10),WORKINGS!$D$116:$D$141,0)) -> F/L (Coverseam / Waist COVER SEAM | C21: =IFERROR(INDEX('MC MASTER'!$C$3:$C$28,MATCH($B21,'MC MASTER'!$B$3:$B$28,0)),0) -> 13 | D21: =IFERROR(INDEX('MC MAP'!$D$113:$AC$113,MATCH($B21,'MC MAP'!$D$86:$AC$86,0)),0) -> 4 | E21: =C21-D21 -> 9 | F21: =IF($D21=0,"IDLE",IF($E21<0,"SHORT",IF($E21/$C21<=0.1,"TIGHT","OK"))) -> OK | G21: =IFERROR($D21/$C21,"") -> 0.30769231 | H21: =IF($E21>=0,WORKINGS!$N21,IF(WORKINGS!$Q21<=0,WORKINGS!$N21&" — no spare, BUY "&TEXT(WORKINGS!$R21,"#,##0.0"),IF(WORKINGS!$R21<=0,WORKINGS!$N21&" — MOVE "&TEXT(WORKINGS!$Q21,"#,##0.0"),WORKINGS!$N21&" — MOVE "&TEXT(WORKINGS!$Q21,"#,##0.0")&", BUY "&TEXT(WORKINGS!$R21,"#,##0.0")))) -> FLAT-LOCK
B22: =INDEX(WORKINGS!$A$116:$A$141,MATCH(SMALL(WORKINGS!$D$116:$D$141,11),WORKINGS!$D$116:$D$141,0)) -> F/L (Coverseam )with pullar | C22: =IFERROR(INDEX('MC MASTER'!$C$3:$C$28,MATCH($B22,'MC MASTER'!$B$3:$B$28,0)),0) -> 37 | D22: =IFERROR(INDEX('MC MAP'!$D$113:$AC$113,MATCH($B22,'MC MAP'!$D$86:$AC$86,0)),0) -> 43.5 | E22: =C22-D22 -> -6.5 | F22: =IF($D22=0,"IDLE",IF($E22<0,"SHORT",IF($E22/$C22<=0.1,"TIGHT","OK"))) -> SHORT | G22: =IFERROR($D22/$C22,"") -> 1.1756757 | H22: =IF($E22>=0,WORKINGS!$N22,IF(WORKINGS!$Q22<=0,WORKINGS!$N22&" — no spare, BUY "&TEXT(WORKINGS!$R22,"#,##0.0"),IF(WORKINGS!$R22<=0,WORKINGS!$N22&" — MOVE "&TEXT(WORKINGS!$Q22,"#,##0.0"),WORKINGS!$N22&" — MOVE "&TEXT(WORKINGS!$Q22,"#,##0.0")&", BUY "&TEXT(WORKINGS!$R22,"#,##0.0")))) -> FLAT-LOCK — MOVE 6.5 | I22: Idle, but unusable | J22: =COUNTIF('MC MAP'!$BU$5:$BU$30,0)&" groups no style needs at all" -> 2 groups no style needs at all | L22: {=SUMPRODUCT(--('MC MAP'!$BU$5:$BU$30=0)*'MC MASTER'!$C$3:$C$28)} -> 4
B23: =INDEX(WORKINGS!$A$116:$A$141,MATCH(SMALL(WORKINGS!$D$116:$D$141,12),WORKINGS!$D$116:$D$141,0)) -> F/L (Coverseam ) | C23: =IFERROR(INDEX('MC MASTER'!$C$3:$C$28,MATCH($B23,'MC MASTER'!$B$3:$B$28,0)),0) -> 6 | D23: =IFERROR(INDEX('MC MAP'!$D$113:$AC$113,MATCH($B23,'MC MAP'!$D$86:$AC$86,0)),0) -> 17 | E23: =C23-D23 -> -11 | F23: =IF($D23=0,"IDLE",IF($E23<0,"SHORT",IF($E23/$C23<=0.1,"TIGHT","OK"))) -> SHORT | G23: =IFERROR($D23/$C23,"") -> 2.8333333 | H23: =IF($E23>=0,WORKINGS!$N23,IF(WORKINGS!$Q23<=0,WORKINGS!$N23&" — no spare, BUY "&TEXT(WORKINGS!$R23,"#,##0.0"),IF(WORKINGS!$R23<=0,WORKINGS!$N23&" — MOVE "&TEXT(WORKINGS!$Q23,"#,##0.0"),WORKINGS!$N23&" — MOVE "&TEXT(WORKINGS!$Q23,"#,##0.0")&", BUY "&TEXT(WORKINGS!$R23,"#,##0.0")))) -> FLAT-LOCK — MOVE 11.0
B24: =INDEX(WORKINGS!$A$116:$A$141,MATCH(SMALL(WORKINGS!$D$116:$D$141,13),WORKINGS!$D$116:$D$141,0)) -> 3N5T-F/L -( TopStitch) | C24: =IFERROR(INDEX('MC MASTER'!$C$3:$C$28,MATCH($B24,'MC MASTER'!$B$3:$B$28,0)),0) -> 54 | D24: =IFERROR(INDEX('MC MAP'!$D$113:$AC$113,MATCH($B24,'MC MAP'!$D$86:$AC$86,0)),0) -> 47 | E24: =C24-D24 -> 7 | F24: =IF($D24=0,"IDLE",IF($E24<0,"SHORT",IF($E24/$C24<=0.1,"TIGHT","OK"))) -> OK | G24: =IFERROR($D24/$C24,"") -> 0.87037037 | H24: =IF($E24>=0,WORKINGS!$N24,IF(WORKINGS!$Q24<=0,WORKINGS!$N24&" — no spare, BUY "&TEXT(WORKINGS!$R24,"#,##0.0"),IF(WORKINGS!$R24<=0,WORKINGS!$N24&" — MOVE "&TEXT(WORKINGS!$Q24,"#,##0.0"),WORKINGS!$N24&" — MOVE "&TEXT(WORKINGS!$Q24,"#,##0.0")&", BUY "&TEXT(WORKINGS!$R24,"#,##0.0")))) -> FLAT-LOCK | I24: Short | J24: =COUNTIF($F$12:$F$37,"SHORT")&" groups need more than we own" -> 5 groups need more than we own | L24: =-SUMIF($E$12:$E$37,"<0") -> 37.5
B25: =INDEX(WORKINGS!$A$116:$A$141,MATCH(SMALL(WORKINGS!$D$116:$D$141,14),WORKINGS!$D$116:$D$141,0)) -> Flatlock (VT) | C25: =IFERROR(INDEX('MC MASTER'!$C$3:$C$28,MATCH($B25,'MC MASTER'!$B$3:$B$28,0)),0) -> 21 | D25: =IFERROR(INDEX('MC MAP'!$D$113:$AC$113,MATCH($B25,'MC MAP'!$D$86:$AC$86,0)),0) -> 13 | E25: =C25-D25 -> 8 | F25: =IF($D25=0,"IDLE",IF($E25<0,"SHORT",IF($E25/$C25<=0.1,"TIGHT","OK"))) -> OK | G25: =IFERROR($D25/$C25,"") -> 0.61904762 | H25: =IF($E25>=0,WORKINGS!$N25,IF(WORKINGS!$Q25<=0,WORKINGS!$N25&" — no spare, BUY "&TEXT(WORKINGS!$R25,"#,##0.0"),IF(WORKINGS!$R25<=0,WORKINGS!$N25&" — MOVE "&TEXT(WORKINGS!$Q25,"#,##0.0"),WORKINGS!$N25&" — MOVE "&TEXT(WORKINGS!$Q25,"#,##0.0")&", BUY "&TEXT(WORKINGS!$R25,"#,##0.0")))) -> FLAT-LOCK
B26: =INDEX(WORKINGS!$A$116:$A$141,MATCH(SMALL(WORKINGS!$D$116:$D$141,15),WORKINGS!$D$116:$D$141,0)) -> Flatlock (Ring Elastic Attach) | C26: =IFERROR(INDEX('MC MASTER'!$C$3:$C$28,MATCH($B26,'MC MASTER'!$B$3:$B$28,0)),0) -> 42 | D26: =IFERROR(INDEX('MC MAP'!$D$113:$AC$113,MATCH($B26,'MC MAP'!$D$86:$AC$86,0)),0) -> 34.5 | E26: =C26-D26 -> 7.5 | F26: =IF($D26=0,"IDLE",IF($E26<0,"SHORT",IF($E26/$C26<=0.1,"TIGHT","OK"))) -> OK | G26: =IFERROR($D26/$C26,"") -> 0.82142857 | H26: =IF($E26>=0,WORKINGS!$N26,IF(WORKINGS!$Q26<=0,WORKINGS!$N26&" — no spare, BUY "&TEXT(WORKINGS!$R26,"#,##0.0"),IF(WORKINGS!$R26<=0,WORKINGS!$N26&" — MOVE "&TEXT(WORKINGS!$Q26,"#,##0.0"),WORKINGS!$N26&" — MOVE "&TEXT(WORKINGS!$Q26,"#,##0.0")&", BUY "&TEXT(WORKINGS!$R26,"#,##0.0")))) -> OUTER ELASTIC | I26: =IF($L$24=0,"No shortage — all "&TEXT($L$20+$L$22,"#,##0")&" idle machines are genuine spare capacity.",TEXT($L$24,"#,##0")&" short vs "&TEXT($L$20,"#,##0")&" free — wrong machine types. Buy, hire or convert.") -> 38 short vs 146 free — wrong machine types. Buy, hire or convert.
B27: =INDEX(WORKINGS!$A$116:$A$141,MATCH(SMALL(WORKINGS!$D$116:$D$141,16),WORKINGS!$D$116:$D$141,0)) -> 3N5T-F/L -BINDING | C27: =IFERROR(INDEX('MC MASTER'!$C$3:$C$28,MATCH($B27,'MC MASTER'!$B$3:$B$28,0)),0) -> 58 | D27: =IFERROR(INDEX('MC MAP'!$D$113:$AC$113,MATCH($B27,'MC MAP'!$D$86:$AC$86,0)),0) -> 40 | E27: =C27-D27 -> 18 | F27: =IF($D27=0,"IDLE",IF($E27<0,"SHORT",IF($E27/$C27<=0.1,"TIGHT","OK"))) -> OK | G27: =IFERROR($D27/$C27,"") -> 0.68965517 | H27: =IF($E27>=0,WORKINGS!$N27,IF(WORKINGS!$Q27<=0,WORKINGS!$N27&" — no spare, BUY "&TEXT(WORKINGS!$R27,"#,##0.0"),IF(WORKINGS!$R27<=0,WORKINGS!$N27&" — MOVE "&TEXT(WORKINGS!$Q27,"#,##0.0"),WORKINGS!$N27&" — MOVE "&TEXT(WORKINGS!$Q27,"#,##0.0")&", BUY "&TEXT(WORKINGS!$R27,"#,##0.0")))) -> BINDING
B28: =INDEX(WORKINGS!$A$116:$A$141,MATCH(SMALL(WORKINGS!$D$116:$D$141,17),WORKINGS!$D$116:$D$141,0)) -> FlatSeamer FS | C28: =IFERROR(INDEX('MC MASTER'!$C$3:$C$28,MATCH($B28,'MC MASTER'!$B$3:$B$28,0)),0) -> 8 | D28: =IFERROR(INDEX('MC MAP'!$D$113:$AC$113,MATCH($B28,'MC MAP'!$D$86:$AC$86,0)),0) -> 0 | E28: =C28-D28 -> 8 | F28: =IF($D28=0,"IDLE",IF($E28<0,"SHORT",IF($E28/$C28<=0.1,"TIGHT","OK"))) -> IDLE | G28: =IFERROR($D28/$C28,"") -> 0 | H28: =IF($E28>=0,WORKINGS!$N28,IF(WORKINGS!$Q28<=0,WORKINGS!$N28&" — no spare, BUY "&TEXT(WORKINGS!$R28,"#,##0.0"),IF(WORKINGS!$R28<=0,WORKINGS!$N28&" — MOVE "&TEXT(WORKINGS!$Q28,"#,##0.0"),WORKINGS!$N28&" — MOVE "&TEXT(WORKINGS!$Q28,"#,##0.0")&", BUY "&TEXT(WORKINGS!$R28,"#,##0.0")))) -> FS
B29: =INDEX(WORKINGS!$A$116:$A$141,MATCH(SMALL(WORKINGS!$D$116:$D$141,18),WORKINGS!$D$116:$D$141,0)) -> Kansai | C29: =IFERROR(INDEX('MC MASTER'!$C$3:$C$28,MATCH($B29,'MC MASTER'!$B$3:$B$28,0)),0) -> 8 | D29: =IFERROR(INDEX('MC MAP'!$D$113:$AC$113,MATCH($B29,'MC MAP'!$D$86:$AC$86,0)),0) -> 3 | E29: =C29-D29 -> 5 | F29: =IF($D29=0,"IDLE",IF($E29<0,"SHORT",IF($E29/$C29<=0.1,"TIGHT","OK"))) -> OK | G29: =IFERROR($D29/$C29,"") -> 0.375 | H29: =IF($E29>=0,WORKINGS!$N29,IF(WORKINGS!$Q29<=0,WORKINGS!$N29&" — no spare, BUY "&TEXT(WORKINGS!$R29,"#,##0.0"),IF(WORKINGS!$R29<=0,WORKINGS!$N29&" — MOVE "&TEXT(WORKINGS!$Q29,"#,##0.0"),WORKINGS!$N29&" — MOVE "&TEXT(WORKINGS!$Q29,"#,##0.0")&", BUY "&TEXT(WORKINGS!$R29,"#,##0.0")))) -> MULTI-NEEDLE
B30: =INDEX(WORKINGS!$A$116:$A$141,MATCH(SMALL(WORKINGS!$D$116:$D$141,19),WORKINGS!$D$116:$D$141,0)) -> Chain stitch | C30: =IFERROR(INDEX('MC MASTER'!$C$3:$C$28,MATCH($B30,'MC MASTER'!$B$3:$B$28,0)),0) -> 2 | D30: =IFERROR(INDEX('MC MAP'!$D$113:$AC$113,MATCH($B30,'MC MAP'!$D$86:$AC$86,0)),0) -> 0 | E30: =C30-D30 -> 2 | F30: =IF($D30=0,"IDLE",IF($E30<0,"SHORT",IF($E30/$C30<=0.1,"TIGHT","OK"))) -> IDLE | G30: =IFERROR($D30/$C30,"") -> 0 | H30: =IF($E30>=0,WORKINGS!$N30,IF(WORKINGS!$Q30<=0,WORKINGS!$N30&" — no spare, BUY "&TEXT(WORKINGS!$R30,"#,##0.0"),IF(WORKINGS!$R30<=0,WORKINGS!$N30&" — MOVE "&TEXT(WORKINGS!$Q30,"#,##0.0"),WORKINGS!$N30&" — MOVE "&TEXT(WORKINGS!$Q30,"#,##0.0")&", BUY "&TEXT(WORKINGS!$R30,"#,##0.0")))) -> CS-DNLS
B31: =INDEX(WORKINGS!$A$116:$A$141,MATCH(SMALL(WORKINGS!$D$116:$D$141,20),WORKINGS!$D$116:$D$141,0)) -> Heat Seal | C31: =IFERROR(INDEX('MC MASTER'!$C$3:$C$28,MATCH($B31,'MC MASTER'!$B$3:$B$28,0)),0) -> 35 | D31: =IFERROR(INDEX('MC MAP'!$D$113:$AC$113,MATCH($B31,'MC MAP'!$D$86:$AC$86,0)),0) -> 31 | E31: =C31-D31 -> 4 | F31: =IF($D31=0,"IDLE",IF($E31<0,"SHORT",IF($E31/$C31<=0.1,"TIGHT","OK"))) -> OK | G31: =IFERROR($D31/$C31,"") -> 0.88571429 | H31: =IF($E31>=0,WORKINGS!$N31,IF(WORKINGS!$Q31<=0,WORKINGS!$N31&" — no spare, BUY "&TEXT(WORKINGS!$R31,"#,##0.0"),IF(WORKINGS!$R31<=0,WORKINGS!$N31&" — MOVE "&TEXT(WORKINGS!$Q31,"#,##0.0"),WORKINGS!$N31&" — MOVE "&TEXT(WORKINGS!$Q31,"#,##0.0")&", BUY "&TEXT(WORKINGS!$R31,"#,##0.0")))) -> HT
B32: =INDEX(WORKINGS!$A$116:$A$141,MATCH(SMALL(WORKINGS!$D$116:$D$141,21),WORKINGS!$D$116:$D$141,0)) -> Snap button | C32: =IFERROR(INDEX('MC MASTER'!$C$3:$C$28,MATCH($B32,'MC MASTER'!$B$3:$B$28,0)),0) -> 2 | D32: =IFERROR(INDEX('MC MAP'!$D$113:$AC$113,MATCH($B32,'MC MAP'!$D$86:$AC$86,0)),0) -> 2 | E32: =C32-D32 -> 0 | F32: =IF($D32=0,"IDLE",IF($E32<0,"SHORT",IF($E32/$C32<=0.1,"TIGHT","OK"))) -> TIGHT | G32: =IFERROR($D32/$C32,"") -> 1 | H32: =IF($E32>=0,WORKINGS!$N32,IF(WORKINGS!$Q32<=0,WORKINGS!$N32&" — no spare, BUY "&TEXT(WORKINGS!$R32,"#,##0.0"),IF(WORKINGS!$R32<=0,WORKINGS!$N32&" — MOVE "&TEXT(WORKINGS!$Q32,"#,##0.0"),WORKINGS!$N32&" — MOVE "&TEXT(WORKINGS!$Q32,"#,##0.0")&", BUY "&TEXT(WORKINGS!$R32,"#,##0.0")))) -> ILET
B33: =INDEX(WORKINGS!$A$116:$A$141,MATCH(SMALL(WORKINGS!$D$116:$D$141,22),WORKINGS!$D$116:$D$141,0)) -> Button Hole | C33: =IFERROR(INDEX('MC MASTER'!$C$3:$C$28,MATCH($B33,'MC MASTER'!$B$3:$B$28,0)),0) -> 3 | D33: =IFERROR(INDEX('MC MAP'!$D$113:$AC$113,MATCH($B33,'MC MAP'!$D$86:$AC$86,0)),0) -> 2 | E33: =C33-D33 -> 1 | F33: =IF($D33=0,"IDLE",IF($E33<0,"SHORT",IF($E33/$C33<=0.1,"TIGHT","OK"))) -> OK | G33: =IFERROR($D33/$C33,"") -> 0.66666667 | H33: =IF($E33>=0,WORKINGS!$N33,IF(WORKINGS!$Q33<=0,WORKINGS!$N33&" — no spare, BUY "&TEXT(WORKINGS!$R33,"#,##0.0"),IF(WORKINGS!$R33<=0,WORKINGS!$N33&" — MOVE "&TEXT(WORKINGS!$Q33,"#,##0.0"),WORKINGS!$N33&" — MOVE "&TEXT(WORKINGS!$Q33,"#,##0.0")&", BUY "&TEXT(WORKINGS!$R33,"#,##0.0")))) -> BH
B34: =INDEX(WORKINGS!$A$116:$A$141,MATCH(SMALL(WORKINGS!$D$116:$D$141,23),WORKINGS!$D$116:$D$141,0)) -> Button Attach | C34: =IFERROR(INDEX('MC MASTER'!$C$3:$C$28,MATCH($B34,'MC MASTER'!$B$3:$B$28,0)),0) -> 1 | D34: =IFERROR(INDEX('MC MAP'!$D$113:$AC$113,MATCH($B34,'MC MAP'!$D$86:$AC$86,0)),0) -> 0 | E34: =C34-D34 -> 1 | F34: =IF($D34=0,"IDLE",IF($E34<0,"SHORT",IF($E34/$C34<=0.1,"TIGHT","OK"))) -> IDLE | G34: =IFERROR($D34/$C34,"") -> 0 | H34: =IF($E34>=0,WORKINGS!$N34,IF(WORKINGS!$Q34<=0,WORKINGS!$N34&" — no spare, BUY "&TEXT(WORKINGS!$R34,"#,##0.0"),IF(WORKINGS!$R34<=0,WORKINGS!$N34&" — MOVE "&TEXT(WORKINGS!$Q34,"#,##0.0"),WORKINGS!$N34&" — MOVE "&TEXT(WORKINGS!$Q34,"#,##0.0")&", BUY "&TEXT(WORKINGS!$R34,"#,##0.0")))) -> BA
B35: =INDEX(WORKINGS!$A$116:$A$141,MATCH(SMALL(WORKINGS!$D$116:$D$141,24),WORKINGS!$D$116:$D$141,0)) -> Bartack | C35: =IFERROR(INDEX('MC MASTER'!$C$3:$C$28,MATCH($B35,'MC MASTER'!$B$3:$B$28,0)),0) -> 13 | D35: =IFERROR(INDEX('MC MAP'!$D$113:$AC$113,MATCH($B35,'MC MAP'!$D$86:$AC$86,0)),0) -> 4.5 | E35: =C35-D35 -> 8.5 | F35: =IF($D35=0,"IDLE",IF($E35<0,"SHORT",IF($E35/$C35<=0.1,"TIGHT","OK"))) -> OK | G35: =IFERROR($D35/$C35,"") -> 0.34615385 | H35: =IF($E35>=0,WORKINGS!$N35,IF(WORKINGS!$Q35<=0,WORKINGS!$N35&" — no spare, BUY "&TEXT(WORKINGS!$R35,"#,##0.0"),IF(WORKINGS!$R35<=0,WORKINGS!$N35&" — MOVE "&TEXT(WORKINGS!$Q35,"#,##0.0"),WORKINGS!$N35&" — MOVE "&TEXT(WORKINGS!$Q35,"#,##0.0")&", BUY "&TEXT(WORKINGS!$R35,"#,##0.0")))) -> BTK
B36: =INDEX(WORKINGS!$A$116:$A$141,MATCH(SMALL(WORKINGS!$D$116:$D$141,25),WORKINGS!$D$116:$D$141,0)) -> Bartack Pattern tacker (LABEL ATTACH ) | C36: =IFERROR(INDEX('MC MASTER'!$C$3:$C$28,MATCH($B36,'MC MASTER'!$B$3:$B$28,0)),0) -> 2 | D36: =IFERROR(INDEX('MC MAP'!$D$113:$AC$113,MATCH($B36,'MC MAP'!$D$86:$AC$86,0)),0) -> 0 | E36: =C36-D36 -> 2 | F36: =IF($D36=0,"IDLE",IF($E36<0,"SHORT",IF($E36/$C36<=0.1,"TIGHT","OK"))) -> IDLE | G36: =IFERROR($D36/$C36,"") -> 0 | H36: =IF($E36>=0,WORKINGS!$N36,IF(WORKINGS!$Q36<=0,WORKINGS!$N36&" — no spare, BUY "&TEXT(WORKINGS!$R36,"#,##0.0"),IF(WORKINGS!$R36<=0,WORKINGS!$N36&" — MOVE "&TEXT(WORKINGS!$Q36,"#,##0.0"),WORKINGS!$N36&" — MOVE "&TEXT(WORKINGS!$Q36,"#,##0.0")&", BUY "&TEXT(WORKINGS!$R36,"#,##0.0")))) -> PATTERN-TACKER
B37: =INDEX(WORKINGS!$A$116:$A$141,MATCH(SMALL(WORKINGS!$D$116:$D$141,26),WORKINGS!$D$116:$D$141,0)) -> Bartack Pattern tacker | C37: =IFERROR(INDEX('MC MASTER'!$C$3:$C$28,MATCH($B37,'MC MASTER'!$B$3:$B$28,0)),0) -> 35 | D37: =IFERROR(INDEX('MC MAP'!$D$113:$AC$113,MATCH($B37,'MC MAP'!$D$86:$AC$86,0)),0) -> 29 | E37: =C37-D37 -> 6 | F37: =IF($D37=0,"IDLE",IF($E37<0,"SHORT",IF($E37/$C37<=0.1,"TIGHT","OK"))) -> OK | G37: =IFERROR($D37/$C37,"") -> 0.82857143 | H37: =IF($E37>=0,WORKINGS!$N37,IF(WORKINGS!$Q37<=0,WORKINGS!$N37&" — no spare, BUY "&TEXT(WORKINGS!$R37,"#,##0.0"),IF(WORKINGS!$R37<=0,WORKINGS!$N37&" — MOVE "&TEXT(WORKINGS!$Q37,"#,##0.0"),WORKINGS!$N37&" — MOVE "&TEXT(WORKINGS!$Q37,"#,##0.0")&", BUY "&TEXT(WORKINGS!$R37,"#,##0.0")))) -> PATTERN-TACKER
B38: TOTAL | C38: =SUM(C12:C37) -> 920 | D38: =SUM(D12:D37) -> 808 | E38: =C38-D38 -> 112 | G38: =IFERROR(D38/C38,"") -> 0.87826087
B40: LINE LOADING (26 SEWING LINES)
B41: Line | C41: Style | D41: Machines req. | E41: Output pcs/day | F41: Pcs per machine | G41: Status | H41: Garment type
B42: ='MC MAP'!A89 -> 3 | C42: ='MC MAP'!C89 -> 6137 | D42: ='MC MAP'!AD89 -> 29 | E42: ='MC MAP'!AE89 -> 3500 | F42: =IFERROR($E42/$D42,"-") -> 120.68966 | G42: ='MC MAP'!AF89 -> OK | H42: ='MC MAP'!AH89 -> BRIEF
B43: ='MC MAP'!A93 -> 7 | C43: ='MC MAP'!C93 -> 6137 | D43: ='MC MAP'!AD93 -> 29 | E43: ='MC MAP'!AE93 -> 3500 | F43: =IFERROR($E43/$D43,"-") -> 120.68966 | G43: ='MC MAP'!AF93 -> OK | H43: ='MC MAP'!AH93 -> BRIEF
B44: ='MC MAP'!A99 -> 13 | C44: ='MC MAP'!C99 -> RS-17 | D44: ='MC MAP'!AD99 -> 30 | E44: ='MC MAP'!AE99 -> 2000 | F44: =IFERROR($E44/$D44,"-") -> 66.666667 | G44: ='MC MAP'!AF99 -> OK | H44: ='MC MAP'!AH99 -> BRIEF
B45: ='MC MAP'!A100 -> 14 | C45: ='MC MAP'!C100 -> 6137 | D45: ='MC MAP'!AD100 -> 29 | E45: ='MC MAP'!AE100 -> 3500 | F45: =IFERROR($E45/$D45,"-") -> 120.68966 | G45: ='MC MAP'!AF100 -> OK | H45: ='MC MAP'!AH100 -> BRIEF
B46: ='MC MAP'!A101 -> 15 | C46: ='MC MAP'!C101 -> 6135 | D46: ='MC MAP'!AD101 -> 33.5 | E46: ='MC MAP'!AE101 -> 3500 | F46: =IFERROR($E46/$D46,"-") -> 104.47761 | G46: ='MC MAP'!AF101 -> OK | H46: ='MC MAP'!AH101 -> BRIEF
B47: ='MC MAP'!A106 -> 20 | C47: ='MC MAP'!C106 -> 6137 | D47: ='MC MAP'!AD106 -> 29 | E47: ='MC MAP'!AE106 -> 3500 | F47: =IFERROR($E47/$D47,"-") -> 120.68966 | G47: ='MC MAP'!AF106 -> OK | H47: ='MC MAP'!AH106 -> BRIEF
B48: ='MC MAP'!A107 -> 21 | C48: ='MC MAP'!C107 -> 6137 | D48: ='MC MAP'!AD107 -> 29 | E48: ='MC MAP'!AE107 -> 3500 | F48: =IFERROR($E48/$D48,"-") -> 120.68966 | G48: ='MC MAP'!AF107 -> OK | H48: ='MC MAP'!AH107 -> BRIEF
B49: ='MC MAP'!A109 -> 23 | C49: ='MC MAP'!C109 -> 6135 | D49: ='MC MAP'!AD109 -> 33.5 | E49: ='MC MAP'!AE109 -> 3500 | F49: =IFERROR($E49/$D49,"-") -> 104.47761 | G49: ='MC MAP'!AF109 -> OK | H49: ='MC MAP'!AH109 -> BRIEF
B50: ='MC MAP'!A112 -> 26 | C50: ='MC MAP'!C112 -> 6135 | D50: ='MC MAP'!AD112 -> 33.5 | E50: ='MC MAP'!AE112 -> 3500 | F50: =IFERROR($E50/$D50,"-") -> 104.47761 | G50: ='MC MAP'!AF112 -> OK | H50: ='MC MAP'!AH112 -> BRIEF
B51: ='MC MAP'!A94 -> 8 | C51: ='MC MAP'!C94 -> 6109 | D51: ='MC MAP'!AD94 -> 30 | E51: ='MC MAP'!AE94 -> 3500 | F51: =IFERROR($E51/$D51,"-") -> 116.66667 | G51: ='MC MAP'!AF94 -> OK | H51: ='MC MAP'!AH94 -> TRUNK
B52: ='MC MAP'!A95 -> 9 | C52: ='MC MAP'!C95 -> 6109 | D52: ='MC MAP'!AD95 -> 30 | E52: ='MC MAP'!AE95 -> 3500 | F52: =IFERROR($E52/$D52,"-") -> 116.66667 | G52: ='MC MAP'!AF95 -> OK | H52: ='MC MAP'!AH95 -> TRUNK
B53: ='MC MAP'!A96 -> 10 | C53: ='MC MAP'!C96 -> 6109 | D53: ='MC MAP'!AD96 -> 30 | E53: ='MC MAP'!AE96 -> 3500 | F53: =IFERROR($E53/$D53,"-") -> 116.66667 | G53: ='MC MAP'!AF96 -> OK | H53: ='MC MAP'!AH96 -> TRUNK
B54: ='MC MAP'!A97 -> 11 | C54: ='MC MAP'!C97 -> 6108 | D54: ='MC MAP'!AD97 -> 31.5 | E54: ='MC MAP'!AE97 -> 3500 | F54: =IFERROR($E54/$D54,"-") -> 111.11111 | G54: ='MC MAP'!AF97 -> OK | H54: ='MC MAP'!AH97 -> TRUNK
B55: ='MC MAP'!A98 -> 12 | C55: ='MC MAP'!C98 -> 6108 | D55: ='MC MAP'!AD98 -> 31.5 | E55: ='MC MAP'!AE98 -> 3500 | F55: =IFERROR($E55/$D55,"-") -> 111.11111 | G55: ='MC MAP'!AF98 -> OK | H55: ='MC MAP'!AH98 -> TRUNK
B56: ='MC MAP'!A103 -> 17 | C56: ='MC MAP'!C103 -> 4117 | D56: ='MC MAP'!AD103 -> 30.5 | E56: ='MC MAP'!AE103 -> 3000 | F56: =IFERROR($E56/$D56,"-") -> 98.360656 | G56: ='MC MAP'!AF103 -> OK | H56: ='MC MAP'!AH103 -> TRUNK
B57: ='MC MAP'!A104 -> 18 | C57: ='MC MAP'!C104 -> 4117 | D57: ='MC MAP'!AD104 -> 30.5 | E57: ='MC MAP'!AE104 -> 3000 | F57: =IFERROR($E57/$D57,"-") -> 98.360656 | G57: ='MC MAP'!AF104 -> OK | H57: ='MC MAP'!AH104 -> TRUNK
B58: ='MC MAP'!A105 -> 19 | C58: ='MC MAP'!C105 -> 4115 | D58: ='MC MAP'!AD105 -> 33.5 | E58: ='MC MAP'!AE105 -> 3000 | F58: =IFERROR($E58/$D58,"-") -> 89.552239 | G58: ='MC MAP'!AF105 -> OK | H58: ='MC MAP'!AH105 -> TRUNK
B59: ='MC MAP'!A90 -> 4 | C59: ='MC MAP'!C90 -> RS-27 | D59: ='MC MAP'!AD90 -> 25 | E59: ='MC MAP'!AE90 -> 3000 | F59: =IFERROR($E59/$D59,"-") -> 120 | G59: ='MC MAP'!AF90 -> OK | H59: ='MC MAP'!AH90 -> VEST
B60: ='MC MAP'!A91 -> 5 | C60: ='MC MAP'!C91 -> 6820 | D60: ='MC MAP'!AD91 -> 32 | E60: ='MC MAP'!AE91 -> 5000 | F60: =IFERROR($E60/$D60,"-") -> 156.25 | G60: ='MC MAP'!AF91 -> OK | H60: ='MC MAP'!AH91 -> VEST
B61: ='MC MAP'!A92 -> 6 | C61: ='MC MAP'!C92 -> 6820 | D61: ='MC MAP'!AD92 -> 32 | E61: ='MC MAP'!AE92 -> 5000 | F61: =IFERROR($E61/$D61,"-") -> 156.25 | G61: ='MC MAP'!AF92 -> OK | H61: ='MC MAP'!AH92 -> VEST
B62: ='MC MAP'!A102 -> 16 | C62: ='MC MAP'!C102 -> Panty | D62: ='MC MAP'!AD102 -> 29.5 | E62: ='MC MAP'!AE102 -> 5000 | F62: =IFERROR($E62/$D62,"-") -> 169.49153 | G62: ='MC MAP'!AF102 -> OK | H62: ='MC MAP'!AH102 -> PANTY
B63: ='MC MAP'!A88 -> 2 | C63: ='MC MAP'!C88 -> 4300 | D63: ='MC MAP'!AD88 -> 37.5 | E63: ='MC MAP'!AE88 -> 1000 | F63: =IFERROR($E63/$D63,"-") -> 26.666667 | G63: ='MC MAP'!AF88 -> OK | H63: ='MC MAP'!AH88 -> PAJAMA
B64: ='MC MAP'!A108 -> 22 | C64: ='MC MAP'!C108 -> TH-02 | D64: ='MC MAP'!AD108 -> 28 | E64: ='MC MAP'!AE108 -> 1200 | F64: =IFERROR($E64/$D64,"-") -> 42.857143 | G64: ='MC MAP'!AF108 -> OK | H64: ='MC MAP'!AH108 -> THERMAL
B65: ='MC MAP'!A110 -> 24 | C65: ='MC MAP'!C110 -> 5520 | D65: ='MC MAP'!AD110 -> 32 | E65: ='MC MAP'!AE110 -> 2000 | F65: =IFERROR($E65/$D65,"-") -> 62.5 | G65: ='MC MAP'!AF110 -> OK | H65: ='MC MAP'!AH110 -> THERMAL
B66: ='MC MAP'!A111 -> 25 | C66: ='MC MAP'!C111 -> 5520 | D66: ='MC MAP'!AD111 -> 32 | E66: ='MC MAP'!AE111 -> 2000 | F66: =IFERROR($E66/$D66,"-") -> 62.5 | G66: ='MC MAP'!AF111 -> OK | H66: ='MC MAP'!AH111 -> THERMAL
B67: ='MC MAP'!A87 -> 1 | C67: ='MC MAP'!C87 -> 7926 | D67: ='MC MAP'!AD87 -> 37 | E67: ='MC MAP'!AE87 -> 1000 | F67: =IFERROR($E67/$D67,"-") -> 27.027027 | G67: ='MC MAP'!AF87 -> OK | H67: ='MC MAP'!AH87 -> SHORTS
B68: TOTAL | D68: =SUM(D42:D67) -> 808 | E68: =SUM(E42:E67) -> 81700 | F68: =IFERROR(E68/D68,"-") -> 101.11386
B70: ="MACHINES AND OUTPUT BY GARMENT TYPE ON "&UPPER(TEXT(WORKINGS!$B$75,"ddd d-mmm-yyyy")) -> MACHINES AND OUTPUT BY GARMENT TYPE ON SAT 8-AUG-2026 | I70: ="MACHINES ENGAGED IN ONE GARMENT ON "&UPPER(TEXT(WORKINGS!$B$75,"ddd d-mmm-yyyy")) -> MACHINES ENGAGED IN ONE GARMENT ON SAT 8-AUG-2026
B71: Garment type | C71: Lines | D71: Machines req. | E71: Output pcs/day | F71: % of machines | G71: Check | I71: Pick a garment ▾ | K71: TRUNK | M71: of installed
B72: ='MC MAP'!$AJ33 -> BRIEF | C72: =COUNTIF($H$42:$H$67,$B72) -> 9 | D72: =SUMIF($H$42:$H$67,$B72,$D$42:$D$67) -> 275.5 | E72: =SUMIF($H$42:$H$67,$B72,$E$42:$E$67) -> 30000 | F72: =IFERROR($D72/$D$80,"-") -> 0.34096535 | I72: Machine group | J72: Machines | K72: Share | L72: Installed | M72: % of group
B73: ='MC MAP'!$AJ34 -> TRUNK | C73: =COUNTIF($H$42:$H$67,$B73) -> 8 | D73: =SUMIF($H$42:$H$67,$B73,$D$42:$D$67) -> 247.5 | E73: =SUMIF($H$42:$H$67,$B73,$E$42:$E$67) -> 26500 | F73: =IFERROR($D73/$D$80,"-") -> 0.30631188 | I73: =IFERROR(IF(LARGE(WORKINGS!$C$41:$C$66,ROW()-72)<=0,"",INDEX(WORKINGS!$A$41:$A$66,MATCH(LARGE(WORKINGS!$C$41:$C$66,ROW()-72),WORKINGS!$C$41:$C$66,0))),"") -> 4th Overlock | J73: =IF($I73="","",INDEX(WORKINGS!$B$41:$B$66,MATCH($I73,WORKINGS!$A$41:$A$66,0))) -> 76 | K73: =IFERROR(IF($I73="","",$J73/INDEX('MC MAP'!$CB$35:$CB$42,MATCH($K$71,'MC MAP'!$BA$35:$BA$42,0))),"") -> 0.30707071 | L73: =IFERROR(IF($I73="","",INDEX('MC MASTER'!$C$3:$C$28,MATCH($I73,'MC MASTER'!$B$3:$B$28,0))),"") -> 279 | M73: =IFERROR(IF($I73="","",$J73/$L73),"") -> 0.27240143
B74: ='MC MAP'!$AJ35 -> VEST | C74: =COUNTIF($H$42:$H$67,$B74) -> 3 | D74: =SUMIF($H$42:$H$67,$B74,$D$42:$D$67) -> 89 | E74: =SUMIF($H$42:$H$67,$B74,$E$42:$E$67) -> 13000 | F74: =IFERROR($D74/$D$80,"-") -> 0.11014851 | I74: =IFERROR(IF(LARGE(WORKINGS!$C$41:$C$66,ROW()-72)<=0,"",INDEX(WORKINGS!$A$41:$A$66,MATCH(LARGE(WORKINGS!$C$41:$C$66,ROW()-72),WORKINGS!$C$41:$C$66,0))),"") -> SNLS | J74: =IF($I74="","",INDEX(WORKINGS!$B$41:$B$66,MATCH($I74,WORKINGS!$A$41:$A$66,0))) -> 47 | K74: =IFERROR(IF($I74="","",$J74/INDEX('MC MAP'!$CB$35:$CB$42,MATCH($K$71,'MC MAP'!$BA$35:$BA$42,0))),"") -> 0.18989899 | L74: =IFERROR(IF($I74="","",INDEX('MC MASTER'!$C$3:$C$28,MATCH($I74,'MC MASTER'!$B$3:$B$28,0))),"") -> 185 | M74: =IFERROR(IF($I74="","",$J74/$L74),"") -> 0.25405405
B75: ='MC MAP'!$AJ36 -> THERMAL | C75: =COUNTIF($H$42:$H$67,$B75) -> 3 | D75: =SUMIF($H$42:$H$67,$B75,$D$42:$D$67) -> 92 | E75: =SUMIF($H$42:$H$67,$B75,$E$42:$E$67) -> 5200 | F75: =IFERROR($D75/$D$80,"-") -> 0.11386139 | I75: =IFERROR(IF(LARGE(WORKINGS!$C$41:$C$66,ROW()-72)<=0,"",INDEX(WORKINGS!$A$41:$A$66,MATCH(LARGE(WORKINGS!$C$41:$C$66,ROW()-72),WORKINGS!$C$41:$C$66,0))),"") -> 3N5T-F/L -( TopStitch) | J75: =IF($I75="","",INDEX(WORKINGS!$B$41:$B$66,MATCH($I75,WORKINGS!$A$41:$A$66,0))) -> 29 | K75: =IFERROR(IF($I75="","",$J75/INDEX('MC MAP'!$CB$35:$CB$42,MATCH($K$71,'MC MAP'!$BA$35:$BA$42,0))),"") -> 0.11717172 | L75: =IFERROR(IF($I75="","",INDEX('MC MASTER'!$C$3:$C$28,MATCH($I75,'MC MASTER'!$B$3:$B$28,0))),"") -> 54 | M75: =IFERROR(IF($I75="","",$J75/$L75),"") -> 0.53703704
B76: ='MC MAP'!$AJ37 -> SHORTS | C76: =COUNTIF($H$42:$H$67,$B76) -> 1 | D76: =SUMIF($H$42:$H$67,$B76,$D$42:$D$67) -> 37 | E76: =SUMIF($H$42:$H$67,$B76,$E$42:$E$67) -> 1000 | F76: =IFERROR($D76/$D$80,"-") -> 0.045792079 | I76: =IFERROR(IF(LARGE(WORKINGS!$C$41:$C$66,ROW()-72)<=0,"",INDEX(WORKINGS!$A$41:$A$66,MATCH(LARGE(WORKINGS!$C$41:$C$66,ROW()-72),WORKINGS!$C$41:$C$66,0))),"") -> Overlock (Ring Elastic Attach) | J76: =IF($I76="","",INDEX(WORKINGS!$B$41:$B$66,MATCH($I76,WORKINGS!$A$41:$A$66,0))) -> 18 | K76: =IFERROR(IF($I76="","",$J76/INDEX('MC MAP'!$CB$35:$CB$42,MATCH($K$71,'MC MAP'!$BA$35:$BA$42,0))),"") -> 0.072727273 | L76: =IFERROR(IF($I76="","",INDEX('MC MASTER'!$C$3:$C$28,MATCH($I76,'MC MASTER'!$B$3:$B$28,0))),"") -> 29 | M76: =IFERROR(IF($I76="","",$J76/$L76),"") -> 0.62068966
B77: ='MC MAP'!$AJ38 -> PAJAMA | C77: =COUNTIF($H$42:$H$67,$B77) -> 1 | D77: =SUMIF($H$42:$H$67,$B77,$D$42:$D$67) -> 37.5 | E77: =SUMIF($H$42:$H$67,$B77,$E$42:$E$67) -> 1000 | F77: =IFERROR($D77/$D$80,"-") -> 0.046410891 | I77: =IFERROR(IF(LARGE(WORKINGS!$C$41:$C$66,ROW()-72)<=0,"",INDEX(WORKINGS!$A$41:$A$66,MATCH(LARGE(WORKINGS!$C$41:$C$66,ROW()-72),WORKINGS!$C$41:$C$66,0))),"") -> 3N5T-F/L -BINDING | J77: =IF($I77="","",INDEX(WORKINGS!$B$41:$B$66,MATCH($I77,WORKINGS!$A$41:$A$66,0))) -> 17 | K77: =IFERROR(IF($I77="","",$J77/INDEX('MC MAP'!$CB$35:$CB$42,MATCH($K$71,'MC MAP'!$BA$35:$BA$42,0))),"") -> 0.068686869 | L77: =IFERROR(IF($I77="","",INDEX('MC MASTER'!$C$3:$C$28,MATCH($I77,'MC MASTER'!$B$3:$B$28,0))),"") -> 58 | M77: =IFERROR(IF($I77="","",$J77/$L77),"") -> 0.29310345
B78: ='MC MAP'!$AJ39 -> PANTY | C78: =COUNTIF($H$42:$H$67,$B78) -> 1 | D78: =SUMIF($H$42:$H$67,$B78,$D$42:$D$67) -> 29.5 | E78: =SUMIF($H$42:$H$67,$B78,$E$42:$E$67) -> 5000 | F78: =IFERROR($D78/$D$80,"-") -> 0.036509901 | I78: =IFERROR(IF(LARGE(WORKINGS!$C$41:$C$66,ROW()-72)<=0,"",INDEX(WORKINGS!$A$41:$A$66,MATCH(LARGE(WORKINGS!$C$41:$C$66,ROW()-72),WORKINGS!$C$41:$C$66,0))),"") -> Flatlock (Ring Elastic Attach) | J78: =IF($I78="","",INDEX(WORKINGS!$B$41:$B$66,MATCH($I78,WORKINGS!$A$41:$A$66,0))) -> 16.5 | K78: =IFERROR(IF($I78="","",$J78/INDEX('MC MAP'!$CB$35:$CB$42,MATCH($K$71,'MC MAP'!$BA$35:$BA$42,0))),"") -> 0.066666667 | L78: =IFERROR(IF($I78="","",INDEX('MC MASTER'!$C$3:$C$28,MATCH($I78,'MC MASTER'!$B$3:$B$28,0))),"") -> 42 | M78: =IFERROR(IF($I78="","",$J78/$L78),"") -> 0.39285714
B79: (not set) / no work | C79: =COUNTA($H$42:$H$67)-SUM($C$72:$C$78) -> 0 | D79: =$D$68-SUM($D$72:$D$78) -> 0 | E79: =$E$68-SUM($E$72:$E$78) -> 0 | F79: =IFERROR($D79/$D$80,"-") -> 0 | I79: =IFERROR(IF(LARGE(WORKINGS!$C$41:$C$66,ROW()-72)<=0,"",INDEX(WORKINGS!$A$41:$A$66,MATCH(LARGE(WORKINGS!$C$41:$C$66,ROW()-72),WORKINGS!$C$41:$C$66,0))),"") -> Bartack Pattern tacker | J79: =IF($I79="","",INDEX(WORKINGS!$B$41:$B$66,MATCH($I79,WORKINGS!$A$41:$A$66,0))) -> 14 | K79: =IFERROR(IF($I79="","",$J79/INDEX('MC MAP'!$CB$35:$CB$42,MATCH($K$71,'MC MAP'!$BA$35:$BA$42,0))),"") -> 0.056565657 | L79: =IFERROR(IF($I79="","",INDEX('MC MASTER'!$C$3:$C$28,MATCH($I79,'MC MASTER'!$B$3:$B$28,0))),"") -> 35 | M79: =IFERROR(IF($I79="","",$J79/$L79),"") -> 0.4
B80: TOTAL | C80: =SUM($C$72:$C$79) -> 26 | D80: =SUM($D$72:$D$79) -> 808 | E80: =SUM($E$72:$E$79) -> 81700 | F80: =IFERROR($D80/$D$80,"-") -> 1 | G80: =IF(AND($C80=COUNTA($B$42:$B$67),ABS($D80-$D$68)<0.01,ABS($E80-$E$68)<0.01),"TIES TO LINE TABLE","** DOES NOT TIE — check the garment list **") -> TIES TO LINE TABLE | I80: ="TOTAL "&$K$71&" — all "&COUNTIF(WORKINGS!$B$41:$B$66,">0")&" groups used" -> TOTAL TRUNK — all 12 groups used | J80: =IFERROR(INDEX('MC MAP'!$CB$35:$CB$42,MATCH($K$71,'MC MAP'!$BA$35:$BA$42,0)),0) -> 247.5 | K80: =IFERROR($J80/$J80,"") -> 1 | L80: =IFERROR(INDEX('MC MAP'!$CC$35:$CC$42,MATCH($K$71,'MC MAP'!$BA$35:$BA$42,0))&" lines","") -> 8 lines | M80: =IFERROR(IF($J80=0,"",$J80/'MC MASTER'!$C$29),"") -> 0.26902174
B81: PEAK MACHINE DEMAND ACROSS THE WHOLE 105-DAY PLAN — buy against these numbers, not against today
B83: Machine group | C83: Installed | D83: Today | E83: Peak req. | F83: Peak date | G83: Gap at peak | H83: Verdict
B84: =$B12 -> SNLS | C84: =$C12 -> 185 | D84: =$D12 -> 152 | E84: =MAX(INDEX('DEMAND BY DATE'!$B$4:$AA$203,0,MATCH($B84,'DEMAND BY DATE'!$B$3:$AA$3,0))) -> 152 | F84: =IF($E84=0,"—",IFERROR(INDEX('DEMAND BY DATE'!$A$4:$A$203,MATCH($E84,INDEX('DEMAND BY DATE'!$B$4:$AA$203,0,MATCH($B84,'DEMAND BY DATE'!$B$3:$AA$3,0)),0)),"")) -> 46235 | G84: =$C84-$E84 -> 33 | H84: =IF($E84=0,"IDLE ALL PLAN",IF($G84<0,"BUY "&TEXT(-$G84,"#,##0.0"),IF($G84/$C84<=0.1,"TIGHT","OK"))) -> OK
B85: =$B13 -> DNLS | C85: =$C13 -> 8 | D85: =$D13 -> 1 | E85: =MAX(INDEX('DEMAND BY DATE'!$B$4:$AA$203,0,MATCH($B85,'DEMAND BY DATE'!$B$3:$AA$3,0))) -> 1 | F85: =IF($E85=0,"—",IFERROR(INDEX('DEMAND BY DATE'!$A$4:$A$203,MATCH($E85,INDEX('DEMAND BY DATE'!$B$4:$AA$203,0,MATCH($B85,'DEMAND BY DATE'!$B$3:$AA$3,0)),0)),"")) -> 46235 | G85: =$C85-$E85 -> 7 | H85: =IF($E85=0,"IDLE ALL PLAN",IF($G85<0,"BUY "&TEXT(-$G85,"#,##0.0"),IF($G85/$C85<=0.1,"TIGHT","OK"))) -> OK
B86: =$B14 -> SNLS - Edge cutter | C86: =$C14 -> 2 | D86: =$D14 -> 0 | E86: =MAX(INDEX('DEMAND BY DATE'!$B$4:$AA$203,0,MATCH($B86,'DEMAND BY DATE'!$B$3:$AA$3,0))) -> 0 | F86: =IF($E86=0,"—",IFERROR(INDEX('DEMAND BY DATE'!$A$4:$A$203,MATCH($E86,INDEX('DEMAND BY DATE'!$B$4:$AA$203,0,MATCH($B86,'DEMAND BY DATE'!$B$3:$AA$3,0)),0)),"")) -> — | G86: =$C86-$E86 -> 2 | H86: =IF($E86=0,"IDLE ALL PLAN",IF($G86<0,"BUY "&TEXT(-$G86,"#,##0.0"),IF($G86/$C86<=0.1,"TIGHT","OK"))) -> IDLE ALL PLAN
B87: =$B15 -> Zig - Zag | C87: =$C15 -> 8 | D87: =$D15 -> 4 | E87: =MAX(INDEX('DEMAND BY DATE'!$B$4:$AA$203,0,MATCH($B87,'DEMAND BY DATE'!$B$3:$AA$3,0))) -> 4 | F87: =IF($E87=0,"—",IFERROR(INDEX('DEMAND BY DATE'!$A$4:$A$203,MATCH($E87,INDEX('DEMAND BY DATE'!$B$4:$AA$203,0,MATCH($B87,'DEMAND BY DATE'!$B$3:$AA$3,0)),0)),"")) -> 46235 | G87: =$C87-$E87 -> 4 | H87: =IF($E87=0,"IDLE ALL PLAN",IF($G87<0,"BUY "&TEXT(-$G87,"#,##0.0"),IF($G87/$C87<=0.1,"TIGHT","OK"))) -> OK
B88: =$B16 -> 4th Overlock | C88: =$C16 -> 279 | D88: =$D16 -> 291 | E88: =MAX(INDEX('DEMAND BY DATE'!$B$4:$AA$203,0,MATCH($B88,'DEMAND BY DATE'!$B$3:$AA$3,0))) -> 291 | F88: =IF($E88=0,"—",IFERROR(INDEX('DEMAND BY DATE'!$A$4:$A$203,MATCH($E88,INDEX('DEMAND BY DATE'!$B$4:$AA$203,0,MATCH($B88,'DEMAND BY DATE'!$B$3:$AA$3,0)),0)),"")) -> 46235 | G88: =$C88-$E88 -> -12 | H88: =IF($E88=0,"IDLE ALL PLAN",IF($G88<0,"BUY "&TEXT(-$G88,"#,##0.0"),IF($G88/$C88<=0.1,"TIGHT","OK"))) -> BUY 12.0
B89: =$B17 -> 3th Overlock (Leg elastic) | C89: =$C17 -> 30 | D89: =$D17 -> 31 | E89: =MAX(INDEX('DEMAND BY DATE'!$B$4:$AA$203,0,MATCH($B89,'DEMAND BY DATE'!$B$3:$AA$3,0))) -> 31 | F89: =IF($E89=0,"—",IFERROR(INDEX('DEMAND BY DATE'!$A$4:$A$203,MATCH($E89,INDEX('DEMAND BY DATE'!$B$4:$AA$203,0,MATCH($B89,'DEMAND BY DATE'!$B$3:$AA$3,0)),0)),"")) -> 46235 | G89: =$C89-$E89 -> -1 | H89: =IF($E89=0,"IDLE ALL PLAN",IF($G89<0,"BUY "&TEXT(-$G89,"#,##0.0"),IF($G89/$C89<=0.1,"TIGHT","OK"))) -> BUY 1.0
B90: =$B18 -> 5th Overlock | C90: =$C18 -> 5 | D90: =$D18 -> 0 | E90: =MAX(INDEX('DEMAND BY DATE'!$B$4:$AA$203,0,MATCH($B90,'DEMAND BY DATE'!$B$3:$AA$3,0))) -> 0 | F90: =IF($E90=0,"—",IFERROR(INDEX('DEMAND BY DATE'!$A$4:$A$203,MATCH($E90,INDEX('DEMAND BY DATE'!$B$4:$AA$203,0,MATCH($B90,'DEMAND BY DATE'!$B$3:$AA$3,0)),0)),"")) -> — | G90: =$C90-$E90 -> 5 | H90: =IF($E90=0,"IDLE ALL PLAN",IF($G90<0,"BUY "&TEXT(-$G90,"#,##0.0"),IF($G90/$C90<=0.1,"TIGHT","OK"))) -> IDLE ALL PLAN
B91: =$B19 -> Overlock (Ring Elastic Attach) | C91: =$C19 -> 29 | D91: =$D19 -> 36 | E91: =MAX(INDEX('DEMAND BY DATE'!$B$4:$AA$203,0,MATCH($B91,'DEMAND BY DATE'!$B$3:$AA$3,0))) -> 41 | F91: =IF($E91=0,"—",IFERROR(INDEX('DEMAND BY DATE'!$A$4:$A$203,MATCH($E91,INDEX('DEMAND BY DATE'!$B$4:$AA$203,0,MATCH($B91,'DEMAND BY DATE'!$B$3:$AA$3,0)),0)),"")) -> 46286 | G91: =$C91-$E91 -> -12 | H91: =IF($E91=0,"IDLE ALL PLAN",IF($G91<0,"BUY "&TEXT(-$G91,"#,##0.0"),IF($G91/$C91<=0.1,"TIGHT","OK"))) -> BUY 12.0
B92: =$B20 -> Flatlock Hem | C92: =$C20 -> 34 | D92: =$D20 -> 22.5 | E92: =MAX(INDEX('DEMAND BY DATE'!$B$4:$AA$203,0,MATCH($B92,'DEMAND BY DATE'!$B$3:$AA$3,0))) -> 32.5 | F92: =IF($E92=0,"—",IFERROR(INDEX('DEMAND BY DATE'!$A$4:$A$203,MATCH($E92,INDEX('DEMAND BY DATE'!$B$4:$AA$203,0,MATCH($B92,'DEMAND BY DATE'!$B$3:$AA$3,0)),0)),"")) -> 46286 | G92: =$C92-$E92 -> 1.5 | H92: =IF($E92=0,"IDLE ALL PLAN",IF($G92<0,"BUY "&TEXT(-$G92,"#,##0.0"),IF($G92/$C92<=0.1,"TIGHT","OK"))) -> TIGHT
B93: =$B21 -> F/L (Coverseam / Waist COVER SEAM | C93: =$C21 -> 13 | D93: =$D21 -> 4 | E93: =MAX(INDEX('DEMAND BY DATE'!$B$4:$AA$203,0,MATCH($B93,'DEMAND BY DATE'!$B$3:$AA$3,0))) -> 16 | F93: =IF($E93=0,"—",IFERROR(INDEX('DEMAND BY DATE'!$A$4:$A$203,MATCH($E93,INDEX('DEMAND BY DATE'!$B$4:$AA$203,0,MATCH($B93,'DEMAND BY DATE'!$B$3:$AA$3,0)),0)),"")) -> 46272 | G93: =$C93-$E93 -> -3 | H93: =IF($E93=0,"IDLE ALL PLAN",IF($G93<0,"BUY "&TEXT(-$G93,"#,##0.0"),IF($G93/$C93<=0.1,"TIGHT","OK"))) -> BUY 3.0
B94: =$B22 -> F/L (Coverseam )with pullar | C94: =$C22 -> 37 | D94: =$D22 -> 43.5 | E94: =MAX(INDEX('DEMAND BY DATE'!$B$4:$AA$203,0,MATCH($B94,'DEMAND BY DATE'!$B$3:$AA$3,0))) -> 43.5 | F94: =IF($E94=0,"—",IFERROR(INDEX('DEMAND BY DATE'!$A$4:$A$203,MATCH($E94,INDEX('DEMAND BY DATE'!$B$4:$AA$203,0,MATCH($B94,'DEMAND BY DATE'!$B$3:$AA$3,0)),0)),"")) -> 46235 | G94: =$C94-$E94 -> -6.5 | H94: =IF($E94=0,"IDLE ALL PLAN",IF($G94<0,"BUY "&TEXT(-$G94,"#,##0.0"),IF($G94/$C94<=0.1,"TIGHT","OK"))) -> BUY 6.5
B95: =$B23 -> F/L (Coverseam ) | C95: =$C23 -> 6 | D95: =$D23 -> 17 | E95: =MAX(INDEX('DEMAND BY DATE'!$B$4:$AA$203,0,MATCH($B95,'DEMAND BY DATE'!$B$3:$AA$3,0))) -> 33 | F95: =IF($E95=0,"—",IFERROR(INDEX('DEMAND BY DATE'!$A$4:$A$203,MATCH($E95,INDEX('DEMAND BY DATE'!$B$4:$AA$203,0,MATCH($B95,'DEMAND BY DATE'!$B$3:$AA$3,0)),0)),"")) -> 46286 | G95: =$C95-$E95 -> -27 | H95: =IF($E95=0,"IDLE ALL PLAN",IF($G95<0,"BUY "&TEXT(-$G95,"#,##0.0"),IF($G95/$C95<=0.1,"TIGHT","OK"))) -> BUY 27.0
... B109: =$B37 -> Bartack Pattern tacker | C109: =$C37 -> 35 | D109: =$D37 -> 29 | E109: =MAX(INDEX('DEMAND BY DATE'!$B$4:$AA$203,0,MATCH($B109,'DEMAND BY DATE'!$B$3:$AA$3,0))) -> 29 | F109: =IF($E109=0,"—",IFERROR(INDEX('DEMAND BY DATE'!$A$4:$A$203,MATCH($E109,INDEX('DEMAND BY DATE'!$B$4:$AA$203,0,MATCH($B109,'DEMAND BY DATE'!$B$3:$AA$3,0)),0)),"")) -> 46235 | G109: =$C109-$E109 -> 6 | H109: =IF($E109=0,"IDLE ALL PLAN",IF($G109<0,"BUY "&TEXT(-$G109,"#,##0.0"),IF($G109/$C109<=0.1,"TIGHT","OK"))) -> OK
B110: TOTAL / TO BUY AT PEAK | C110: =SUM($C$84:$C$109) -> 920 | F110: peaks fall on different dates — | G110: =-SUMIF($G$84:$G$109,"<0") -> 74.5 | H110: =COUNTIF($H$84:$H$109,"BUY*")&" groups" -> 7 groups
B111: "To buy at peak" is the sum of each group's own worst-day shortfall. Those worst days are not the same date, so this is a procurement ceiling, not a single-day requirement.

Sheet PPC
A1: SUPERSEDED — this painted board is no longer the plan. The live plan is the PLAN DECODED sheet, where styles are typed. Kept for history only; nothing reads from it. | D1: Garment Unit A
D2: Line Planning Chart | G2: M5 | AB2: M6 | BD2: M7 | CF2: M8
D4: Line No | E4: Style | G4: 46235 | H4: 46236 | I4: 46237 | J4: 46238 | K4: 46239 | L4: 46240 | M4: 46241 | N4: 46242 | O4: 46243 | P4: 46244 | Q4: 46245 | R4: 46246 | S4: 46247 | T4: 46248 | U4: 46249 | V4: 46250 | W4: 46251 | X4: 46252 | Y4: 46253 | Z4: 46254 | AA4: 46255 | AB4: 46256 | AC4: 46257 | AD4: 46258 | AE4: 46259 | AF4: 46260 | AG4: 46261 | AH4: 46262 | AI4: 46263 | AJ4: 46264 | AK4: 46265 | AL4: 46266 | AM4: 46267 | AN4: 46268 | AO4: 46269 | AP4: 46270 | AQ4: 46271 | AR4: 46272 | AS4: 46273 | AT4: 46274 | AU4: 46275 | AV4: 46276 | AW4: 46277 | AX4: 46278 | AY4: 46279 | AZ4: 46280 | BA4: 46281 | BB4: 46282 | BC4: 46283 | BD4: 46284 | BE4: 46285 | BF4: 46286 | BG4: 46287 | BH4: 46288 | BI4: 46289 | BJ4: 46290 | BK4: 46291 | BL4: 46292 | BM4: 46293 | BN4: 46294 | BO4: 46295 | BP4: 46296 | BQ4: 46297 | BR4: 46298 | BS4: 46299 | BT4: 46300 | BU4: 46301 | BV4: 46302 | BW4: 46303 | BX4: 46304 | BY4: 46305 | BZ4: 46306 | CA4: 46307 | CB4: 46308 | CC4: 46309 | CD4: 46310 | CE4: 46311 | CF4: 46312 | CG4: 46313 | CH4: 46314 | CI4: 46315 | CJ4: 46316 | CK4: 46317 | CL4: 46318 | CM4: 46319 | CN4: 46320 | CO4: 46321 | CP4: 46322 | CQ4: 46323 | CR4: 46324 | CS4: 46325 | CT4: 46326 | CU4: 46327 | CV4: 46328 | CW4: 46329 | CX4: 46330 | CY4: 46331 | CZ4: 46332 | DA4: 46333 | DB4: 46334 | DC4: 46335 | DD4: 46336 | DE4: 46337 | DF4: 46338 | DG4: 46339
A5: STYLES | B5: COLOUR CODES | D5: 1 | E5: 7926 | F5: 7926
A6: 7926 | D6: 2 | E6: 4300/4301 | F6: 4300/4301
A7: 4300/4301 | D7: 3 | E7: 6137 | F7: 6137 | U7: 4110
A8: RS 26/27 | D8: 4 | E8: RS26/27 | F8: RS26/27
A9: 6820 | D9: 5 | E9: RS26/27 | F9: 6820
A10: 6108 | D10: 6 | E10: 6820 | F10: 6820
A11: 6109 | D11: 7 | E11: 6137 | F11: 6137 | U11: RS 17 | AT11: 4117
A12: 4117 | D12: 8 | E12: 6109 | F12: 6109
A13: 4406/10 | D13: 9 | E13: 6109 | F13: 6109
A14: 4115 | D14: 10 | E14: 6109 | F14: 6109
A15: RS17 | D15: 11 | E15: 6108 | F15: 6108 | AZ15: 4117
A16: 6135 | D16: 12 | E16: 6108 | F16: 6108 | AZ16: 4117
A17: THERMAL | D17: 13 | E17: RS17 | F17: RS17 | BF17: 4117
A18: VACCANT | D18: 14 | E18: 6137 | F18: 6137 | U18: 4406/10
A19: 6137 | D19: 15 | E19: 6135 | F19: 6135
A20: 4110 | D20: 16 | E20: 4406/4410 | F20: 4406/4410
D21: 17 | E21: 4117 | F21: 4117
D22: 18 | E22: 4117 | F22: 4117
D23: 19 | E23: 4115 | F23: 4115
D24: 20 | E24: 6137 | F24: 6137 | AZ24: 6109
D25: 21 | E25: 6137 | F25: 6137 | U25: RS 17 | BF25: 4117
D26: 22 | E26: TH01/02 | F26: TH04
D27: 23 | E27: 6135 | F27: 6135 | AR27: 4406/10 | BI27: 6137
D28: 24 | E28: 5520 | F28: 5520
D29: 25 | E29: 5520 | F29: 5520
D30: 26 | E30: 6135 | F30: 6135 | AR30: TH02

Sheet LINE PLAN
A1: LINE PLAN — MASTER
A2: PLAN START | B2: 46235 | C2: ◄ CHANGE THIS to shift the whole plan to a different start date | HA2: {=IF(SUMPRODUCT(($B$36:$GS$61<>"")*(COUNTIF('MC MAP'!$A$33:$A$80,$B$36:$GS$61)=0))=0,"ALL PLANNED STYLES CAN BE PRICED","** "&SUMPRODUCT(($B$36:$GS$61<>"")*(COUNTIF('MC MAP'!$A$33:$A$80,$B$36:$GS$61)=0))&" PLANNED CELLS USE A STYLE WITH NO MACHINE RECIPE — THEY ARE NOT COSTED **")} -> ALL PLANNED STYLES CAN BE PRICED
A3: DAYS IN PLAN | B3: 105 | C3: ◄ CHANGE THIS to add or remove days (max 200). The date row is calculated and cannot be typed into. | HA3: PLAN STYLE LIST — drives the pricing matrix. DO NOT overwrite. | HE3: VALIDATION LIST
A4: 1. THE PLAN — type or pick a style in every working cell | GX4: COLOUR LEGEND USED | HA4: Style | HB4: Light fill | HC4: Original board colour | HE4: Style
A5: Line | B5: =IF(COLUMN()-1>$B$3,0,$B$2+COLUMN()-2) -> 46235 | C5: =IF(COLUMN()-1>$B$3,0,$B$2+COLUMN()-2) -> 46236 | D5: =IF(COLUMN()-1>$B$3,0,$B$2+COLUMN()-2) -> 46237 | E5: =IF(COLUMN()-1>$B$3,0,$B$2+COLUMN()-2) -> 46238 | F5: =IF(COLUMN()-1>$B$3,0,$B$2+COLUMN()-2) -> 46239 | G5: =IF(COLUMN()-1>$B$3,0,$B$2+COLUMN()-2) -> 46240 | H5: =IF(COLUMN()-1>$B$3,0,$B$2+COLUMN()-2) -> 46241 | I5: =IF(COLUMN()-1>$B$3,0,$B$2+COLUMN()-2) -> 46242 | ... GS5: =IF(COLUMN()-1>$B$3,0,$B$2+COLUMN()-2) -> 0 | GX5: Hex | GY5: Style / status | GZ5: Swatch | HA5: 7926 | HC5: #FF33CC | HE5: 6135
A6: 1 | B6: 7926 | C6: 7926 | D6: 7926 | E6: 7926 | F6: 7926 | G6: 7926 | H6: 7926 | I6: 7926 | J6: 7926 | K6: 7926 | L6: 7926 | M6: 7926 | N6: 7926 | O6: 7926 | P6: 7926 | Q6: 7926 | R6: 7926 | S6: 7926 | T6: 7926 | U6: 7926 | V6: 7926 | W6: 7926 | X6: 7926 | Y6: 7926 | Z6: 7926 | AA6: 7926 | AB6: 7926 | AC6: 7926 | AD6: 7926 | AE6: 7926 | AF6: 7926 | AG6: 7926 | AH6: 7926 | AI6: 7926 | AJ6: 7926 | AK6: 7926 | AL6: 7926 | AM6: 7926 | AN6: 7926 | AO6: 7926 | AP6: 7926 | AQ6: 7926 | AR6: 7926 | AS6: 7926 | AT6: 7926 | AU6: 7926 | AV6: 7926 | AW6: 7926 | AX6: 7926 | AY6: 7926 | AZ6: 7926 | BA6: 7926 | BB6: 7926 | BC6: 7926 | BD6: 7926 | BE6: 7926 | BF6: 7926 | BG6: 7926 | BH6: 7926 | BI6: 7926 | BJ6: 7926 | BK6: 7926 | BL6: 7926 | BM6: 7926 | BN6: 7926 | BO6: 7926 | BP6: 7926 | BQ6: 7926 | BR6: 7926 | BS6: 7926 | BT6: 7926 | BU6: 7926 | BV6: 7926 | BW6: 7926 | BX6: 7926 | BY6: 7926 | BZ6: 7926 | CA6: 7926 | CB6: 7926 | CC6: 7926 | CD6: 7926 | CE6: 7926 | CF6: VACCANT | GX6: #FF33CC | GY6: 7926 | HA6: 4300/4301 | HC6: #CC0000 | HE6: 6137
A7: 2 | B7: 4300/4301 | C7: 4300/4301 | D7: 4300/4301 | E7: 4300/4301 | F7: 4300/4301 | G7: 4300/4301 | H7: 4300/4301 | I7: 4300/4301 | J7: 4300/4301 | K7: 4300/4301 | L7: 4300/4301 | M7: 4300/4301 | N7: 4300/4301 | O7: 4300/4301 | P7: 4300/4301 | Q7: 4300/4301 | R7: 4300/4301 | S7: 4300/4301 | T7: 4300/4301 | U7: 4300/4301 | V7: 4300/4301 | W7: 4300/4301 | X7: 4300/4301 | Y7: 4300/4301 | Z7: 4300/4301 | AA7: 4300/4301 | AB7: 4300/4301 | AC7: 4300/4301 | AD7: 4300/4301 | AE7: 4300/4301 | AF7: 4300/4301 | AG7: 4300/4301 | AH7: 4300/4301 | AI7: 4300/4301 | AJ7: 4300/4301 | AK7: 4300/4301 | AL7: 4300/4301 | AM7: 4300/4301 | AN7: 4300/4301 | AO7: 4300/4301 | AP7: 4300/4301 | AQ7: 4300/4301 | AR7: 4300/4301 | AS7: 4300/4301 | AT7: 4300/4301 | AU7: 4300/4301 | AV7: 4300/4301 | AW7: 4300/4301 | AX7: 4300/4301 | AY7: 4300/4301 | AZ7: 4300/4301 | BA7: 4300/4301 | BB7: 4300/4301 | BC7: 4300/4301 | BD7: 4300/4301 | BE7: 4300/4301 | BF7: 4300/4301 | BG7: 4300/4301 | BH7: 4300/4301 | BI7: 4300/4301 | BJ7: 4300/4301 | BK7: 4300/4301 | BL7: 4300/4301 | BM7: 4300/4301 | BN7: 4300/4301 | BO7: 4300/4301 | BP7: 4300/4301 | BQ7: 4300/4301 | BR7: 4300/4301 | BS7: 4300/4301 | BT7: 4300/4301 | BU7: 4300/4301 | BV7: 4300/4301 | BW7: 4300/4301 | BX7: 4300/4301 | BY7: 4300/4301 | BZ7: 4300/4301 | CA7: 4300/4301 | CB7: 4300/4301 | CC7: 4300/4301 | CD7: 4300/4301 | CE7: 4300/4301 | CF7: 4300/4301 | CG7: VACCANT | GX7: #CC0000 | GY7: 4300/4301 | HA7: RS 26/27 | HC7: #00B050 | HE7: RS-17
A8: 3 | B8: 6137 | C8: 6137 | D8: 6137 | E8: 6137 | F8: 6137 | G8: 6137 | H8: 6137 | I8: 6137 | J8: 6137 | K8: 6137 | L8: 6137 | M8: 6137 | N8: 6137 | O8: VACCANT | P8: 4110 | Q8: 4110 | R8: 4110 | S8: 4110 | T8: 4110 | U8: 4110 | V8: 4110 | W8: 4110 | X8: 4110 | Y8: 4110 | Z8: 4110 | AA8: 4110 | AB8: 4110 | AC8: 4110 | AD8: 4110 | AE8: 4110 | AF8: 4110 | AG8: 4110 | AH8: 4110 | AI8: 4110 | AJ8: 4110 | AK8: 4110 | AL8: 4110 | AM8: 4110 | AN8: 4110 | AO8: 4110 | AP8: 4110 | AQ8: 4110 | AR8: 4110 | AS8: 4110 | AT8: 4110 | AU8: 4110 | AV8: 4110 | AW8: VACCANT | GX8: #00B050 | GY8: RS 26/27 | HA8: 6820 | HC8: #66FF33 | HE8: 4110
A9: 4 | B9: RS 26/27 | C9: RS 26/27 | D9: RS 26/27 | E9: RS 26/27 | F9: RS 26/27 | G9: RS 26/27 | H9: RS 26/27 | I9: RS 26/27 | J9: RS 26/27 | K9: RS 26/27 | L9: RS 26/27 | M9: RS 26/27 | N9: RS 26/27 | O9: RS 26/27 | P9: RS 26/27 | Q9: RS 26/27 | R9: RS 26/27 | S9: RS 26/27 | T9: RS 26/27 | U9: RS 26/27 | V9: RS 26/27 | W9: RS 26/27 | X9: RS 26/27 | Y9: RS 26/27 | Z9: RS 26/27 | AA9: RS 26/27 | AB9: RS 26/27 | AC9: RS 26/27 | AD9: RS 26/27 | AE9: RS 26/27 | AF9: RS 26/27 | AG9: RS 26/27 | AH9: RS 26/27 | AI9: RS 26/27 | AJ9: RS 26/27 | AK9: RS 26/27 | AL9: RS 26/27 | AM9: RS 26/27 | AN9: RS 26/27 | AO9: RS 26/27 | AP9: RS 26/27 | AQ9: RS 26/27 | AR9: RS 26/27 | AS9: RS 26/27 | AT9: RS 26/27 | AU9: RS 26/27 | AV9: RS 26/27 | AW9: RS 26/27 | AX9: RS 26/27 | AY9: RS 26/27 | AZ9: RS 26/27 | BA9: RS 26/27 | BB9: RS 26/27 | BC9: RS 26/27 | BD9: RS 26/27 | BE9: RS 26/27 | BF9: RS 26/27 | BG9: RS 26/27 | BH9: RS 26/27 | BI9: RS 26/27 | BJ9: RS 26/27 | BK9: VACCANT | GX9: #66FF33 | GY9: 6820 | HA9: 6108 | HC9: #F4B084 | HE9: RS-52
A10: 5 | B10: 6820 | C10: 6820 | D10: 6820 | E10: 6820 | F10: 6820 | G10: 6820 | H10: 6820 | I10: 6820 | J10: 6820 | K10: 6820 | L10: 6820 | M10: RS 26/27 | N10: RS 26/27 | O10: RS 26/27 | P10: RS 26/27 | Q10: RS 26/27 | R10: RS 26/27 | S10: RS 26/27 | T10: RS 26/27 | U10: RS 26/27 | V10: RS 26/27 | W10: RS 26/27 | X10: RS 26/27 | Y10: RS 26/27 | Z10: RS 26/27 | AA10: RS 26/27 | AB10: RS 26/27 | AC10: RS 26/27 | AD10: RS 26/27 | AE10: RS 26/27 | AF10: RS 26/27 | AG10: RS 26/27 | AH10: RS 26/27 | AI10: RS 26/27 | AJ10: RS 26/27 | AK10: RS 26/27 | AL10: RS 26/27 | AM10: RS 26/27 | AN10: RS 26/27 | AO10: RS 26/27 | AP10: RS 26/27 | AQ10: RS 26/27 | AR10: RS 26/27 | AS10: RS 26/27 | AT10: RS 26/27 | AU10: RS 26/27 | AV10: RS 26/27 | AW10: RS 26/27 | AX10: RS 26/27 | AY10: RS 26/27 | AZ10: RS 26/27 | BA10: RS 26/27 | BB10: RS 26/27 | BC10: RS 26/27 | BD10: RS 26/27 | BE10: RS 26/27 | BF10: RS 26/27 | BG10: RS 26/27 | BH10: RS 26/27 | BI10: RS 26/27 | BJ10: RS 26/27 | BK10: VACCANT | GX10: #F4B084 | GY10: 6108 | HA10: 6109 | HC10: #00B0F0 | HE10: 6108
A11: 6 | B11: 6820 | C11: 6820 | D11: 6820 | E11: 6820 | F11: 6820 | G11: 6820 | H11: 6820 | I11: 6820 | J11: 6820 | K11: 6820 | L11: 6820 | M11: 6820 | N11: 6820 | O11: 6820 | P11: 6820 | Q11: 6820 | R11: 6820 | S11: 6820 | T11: 6820 | U11: 6820 | V11: 6820 | W11: 6820 | X11: 6820 | Y11: 6820 | Z11: 6820 | AA11: 6820 | AB11: 6820 | AC11: 6820 | AD11: 6820 | AE11: 6820 | AF11: 6820 | AG11: 6820 | AH11: 6820 | AI11: 6820 | AJ11: 6820 | AK11: 6820 | AL11: 6820 | AM11: 6820 | AN11: 6820 | AO11: 6820 | AP11: 6820 | AQ11: 6820 | AR11: 6820 | AS11: 6820 | AT11: 6820 | AU11: 6820 | AV11: 6820 | AW11: 6820 | AX11: 6820 | AY11: 6820 | AZ11: VACCANT | GX11: #00B0F0 | GY11: 6109 | HA11: 4117 | HC11: #FFFF00 | HE11: 6109-T
A12: 7 | B12: 6137 | C12: 6137 | D12: 6137 | E12: 6137 | F12: 6137 | G12: 6137 | H12: 6137 | I12: 6137 | J12: 6137 | K12: 6137 | L12: 6137 | M12: 6137 | N12: 6137 | O12: VACCANT | P12: RS17 | Q12: RS17 | R12: RS17 | S12: RS17 | T12: RS17 | U12: RS17 | V12: RS17 | W12: RS17 | X12: RS17 | Y12: RS17 | Z12: RS17 | AA12: RS17 | AB12: RS17 | AC12: RS17 | AD12: RS17 | AE12: RS17 | AF12: RS17 | AG12: RS17 | AH12: RS17 | AI12: RS17 | AJ12: RS17 | AK12: RS17 | AL12: RS17 | AM12: RS17 | AN12: VACCANT | AO12: 4117 | AP12: 4117 | AQ12: 4117 | AR12: 4117 | AS12: 4117 | AT12: 4117 | AU12: 4117 | AV12: 4117 | AW12: 4117 | AX12: 4117 | AY12: 4117 | AZ12: 4117 | BA12: 4117 | BB12: 4117 | BC12: 4117 | BD12: 4117 | BE12: 4117 | BF12: 4117 | BG12: 4117 | BH12: 4117 | BI12: 4117 | BJ12: 4117 | BK12: 4117 | BL12: 4117 | BM12: 4117 | BN12: 4117 | BO12: 4117 | BP12: 4117 | BQ12: 4117 | BR12: 4117 | BS12: 4117 | BT12: 4117 | BU12: 4117 | BV12: 4117 | BW12: 4117 | BX12: 4117 | BY12: 4117 | BZ12: VACCANT | GX12: #FFFF00 | GY12: 4117 | HA12: 4406/10 | HC12: #C6E0B4 | HE12: 6109
A13: 8 | B13: 6109 | C13: 6109 | D13: 6109 | E13: 6109 | F13: 6109 | G13: 6109 | H13: 6109 | I13: 6109 | J13: 6109 | K13: 6109 | L13: 6109 | M13: 6109 | N13: 6109 | O13: 6109 | P13: 6109 | Q13: 6109 | R13: 6109 | S13: 6109 | T13: 6109 | U13: 6109 | V13: 6109 | W13: 6109 | X13: 6109 | Y13: 6109 | Z13: 6109 | AA13: 6109 | AB13: 6109 | AC13: 6109 | AD13: 6109 | AE13: 6109 | AF13: 6109 | AG13: 6109 | AH13: 6109 | AI13: 6109 | AJ13: 6109 | AK13: 6109 | AL13: 6109 | AM13: 6109 | AN13: 6109 | AO13: 6109 | AP13: 6109 | AQ13: 6109 | AR13: 6109 | AS13: 6109 | AT13: 6109 | AU13: 6109 | AV13: 6109 | AW13: 6109 | AX13: 6109 | AY13: 6109 | AZ13: 6109 | BA13: 6109 | BB13: 6109 | BC13: 6109 | BD13: 6109 | BE13: 6109 | BF13: 6109 | BG13: 6109 | BH13: 6109 | BI13: 6109 | BJ13: 6109 | BK13: 6109 | BL13: 6109 | BM13: 6109 | BN13: 6109 | BO13: 6109 | BP13: 6109 | BQ13: 6109 | BR13: 6109 | BS13: 6109 | BT13: VACCANT | GX13: #C6E0B4 | GY13: 4406/10 | HA13: 4115 | HC13: #BF8F00 | HE13: 4115
A14: 9 | B14: 6109 | C14: 6109 | D14: 6109 | E14: 6109 | F14: 6109 | G14: 6109 | H14: 6109 | I14: 6109 | J14: 6109 | K14: 6109 | L14: 6109 | M14: 6109 | N14: 6109 | O14: 6109 | P14: 6109 | Q14: 6109 | R14: 6109 | S14: 6109 | T14: 6109 | U14: 6109 | V14: 6109 | W14: 6109 | X14: 6109 | Y14: 6109 | Z14: 6109 | AA14: 6109 | AB14: 6109 | AC14: 6109 | AD14: 6109 | AE14: 6109 | AF14: 6109 | AG14: 6109 | AH14: 6109 | AI14: 6109 | AJ14: 6109 | AK14: 6109 | AL14: 6109 | AM14: 6109 | AN14: 6109 | AO14: 6109 | AP14: 6109 | AQ14: 6109 | AR14: 6109 | AS14: 6109 | AT14: 6109 | AU14: 6109 | AV14: 6109 | AW14: 6109 | AX14: 6109 | AY14: 6109 | AZ14: 6109 | BA14: 6109 | BB14: 6109 | BC14: 6109 | BD14: 6109 | BE14: 6109 | BF14: 6109 | BG14: 6109 | BH14: 6109 | BI14: 6109 | BJ14: 6109 | BK14: 6109 | BL14: 6109 | BM14: 6109 | BN14: 6109 | BO14: 6109 | BP14: 6109 | BQ14: 6109 | BR14: 6109 | BS14: 6109 | BT14: VACCANT | GX14: #BF8F00 | GY14: 4115 | HA14: RS17 | HC14: #7030A0 | HE14: 4117-T
A15: 10 | B15: 6109 | C15: 6109 | D15: 6109 | E15: 6109 | F15: 6109 | G15: 6109 | H15: 6109 | I15: 6109 | J15: 6109 | K15: 6109 | L15: 6109 | M15: 6109 | N15: 6109 | O15: 6109 | P15: 6109 | Q15: 6109 | R15: 6109 | S15: 6109 | T15: 6109 | U15: 6109 | V15: 6109 | W15: 6109 | X15: 6109 | Y15: 6109 | Z15: 6109 | AA15: 6109 | AB15: 6109 | AC15: 6109 | AD15: 6109 | AE15: 6109 | AF15: 6109 | AG15: 6109 | AH15: 6109 | AI15: 6109 | AJ15: 6109 | AK15: 6109 | AL15: 6109 | AM15: 6109 | AN15: 6109 | AO15: 6109 | AP15: 6109 | AQ15: 6109 | AR15: 6109 | AS15: 6109 | AT15: 6109 | AU15: 6109 | AV15: 6109 | AW15: 6109 | AX15: 6109 | AY15: 6109 | AZ15: 6109 | BA15: 6109 | BB15: 6109 | BC15: 6109 | BD15: 6109 | BE15: 6109 | BF15: 6109 | BG15: 6109 | BH15: 6109 | BI15: 6109 | BJ15: 6109 | BK15: 6109 | BL15: 6109 | BM15: 6109 | BN15: 6109 | BO15: 6109 | BP15: 6109 | BQ15: 6109 | BR15: 6109 | BS15: 6109 | BT15: VACCANT | GX15: #7030A0 | GY15: RS17 | HA15: 6135 | HC15: #ACB9CA | HE15: 4117
A16: 11 | B16: 6108 | C16: 6108 | D16: 6108 | E16: 6108 | F16: 6108 | G16: 6108 | H16: 6108 | I16: 6108 | J16: 6108 | K16: 6108 | L16: 6108 | M16: 6108 | N16: 6108 | O16: 6108 | P16: 6108 | Q16: 6108 | R16: 6108 | S16: 6108 | T16: 6108 | U16: 6108 | V16: 6108 | W16: 6108 | X16: 6108 | Y16: 6108 | Z16: 6108 | AA16: 6108 | AB16: 6108 | AC16: 6108 | AD16: 6108 | AE16: 6108 | AF16: 6108 | AG16: 6108 | AH16: 6108 | AI16: 6108 | AJ16: 6108 | AK16: 6108 | AL16: 6108 | AM16: 6108 | AN16: 6108 | AO16: 6108 | AP16: 6108 | AQ16: 6108 | AR16: 6108 | AS16: 6108 | AT16: 6108 | AU16: 4117 | AV16: 4117 | AW16: 4117 | AX16: 4117 | AY16: 4117 | AZ16: 4117 | BA16: 4117 | BB16: 4117 | BC16: 4117 | BD16: 4117 | BE16: 4117 | BF16: 4117 | BG16: 4117 | BH16: 4117 | BI16: 4117 | BJ16: 4117 | BK16: 4117 | BL16: 4117 | BM16: 4117 | BN16: 4117 | BO16: 4117 | BP16: 4117 | BQ16: 4117 | BR16: 4117 | BS16: 4117 | BT16: 4117 | BU16: 4117 | BV16: 4117 | BW16: 4117 | BX16: 4117 | BY16: 4117 | BZ16: VACCANT | GX16: #ACB9CA | GY16: 6135 | HA16: THERMAL | HC16: #00FFFF | HE16: RS-60
A17: 12 | B17: 6108 | C17: 6108 | D17: 6108 | E17: 6108 | F17: 6108 | G17: 6108 | H17: 6108 | I17: 6108 | J17: 6108 | K17: 6108 | L17: 6108 | M17: 6108 | N17: 6108 | O17: 6108 | P17: 6108 | Q17: 6108 | R17: 6108 | S17: 6108 | T17: 6108 | U17: 6108 | V17: 6108 | W17: 6108 | X17: 6108 | Y17: 6108 | Z17: 6108 | AA17: 6108 | AB17: 6108 | AC17: 6108 | AD17: 6108 | AE17: 6108 | AF17: 6108 | AG17: 6108 | AH17: 6108 | AI17: 6108 | AJ17: 6108 | AK17: 6108 | AL17: 6108 | AM17: 6108 | AN17: 6108 | AO17: 6108 | AP17: 6108 | AQ17: 6108 | AR17: 6108 | AS17: 6108 | AT17: 6108 | AU17: 4117 | AV17: 4117 | AW17: 4117 | AX17: 4117 | AY17: 4117 | AZ17: 4117 | BA17: 4117 | BB17: 4117 | BC17: 4117 | BD17: 4117 | BE17: 4117 | BF17: 4117 | BG17: 4117 | BH17: 4117 | BI17: 4117 | BJ17: 4117 | BK17: 4117 | BL17: 4117 | BM17: 4117 | BN17: 4117 | BO17: 4117 | BP17: 4117 | BQ17: 4117 | BR17: 4117 | BS17: 4117 | BT17: 4117 | BU17: 4117 | BV17: 4117 | BW17: 4117 | BX17: 4117 | BY17: 4117 | BZ17: VACCANT | GX17: #00FFFF | GY17: THERMAL | HA17: VACCANT | HC17: #0D0D0D | HE17: RS-63
A18: 13 | B18: RS17 | C18: RS17 | D18: RS17 | E18: RS17 | F18: RS17 | G18: RS17 | H18: RS17 | I18: RS17 | J18: RS17 | K18: RS17 | L18: RS17 | M18: RS17 | N18: RS17 | O18: RS17 | P18: RS17 | Q18: RS17 | R18: RS17 | S18: RS17 | T18: RS17 | U18: RS17 | V18: RS17 | W18: RS17 | X18: RS17 | Y18: RS17 | Z18: RS17 | AA18: RS17 | AB18: RS17 | AC18: RS17 | AD18: RS17 | AE18: RS17 | AF18: RS17 | AG18: RS17 | AH18: RS17 | AI18: RS17 | AJ18: RS17 | AK18: RS17 | AL18: RS17 | AM18: RS17 | AN18: RS17 | AO18: RS17 | AP18: RS17 | AQ18: RS17 | AR18: RS17 | AS18: RS17 | AT18: RS17 | AU18: RS17 | AV18: RS17 | AW18: RS17 | AX18: RS17 | AY18: RS17 | AZ18: VACCANT | BA18: 4117 | BB18: 4117 | BC18: 4117 | BD18: 4117 | BE18: 4117 | BF18: 4117 | BG18: 4117 | BH18: 4117 | BI18: 4117 | BJ18: 4117 | BK18: 4117 | BL18: 4117 | BM18: 4117 | BN18: 4117 | BO18: 4117 | BP18: 4117 | BQ18: 4117 | BR18: 4117 | BS18: 4117 | BT18: 4117 | BU18: 4117 | BV18: 4117 | BW18: 4117 | BX18: 4117 | BY18: 4117 | BZ18: VACCANT | GX18: #0D0D0D | GY18: VACCANT | HA18: 6137 | HC18: #3333CC | HE18: 4523
A19: 14 | B19: 6137 | C19: 6137 | D19: 6137 | E19: 6137 | F19: 6137 | G19: 6137 | H19: 6137 | I19: 6137 | J19: 6137 | K19: 6137 | L19: 6137 | M19: 6137 | N19: 6137 | O19: VACCANT | P19: 4406/10 | Q19: 4406/10 | R19: 4406/10 | S19: 4406/10 | T19: 4406/10 | U19: 4406/10 | V19: 4406/10 | W19: 4406/10 | X19: 4406/10 | Y19: 4406/10 | Z19: 4406/10 | AA19: 4406/10 | AB19: 4406/10 | AC19: 4406/10 | AD19: 4406/10 | AE19: 4406/10 | AF19: 4406/10 | AG19: 4406/10 | AH19: 4406/10 | AI19: 4406/10 | AJ19: 4406/10 | AK19: 4406/10 | AL19: 4406/10 | AM19: 4406/10 | AN19: 4406/10 | AO19: 4406/10 | AP19: 4406/10 | AQ19: 4406/10 | AR19: 4406/10 | AS19: 4406/10 | AT19: 4406/10 | AU19: 4406/10 | AV19: 4406/10 | AW19: 4406/10 | AX19: 4406/10 | AY19: 4406/10 | AZ19: 4406/10 | BA19: 4406/10 | BB19: 4406/10 | BC19: 4406/10 | BD19: 4406/10 | BE19: 4406/10 | BF19: 4406/10 | BG19: 4406/10 | BH19: 4406/10 | BI19: 4406/10 | BJ19: 4406/10 | BK19: 4406/10 | BL19: 4406/10 | BM19: 4406/10 | BN19: 4406/10 | BO19: 4406/10 | BP19: 4406/10 | BQ19: 4406/10 | BR19: 4406/10 | BS19: 4406/10 | BT19: 4406/10 | BU19: 4406/10 | BV19: 4406/10 | BW19: 4406/10 | BX19: 4406/10 | BY19: 4406/10 | BZ19: 4406/10 | CA19: 4406/10 | CB19: 4406/10 | CC19: 4406/10 | CD19: VACCANT | GX19: #3333CC | GY19: 6137 | HA19: 4110 | HC19: #833C0C | HE19: 4525
A20: 15 | B20: 6135 | C20: 6135 | D20: 6135 | E20: 6135 | F20: 6135 | G20: 6135 | H20: 6135 | I20: 6135 | J20: 6135 | K20: 6135 | L20: 6135 | M20: 6135 | N20: 6135 | O20: VACCANT | P20: 4406/10 | Q20: 4406/10 | R20: 4406/10 | S20: 4406/10 | T20: 4406/10 | U20: 4406/10 | V20: 4406/10 | W20: 4406/10 | X20: 4406/10 | Y20: 4406/10 | Z20: 4406/10 | AA20: 4406/10 | AB20: 4406/10 | AC20: 4406/10 | AD20: 4406/10 | AE20: 4406/10 | AF20: 4406/10 | AG20: 4406/10 | AH20: 4406/10 | AI20: 4406/10 | AJ20: 4406/10 | AK20: 4406/10 | AL20: 4406/10 | AM20: 4406/10 | AN20: 4406/10 | AO20: 4406/10 | AP20: 4406/10 | AQ20: 4406/10 | AR20: 4406/10 | AS20: 4406/10 | AT20: 4406/10 | AU20: 4406/10 | AV20: 4406/10 | AW20: 4406/10 | AX20: 4406/10 | AY20: 4406/10 | AZ20: 4406/10 | BA20: 4406/10 | BB20: 4406/10 | BC20: 4406/10 | BD20: 4406/10 | BE20: 4406/10 | BF20: 4406/10 | BG20: 4406/10 | BH20: 4406/10 | BI20: 4406/10 | BJ20: 4406/10 | BK20: 4406/10 | BL20: 4406/10 | BM20: 4406/10 | BN20: 4406/10 | BO20: 4406/10 | BP20: 4406/10 | BQ20: 4406/10 | BR20: 4406/10 | BS20: 4406/10 | BT20: 4406/10 | BU20: 4406/10 | BV20: 4406/10 | BW20: 4406/10 | BX20: 4406/10 | BY20: 4406/10 | BZ20: 4406/10 | CA20: 4406/10 | CB20: 4406/10 | CC20: 4406/10 | CD20: VACCANT | GX20: #833C0C | GY20: 4110 | HE20: Panty
A21: 16 | B21: 4406/10 | C21: 4406/10 | D21: 4406/10 | E21: 4406/10 | F21: 4406/10 | G21: 4406/10 | H21: 4406/10 | I21: 4406/10 | J21: 4406/10 | K21: 4406/10 | L21: 4406/10 | M21: 4406/10 | N21: 4406/10 | O21: 4406/10 | P21: 4406/10 | Q21: 4406/10 | R21: 4406/10 | S21: 4406/10 | T21: 4406/10 | U21: 4406/10 | V21: 4406/10 | W21: 4406/10 | X21: 4406/10 | Y21: 4406/10 | Z21: 4406/10 | AA21: 4406/10 | AB21: 4406/10 | AC21: 4406/10 | AD21: 4406/10 | AE21: 4406/10 | AF21: 4406/10 | AG21: 4406/10 | AH21: 4406/10 | AI21: 4406/10 | AJ21: 4406/10 | AK21: 4406/10 | AL21: 4406/10 | AM21: 4406/10 | AN21: 4406/10 | AO21: 4406/10 | AP21: 4406/10 | AQ21: 4406/10 | AR21: 4406/10 | AS21: 4406/10 | AT21: 4406/10 | AU21: 4406/10 | AV21: 4406/10 | AW21: 4406/10 | AX21: 4406/10 | AY21: 4406/10 | AZ21: 4406/10 | BA21: 4406/10 | BB21: 4406/10 | BC21: 4406/10 | BD21: 4406/10 | BE21: 4406/10 | BF21: 4406/10 | BG21: 4406/10 | BH21: 4406/10 | BI21: 4406/10 | BJ21: 4406/10 | BK21: 4406/10 | BL21: 4406/10 | BM21: 4406/10 | BN21: 4406/10 | BO21: 4406/10 | BP21: 4406/10 | BQ21: 4406/10 | BR21: 4406/10 | BS21: 4406/10 | BT21: 4406/10 | BU21: 4406/10 | BV21: 4406/10 | BW21: 4406/10 | BX21: 4406/10 | BY21: 4406/10 | BZ21: 4406/10 | CA21: 4406/10 | CB21: 4406/10 | CC21: 4406/10 | CD21: VACCANT | GX21: #000000 | GY21: VACCANT | HB21: Garment Unit A | HE21: T Shirt
A22: 17 | B22: 4117 | C22: 4117 | D22: 4117 | E22: 4117 | F22: 4117 | G22: 4117 | H22: 4117 | I22: 4117 | J22: 4117 | K22: 4117 | L22: 4117 | M22: 4117 | N22: 4117 | O22: 4117 | P22: 4117 | Q22: 4117 | R22: 4117 | S22: 4117 | T22: 4117 | U22: 4117 | V22: 4117 | W22: 4117 | X22: 4117 | Y22: 4117 | Z22: 4117 | AA22: 4117 | AB22: 4117 | AC22: 4117 | AD22: 4117 | AE22: 4117 | AF22: 4117 | AG22: 4117 | AH22: 4117 | AI22: 4117 | AJ22: 4117 | AK22: 4117 | AL22: 4117 | AM22: 4117 | AN22: 4117 | AO22: 4117 | AP22: 4117 | AQ22: 4117 | AR22: 4117 | AS22: 4117 | AT22: 4117 | AU22: 4117 | AV22: 4117 | AW22: 4117 | AX22: 4117 | AY22: 4117 | AZ22: 4117 | BA22: 4117 | BB22: 4117 | BC22: 4117 | BD22: 4117 | BE22: 4117 | BF22: 4117 | BG22: 4117 | BH22: 4117 | BI22: 4117 | BJ22: 4117 | BK22: 4117 | BL22: 4117 | BM22: 4117 | BN22: 4117 | BO22: 4117 | BP22: 4117 | BQ22: 4117 | BR22: 4117 | BS22: 4117 | BT22: 4117 | BU22: 4117 | BV22: 4117 | BW22: 4117 | BX22: 4117 | BY22: 4117 | BZ22: VACCANT | GX22: #FFFFFF | GY22: (not planned / blank) | HB22: 46235 | HE22: 6820
A23: 18 | B23: 4117 | C23: 4117 | D23: 4117 | E23: 4117 | F23: 4117 | G23: 4117 | H23: 4117 | I23: 4117 | J23: 4117 | K23: 4117 | L23: 4117 | M23: 4117 | N23: 4117 | O23: 4117 | P23: 4117 | Q23: 4117 | R23: 4117 | S23: 4117 | T23: 4117 | U23: 4117 | V23: 4117 | W23: 4117 | X23: 4117 | Y23: 4117 | Z23: 4117 | AA23: 4117 | AB23: 4117 | AC23: 4117 | AD23: 4117 | AE23: 4117 | AF23: 4117 | AG23: 4117 | AH23: 4117 | AI23: 4117 | AJ23: 4117 | AK23: 4117 | AL23: 4117 | AM23: 4117 | AN23: 4117 | AO23: 4117 | AP23: 4117 | AQ23: 4117 | AR23: 4117 | AS23: 4117 | AT23: 4117 | AU23: 4117 | AV23: 4117 | AW23: 4117 | AX23: 4117 | AY23: 4117 | AZ23: 4117 | BA23: 4117 | BB23: 4117 | BC23: 4117 | BD23: 4117 | BE23: 4117 | BF23: 4117 | BG23: 4117 | BH23: 4117 | BI23: 4117 | BJ23: 4117 | BK23: 4117 | BL23: 4117 | BM23: 4117 | BN23: 4117 | BO23: 4117 | BP23: 4117 | BQ23: 4117 | BR23: 4117 | BS23: 4117 | BT23: 4117 | BU23: 4117 | BV23: 4117 | BW23: 4117 | BX23: 4117 | BY23: 4117 | BZ23: VACCANT | HE23: RS-27
A24: 19 | B24: 4115 | C24: 4115 | D24: 4115 | E24: 4115 | F24: 4115 | G24: 4115 | H24: 4115 | I24: 4115 | J24: 4115 | K24: 4115 | L24: 4115 | M24: 4115 | N24: 4115 | O24: 4115 | P24: 4115 | Q24: 4115 | R24: 4115 | S24: 4115 | T24: 4115 | U24: 4115 | V24: 4115 | W24: 4115 | X24: 4115 | Y24: 4115 | Z24: 4115 | AA24: 4115 | AB24: 4115 | AC24: 4115 | AD24: 4115 | AE24: 4115 | AF24: 4115 | AG24: 4115 | AH24: 4115 | AI24: 4115 | AJ24: 4115 | AK24: 4115 | AL24: 4115 | AM24: 4115 | AN24: 4115 | AO24: 4115 | AP24: 4115 | AQ24: 4115 | AR24: 4115 | AS24: 4115 | AT24: 4115 | AU24: 4115 | AV24: 4115 | AW24: 4115 | AX24: 4115 | AY24: 4115 | AZ24: 4115 | BA24: 4115 | BB24: 4115 | BC24: 4115 | BD24: 4115 | BE24: 4115 | BF24: 4115 | BG24: 4115 | BH24: 4115 | BI24: 4115 | BJ24: 4115 | BK24: 4115 | BL24: 4115 | BM24: 4115 | BN24: VACCANT | BO24: 4117 | BP24: 4117 | BQ24: 4117 | BR24: 4117 | BS24: 4117 | BT24: 4117 | BU24: 4117 | BV24: 4117 | BW24: 4117 | BX24: 4117 | BY24: 4117 | BZ24: VACCANT | HE24: 5201
A25: 20 | B25: 6137 | C25: 6137 | D25: 6137 | E25: 6137 | F25: 6137 | G25: 6137 | H25: 6137 | I25: 6137 | J25: 6137 | K25: 6137 | L25: 6137 | M25: 6137 | N25: 6137 | O25: 6108 | P25: 6108 | Q25: 6108 | R25: 6108 | S25: 6108 | T25: 6108 | U25: 6108 | V25: 6108 | W25: 6108 | X25: 6108 | Y25: 6108 | Z25: 6108 | AA25: 6108 | AB25: 6108 | AC25: 6108 | AD25: 6108 | AE25: 6108 | AF25: 6108 | AG25: 6108 | AH25: 6108 | AI25: 6108 | AJ25: 6108 | AK25: 6108 | AL25: 6108 | AM25: 6108 | AN25: 6108 | AO25: 6108 | AP25: 6108 | AQ25: 6108 | AR25: 6108 | AS25: 6108 | AT25: 6108 | AU25: 6109 | AV25: 6109 | AW25: 6109 | AX25: 6109 | AY25: 6109 | AZ25: 6109 | BA25: 6109 | BB25: 6109 | BC25: 6109 | BD25: 6109 | BE25: 6109 | BF25: 6109 | BG25: 6109 | BH25: 6109 | BI25: 6109 | BJ25: 6109 | BK25: 6109 | BL25: 6109 | BM25: 6109 | BN25: 6109 | BO25: 6109 | BP25: 6109 | BQ25: 6109 | BR25: 6109 | BS25: 6109 | BT25: VACCANT | HE25: 4223
A26: 21 | B26: 6137 | C26: 6137 | D26: 6137 | E26: 6137 | F26: 6137 | G26: 6137 | H26: 6137 | I26: 6137 | J26: 6137 | K26: 6137 | L26: 6137 | M26: 6137 | N26: 6137 | O26: VACCANT | P26: RS17 | Q26: RS17 | R26: RS17 | S26: RS17 | T26: RS17 | U26: RS17 | V26: RS17 | W26: RS17 | X26: RS17 | Y26: RS17 | Z26: RS17 | AA26: RS17 | AB26: RS17 | AC26: RS17 | AD26: RS17 | AE26: RS17 | AF26: RS17 | AG26: RS17 | AH26: RS17 | AI26: RS17 | AJ26: RS17 | AK26: RS17 | AL26: RS17 | AM26: RS17 | AN26: RS17 | AO26: RS17 | AP26: RS17 | AQ26: RS17 | AR26: RS17 | AS26: RS17 | AT26: RS17 | AU26: RS17 | AV26: RS17 | AW26: RS17 | AX26: RS17 | AY26: RS17 | AZ26: VACCANT | BA26: 4117 | BB26: 4117 | BC26: 4117 | BD26: 4117 | BE26: 4117 | BF26: 4117 | BG26: 4117 | BH26: 4117 | BI26: 4117 | BJ26: 4117 | BK26: 4117 | BL26: 4117 | BM26: 4117 | BN26: 4117 | BO26: 4117 | BP26: 4117 | BQ26: 4117 | BR26: 4117 | BS26: 4117 | BT26: 4117 | BU26: 4117 | BV26: 4117 | BW26: 4117 | BX26: 4117 | BY26: 4117 | BZ26: VACCANT | HE26: 4222
A27: 22 | B27: THERMAL | C27: THERMAL | D27: THERMAL | E27: THERMAL | F27: THERMAL | G27: THERMAL | H27: THERMAL | I27: THERMAL | J27: THERMAL | K27: THERMAL | L27: THERMAL | M27: THERMAL | N27: THERMAL | O27: THERMAL | P27: THERMAL | Q27: THERMAL | R27: THERMAL | S27: THERMAL | T27: THERMAL | U27: THERMAL | V27: THERMAL | W27: THERMAL | X27: THERMAL | Y27: THERMAL | Z27: THERMAL | AA27: THERMAL | AB27: THERMAL | AC27: THERMAL | AD27: THERMAL | AE27: THERMAL | AF27: THERMAL | AG27: THERMAL | AH27: THERMAL | AI27: THERMAL | AJ27: THERMAL | AK27: THERMAL | AL27: THERMAL | AM27: THERMAL | AN27: THERMAL | AO27: THERMAL | AP27: THERMAL | AQ27: THERMAL | AR27: THERMAL | AS27: THERMAL | AT27: THERMAL | AU27: THERMAL | AV27: THERMAL | AW27: THERMAL | AX27: THERMAL | AY27: THERMAL | AZ27: THERMAL | BA27: THERMAL | BB27: THERMAL | BC27: THERMAL | BD27: THERMAL | BE27: THERMAL | BF27: THERMAL | BG27: THERMAL | BH27: THERMAL | BI27: THERMAL | BJ27: THERMAL | BK27: THERMAL | BL27: THERMAL | BM27: THERMAL | BN27: THERMAL | BO27: THERMAL | BP27: THERMAL | BQ27: THERMAL | BR27: THERMAL | BS27: THERMAL | BT27: VACCANT | HE27: 4300
A28: 23 | B28: 6135 | C28: 6135 | D28: 6135 | E28: 6135 | F28: 6135 | G28: 6135 | H28: 6135 | I28: 6135 | J28: 6135 | K28: 6135 | L28: 6135 | M28: 6135 | N28: 6135 | O28: 6135 | P28: 6135 | Q28: 6135 | R28: 6135 | S28: 6135 | T28: 6135 | U28: 6135 | V28: 6135 | W28: 6135 | X28: 6135 | Y28: 6135 | Z28: 6135 | AA28: 6135 | AB28: 6135 | AC28: 6135 | AD28: 6135 | AE28: 6135 | AF28: 6135 | AG28: 6135 | AH28: 6135 | AI28: 6135 | AJ28: 6135 | AK28: 6135 | AL28: VACCANT | AM28: 4406/10 | AN28: 4406/10 | AO28: 4406/10 | AP28: 4406/10 | AQ28: 4406/10 | AR28: 4406/10 | AS28: 4406/10 | AT28: 4406/10 | AU28: 4406/10 | AV28: 4406/10 | AW28: 4406/10 | AX28: 4406/10 | AY28: 4406/10 | AZ28: 4406/10 | BA28: 4406/10 | BB28: 4406/10 | BC28: VACCANT | BD28: 6137 | BE28: 6137 | BF28: 6137 | BG28: 6137 | BH28: 6137 | BI28: 6137 | BJ28: 6137 | BK28: VACCANT | HE28: 4359
A29: 24 | B29: THERMAL | C29: THERMAL | D29: THERMAL | E29: THERMAL | F29: THERMAL | G29: THERMAL | H29: THERMAL | I29: THERMAL | J29: THERMAL | K29: THERMAL | L29: THERMAL | M29: THERMAL | N29: THERMAL | O29: THERMAL | P29: THERMAL | Q29: THERMAL | R29: THERMAL | S29: THERMAL | T29: THERMAL | U29: THERMAL | V29: THERMAL | W29: THERMAL | X29: THERMAL | Y29: THERMAL | Z29: THERMAL | AA29: THERMAL | AB29: THERMAL | AC29: THERMAL | AD29: THERMAL | AE29: THERMAL | AF29: THERMAL | AG29: THERMAL | AH29: THERMAL | AI29: THERMAL | AJ29: THERMAL | AK29: THERMAL | AL29: THERMAL | AM29: THERMAL | AN29: THERMAL | AO29: THERMAL | AP29: THERMAL | AQ29: THERMAL | AR29: THERMAL | AS29: THERMAL | AT29: THERMAL | AU29: THERMAL | AV29: THERMAL | AW29: THERMAL | AX29: THERMAL | AY29: THERMAL | AZ29: THERMAL | BA29: THERMAL | BB29: THERMAL | BC29: THERMAL | BD29: THERMAL | BE29: THERMAL | BF29: THERMAL | BG29: THERMAL | BH29: THERMAL | BI29: THERMAL | BJ29: THERMAL | BK29: THERMAL | BL29: THERMAL | BM29: THERMAL | BN29: THERMAL | BO29: THERMAL | BP29: THERMAL | BQ29: THERMAL | BR29: THERMAL | BS29: THERMAL | BT29: VACCANT | HE29: 4301
A30: 25 | B30: THERMAL | C30: THERMAL | D30: THERMAL | E30: THERMAL | F30: THERMAL | G30: THERMAL | H30: THERMAL | I30: THERMAL | J30: THERMAL | K30: THERMAL | L30: THERMAL | M30: THERMAL | N30: THERMAL | O30: THERMAL | P30: THERMAL | Q30: THERMAL | R30: THERMAL | S30: THERMAL | T30: THERMAL | U30: THERMAL | V30: THERMAL | W30: THERMAL | X30: THERMAL | Y30: THERMAL | Z30: THERMAL | AA30: THERMAL | AB30: THERMAL | AC30: THERMAL | AD30: THERMAL | AE30: THERMAL | AF30: THERMAL | AG30: THERMAL | AH30: THERMAL | AI30: THERMAL | AJ30: THERMAL | AK30: THERMAL | AL30: THERMAL | AM30: THERMAL | AN30: THERMAL | AO30: THERMAL | AP30: THERMAL | AQ30: THERMAL | AR30: THERMAL | AS30: THERMAL | AT30: THERMAL | AU30: THERMAL | AV30: THERMAL | AW30: THERMAL | AX30: THERMAL | AY30: THERMAL | AZ30: THERMAL | BA30: THERMAL | BB30: THERMAL | BC30: THERMAL | BD30: THERMAL | BE30: THERMAL | BF30: THERMAL | BG30: THERMAL | BH30: THERMAL | BI30: THERMAL | BJ30: THERMAL | BK30: THERMAL | BL30: THERMAL | BM30: THERMAL | BN30: THERMAL | BO30: THERMAL | BP30: THERMAL | BQ30: THERMAL | BR30: THERMAL | BS30: THERMAL | BT30: VACCANT | HE30: RS-92
A31: 26 | B31: 6135 | C31: 6135 | D31: 6135 | E31: 6135 | F31: 6135 | G31: 6135 | H31: 6135 | I31: 6135 | J31: 6135 | K31: 6135 | L31: 6135 | M31: 6135 | N31: 6135 | O31: 6135 | P31: 6135 | Q31: 6135 | R31: 6135 | S31: 6135 | T31: 6135 | U31: 6135 | V31: 6135 | W31: 6135 | X31: 6135 | Y31: 6135 | Z31: 6135 | AA31: 6135 | AB31: 6135 | AC31: 6135 | AD31: 6135 | AE31: 6135 | AF31: 6135 | AG31: 6135 | AH31: 6135 | AI31: 6135 | AJ31: 6135 | AK31: 6135 | AL31: VACCANT | AM31: THERMAL | AN31: THERMAL | AO31: THERMAL | AP31: THERMAL | AQ31: THERMAL | AR31: THERMAL | AS31: THERMAL | AT31: THERMAL | AU31: THERMAL | AV31: THERMAL | AW31: THERMAL | AX31: THERMAL | AY31: THERMAL | AZ31: THERMAL | BA31: THERMAL | BB31: THERMAL | BC31: THERMAL | BD31: THERMAL | BE31: THERMAL | BF31: THERMAL | BG31: THERMAL | BH31: THERMAL | BI31: THERMAL | BJ31: THERMAL | BK31: THERMAL | BL31: THERMAL | BM31: THERMAL | BN31: THERMAL | BO31: THERMAL | BP31: THERMAL | BQ31: THERMAL | BR31: THERMAL | BS31: THERMAL | BT31: VACCANT | HE31: BW-30
HE32: 5200
HE33: 5220
A34: 2. RESOLVED — | GW34: helper | HE34: 5500
A35: Line | B35: =B$5 -> 46235 | C35: =C$5 -> 46236 | D35: =D$5 -> 46237 | E35: =E$5 -> 46238 | F35: =F$5 -> 46239 | G35: =G$5 -> 46240 | H35: =H$5 -> 46241 | I35: =I$5 -> 46242 | ... GS35: =GS$5 -> 0 | GW35: Thermal recipe resolved (via MC MAP table 2b) | GY35: Thermal style for this line (EDIT ME) | HE35: 5501
A36: =$A6 -> 1 | B36: =IF(B6="","",IF(B6<>"THERMAL",B6,IF($GW36="","THERMAL - NOT SPECIFIED",$GW36))) -> 7926 | C36: =IF(C6="","",IF(C6<>"THERMAL",C6,IF($GW36="","THERMAL - NOT SPECIFIED",$GW36))) -> 7926 | D36: =IF(D6="","",IF(D6<>"THERMAL",D6,IF($GW36="","THERMAL - NOT SPECIFIED",$GW36))) -> 7926 | E36: =IF(E6="","",IF(E6<>"THERMAL",E6,IF($GW36="","THERMAL - NOT SPECIFIED",$GW36))) -> 7926 | F36: =IF(F6="","",IF(F6<>"THERMAL",F6,IF($GW36="","THERMAL - NOT SPECIFIED",$GW36))) -> 7926 | G36: =IF(G6="","",IF(G6<>"THERMAL",G6,IF($GW36="","THERMAL - NOT SPECIFIED",$GW36))) -> 7926 | H36: =IF(H6="","",IF(H6<>"THERMAL",H6,IF($GW36="","THERMAL - NOT SPECIFIED",$GW36))) -> 7926 | I36: =IF(I6="","",IF(I6<>"THERMAL",I6,IF($GW36="","THERMAL - NOT SPECIFIED",$GW36))) -> 7926 | ... GS36: =IF(GS6="","",IF(GS6<>"THERMAL",GS6,IF($GW36="","THERMAL - NOT SPECIFIED",$GW36))) | GW36: =IF($GY36="","",IFERROR(INDEX('MC MAP'!$L$5:$L$28,MATCH($GY36,'MC MAP'!$K$5:$K$28,0)),$GY36)) | HE36: POLO
A37: =$A7 -> 2 | B37: =IF(B7="","",IF(B7<>"THERMAL",B7,IF($GW37="","THERMAL - NOT SPECIFIED",$GW37))) -> 4300/4301 | C37: =IF(C7="","",IF(C7<>"THERMAL",C7,IF($GW37="","THERMAL - NOT SPECIFIED",$GW37))) -> 4300/4301 | D37: =IF(D7="","",IF(D7<>"THERMAL",D7,IF($GW37="","THERMAL - NOT SPECIFIED",$GW37))) -> 4300/4301 | E37: =IF(E7="","",IF(E7<>"THERMAL",E7,IF($GW37="","THERMAL - NOT SPECIFIED",$GW37))) -> 4300/4301 | F37: =IF(F7="","",IF(F7<>"THERMAL",F7,IF($GW37="","THERMAL - NOT SPECIFIED",$GW37))) -> 4300/4301 | G37: =IF(G7="","",IF(G7<>"THERMAL",G7,IF($GW37="","THERMAL - NOT SPECIFIED",$GW37))) -> 4300/4301 | H37: =IF(H7="","",IF(H7<>"THERMAL",H7,IF($GW37="","THERMAL - NOT SPECIFIED",$GW37))) -> 4300/4301 | I37: =IF(I7="","",IF(I7<>"THERMAL",I7,IF($GW37="","THERMAL - NOT SPECIFIED",$GW37))) -> 4300/4301 | ... GS37: =IF(GS7="","",IF(GS7<>"THERMAL",GS7,IF($GW37="","THERMAL - NOT SPECIFIED",$GW37))) | GW37: =IF($GY37="","",IFERROR(INDEX('MC MAP'!$L$5:$L$28,MATCH($GY37,'MC MAP'!$K$5:$K$28,0)),$GY37)) | HE37: 7926
A38: =$A8 -> 3 | B38: =IF(B8="","",IF(B8<>"THERMAL",B8,IF($GW38="","THERMAL - NOT SPECIFIED",$GW38))) -> 6137 | C38: =IF(C8="","",IF(C8<>"THERMAL",C8,IF($GW38="","THERMAL - NOT SPECIFIED",$GW38))) -> 6137 | D38: =IF(D8="","",IF(D8<>"THERMAL",D8,IF($GW38="","THERMAL - NOT SPECIFIED",$GW38))) -> 6137 | E38: =IF(E8="","",IF(E8<>"THERMAL",E8,IF($GW38="","THERMAL - NOT SPECIFIED",$GW38))) -> 6137 | F38: =IF(F8="","",IF(F8<>"THERMAL",F8,IF($GW38="","THERMAL - NOT SPECIFIED",$GW38))) -> 6137 | G38: =IF(G8="","",IF(G8<>"THERMAL",G8,IF($GW38="","THERMAL - NOT SPECIFIED",$GW38))) -> 6137 | H38: =IF(H8="","",IF(H8<>"THERMAL",H8,IF($GW38="","THERMAL - NOT SPECIFIED",$GW38))) -> 6137 | I38: =IF(I8="","",IF(I8<>"THERMAL",I8,IF($GW38="","THERMAL - NOT SPECIFIED",$GW38))) -> 6137 | ... GS38: =IF(GS8="","",IF(GS8<>"THERMAL",GS8,IF($GW38="","THERMAL - NOT SPECIFIED",$GW38))) | GW38: =IF($GY38="","",IFERROR(INDEX('MC MAP'!$L$5:$L$28,MATCH($GY38,'MC MAP'!$K$5:$K$28,0)),$GY38)) -> TH-02 | GY38: TH02 | HE38: 5503
A39: =$A9 -> 4 | B39: =IF(B9="","",IF(B9<>"THERMAL",B9,IF($GW39="","THERMAL - NOT SPECIFIED",$GW39))) -> RS 26/27 | C39: =IF(C9="","",IF(C9<>"THERMAL",C9,IF($GW39="","THERMAL - NOT SPECIFIED",$GW39))) -> RS 26/27 | D39: =IF(D9="","",IF(D9<>"THERMAL",D9,IF($GW39="","THERMAL - NOT SPECIFIED",$GW39))) -> RS 26/27 | E39: =IF(E9="","",IF(E9<>"THERMAL",E9,IF($GW39="","THERMAL - NOT SPECIFIED",$GW39))) -> RS 26/27 | F39: =IF(F9="","",IF(F9<>"THERMAL",F9,IF($GW39="","THERMAL - NOT SPECIFIED",$GW39))) -> RS 26/27 | G39: =IF(G9="","",IF(G9<>"THERMAL",G9,IF($GW39="","THERMAL - NOT SPECIFIED",$GW39))) -> RS 26/27 | H39: =IF(H9="","",IF(H9<>"THERMAL",H9,IF($GW39="","THERMAL - NOT SPECIFIED",$GW39))) -> RS 26/27 | I39: =IF(I9="","",IF(I9<>"THERMAL",I9,IF($GW39="","THERMAL - NOT SPECIFIED",$GW39))) -> RS 26/27 | ... GS39: =IF(GS9="","",IF(GS9<>"THERMAL",GS9,IF($GW39="","THERMAL - NOT SPECIFIED",$GW39))) | GW39: =IF($GY39="","",IFERROR(INDEX('MC MAP'!$L$5:$L$28,MATCH($GY39,'MC MAP'!$K$5:$K$28,0)),$GY39)) | HE39: 5520
A40: =$A10 -> 5 | B40: =IF(B10="","",IF(B10<>"THERMAL",B10,IF($GW40="","THERMAL - NOT SPECIFIED",$GW40))) -> 6820 | C40: =IF(C10="","",IF(C10<>"THERMAL",C10,IF($GW40="","THERMAL - NOT SPECIFIED",$GW40))) -> 6820 | D40: =IF(D10="","",IF(D10<>"THERMAL",D10,IF($GW40="","THERMAL - NOT SPECIFIED",$GW40))) -> 6820 | E40: =IF(E10="","",IF(E10<>"THERMAL",E10,IF($GW40="","THERMAL - NOT SPECIFIED",$GW40))) -> 6820 | F40: =IF(F10="","",IF(F10<>"THERMAL",F10,IF($GW40="","THERMAL - NOT SPECIFIED",$GW40))) -> 6820 | G40: =IF(G10="","",IF(G10<>"THERMAL",G10,IF($GW40="","THERMAL - NOT SPECIFIED",$GW40))) -> 6820 | H40: =IF(H10="","",IF(H10<>"THERMAL",H10,IF($GW40="","THERMAL - NOT SPECIFIED",$GW40))) -> 6820 | I40: =IF(I10="","",IF(I10<>"THERMAL",I10,IF($GW40="","THERMAL - NOT SPECIFIED",$GW40))) -> 6820 | ... GS40: =IF(GS10="","",IF(GS10<>"THERMAL",GS10,IF($GW40="","THERMAL - NOT SPECIFIED",$GW40))) | GW40: =IF($GY40="","",IFERROR(INDEX('MC MAP'!$L$5:$L$28,MATCH($GY40,'MC MAP'!$K$5:$K$28,0)),$GY40)) | HE40: TH-04
A41: =$A11 -> 6 | B41: =IF(B11="","",IF(B11<>"THERMAL",B11,IF($GW41="","THERMAL - NOT SPECIFIED",$GW41))) -> 6820 | C41: =IF(C11="","",IF(C11<>"THERMAL",C11,IF($GW41="","THERMAL - NOT SPECIFIED",$GW41))) -> 6820 | D41: =IF(D11="","",IF(D11<>"THERMAL",D11,IF($GW41="","THERMAL - NOT SPECIFIED",$GW41))) -> 6820 | E41: =IF(E11="","",IF(E11<>"THERMAL",E11,IF($GW41="","THERMAL - NOT SPECIFIED",$GW41))) -> 6820 | F41: =IF(F11="","",IF(F11<>"THERMAL",F11,IF($GW41="","THERMAL - NOT SPECIFIED",$GW41))) -> 6820 | G41: =IF(G11="","",IF(G11<>"THERMAL",G11,IF($GW41="","THERMAL - NOT SPECIFIED",$GW41))) -> 6820 | H41: =IF(H11="","",IF(H11<>"THERMAL",H11,IF($GW41="","THERMAL - NOT SPECIFIED",$GW41))) -> 6820 | I41: =IF(I11="","",IF(I11<>"THERMAL",I11,IF($GW41="","THERMAL - NOT SPECIFIED",$GW41))) -> 6820 | ... GS41: =IF(GS11="","",IF(GS11<>"THERMAL",GS11,IF($GW41="","THERMAL - NOT SPECIFIED",$GW41))) | GW41: =IF($GY41="","",IFERROR(INDEX('MC MAP'!$L$5:$L$28,MATCH($GY41,'MC MAP'!$K$5:$K$28,0)),$GY41)) | HE41: TH-01
A42: =$A12 -> 7 | B42: =IF(B12="","",IF(B12<>"THERMAL",B12,IF($GW42="","THERMAL - NOT SPECIFIED",$GW42))) -> 6137 | C42: =IF(C12="","",IF(C12<>"THERMAL",C12,IF($GW42="","THERMAL - NOT SPECIFIED",$GW42))) -> 6137 | D42: =IF(D12="","",IF(D12<>"THERMAL",D12,IF($GW42="","THERMAL - NOT SPECIFIED",$GW42))) -> 6137 | E42: =IF(E12="","",IF(E12<>"THERMAL",E12,IF($GW42="","THERMAL - NOT SPECIFIED",$GW42))) -> 6137 | F42: =IF(F12="","",IF(F12<>"THERMAL",F12,IF($GW42="","THERMAL - NOT SPECIFIED",$GW42))) -> 6137 | G42: =IF(G12="","",IF(G12<>"THERMAL",G12,IF($GW42="","THERMAL - NOT SPECIFIED",$GW42))) -> 6137 | H42: =IF(H12="","",IF(H12<>"THERMAL",H12,IF($GW42="","THERMAL - NOT SPECIFIED",$GW42))) -> 6137 | I42: =IF(I12="","",IF(I12<>"THERMAL",I12,IF($GW42="","THERMAL - NOT SPECIFIED",$GW42))) -> 6137 | ... GS42: =IF(GS12="","",IF(GS12<>"THERMAL",GS12,IF($GW42="","THERMAL - NOT SPECIFIED",$GW42))) | GW42: =IF($GY42="","",IFERROR(INDEX('MC MAP'!$L$5:$L$28,MATCH($GY42,'MC MAP'!$K$5:$K$28,0)),$GY42)) | HE42: TH-05
A43: =$A13 -> 8 | B43: =IF(B13="","",IF(B13<>"THERMAL",B13,IF($GW43="","THERMAL - NOT SPECIFIED",$GW43))) -> 6109 | C43: =IF(C13="","",IF(C13<>"THERMAL",C13,IF($GW43="","THERMAL - NOT SPECIFIED",$GW43))) -> 6109 | D43: =IF(D13="","",IF(D13<>"THERMAL",D13,IF($GW43="","THERMAL - NOT SPECIFIED",$GW43))) -> 6109 | E43: =IF(E13="","",IF(E13<>"THERMAL",E13,IF($GW43="","THERMAL - NOT SPECIFIED",$GW43))) -> 6109 | F43: =IF(F13="","",IF(F13<>"THERMAL",F13,IF($GW43="","THERMAL - NOT SPECIFIED",$GW43))) -> 6109 | G43: =IF(G13="","",IF(G13<>"THERMAL",G13,IF($GW43="","THERMAL - NOT SPECIFIED",$GW43))) -> 6109 | H43: =IF(H13="","",IF(H13<>"THERMAL",H13,IF($GW43="","THERMAL - NOT SPECIFIED",$GW43))) -> 6109 | I43: =IF(I13="","",IF(I13<>"THERMAL",I13,IF($GW43="","THERMAL - NOT SPECIFIED",$GW43))) -> 6109 | ... GS43: =IF(GS13="","",IF(GS13<>"THERMAL",GS13,IF($GW43="","THERMAL - NOT SPECIFIED",$GW43))) | GW43: =IF($GY43="","",IFERROR(INDEX('MC MAP'!$L$5:$L$28,MATCH($GY43,'MC MAP'!$K$5:$K$28,0)),$GY43)) | HE43: TH-06
A44: =$A14 -> 9 | B44: =IF(B14="","",IF(B14<>"THERMAL",B14,IF($GW44="","THERMAL - NOT SPECIFIED",$GW44))) -> 6109 | C44: =IF(C14="","",IF(C14<>"THERMAL",C14,IF($GW44="","THERMAL - NOT SPECIFIED",$GW44))) -> 6109 | D44: =IF(D14="","",IF(D14<>"THERMAL",D14,IF($GW44="","THERMAL - NOT SPECIFIED",$GW44))) -> 6109 | E44: =IF(E14="","",IF(E14<>"THERMAL",E14,IF($GW44="","THERMAL - NOT SPECIFIED",$GW44))) -> 6109 | F44: =IF(F14="","",IF(F14<>"THERMAL",F14,IF($GW44="","THERMAL - NOT SPECIFIED",$GW44))) -> 6109 | G44: =IF(G14="","",IF(G14<>"THERMAL",G14,IF($GW44="","THERMAL - NOT SPECIFIED",$GW44))) -> 6109 | H44: =IF(H14="","",IF(H14<>"THERMAL",H14,IF($GW44="","THERMAL - NOT SPECIFIED",$GW44))) -> 6109 | I44: =IF(I14="","",IF(I14<>"THERMAL",I14,IF($GW44="","THERMAL - NOT SPECIFIED",$GW44))) -> 6109 | ... GS44: =IF(GS14="","",IF(GS14<>"THERMAL",GS14,IF($GW44="","THERMAL - NOT SPECIFIED",$GW44))) | GW44: =IF($GY44="","",IFERROR(INDEX('MC MAP'!$L$5:$L$28,MATCH($GY44,'MC MAP'!$K$5:$K$28,0)),$GY44)) | HE44: 5544
A45: =$A15 -> 10 | B45: =IF(B15="","",IF(B15<>"THERMAL",B15,IF($GW45="","THERMAL - NOT SPECIFIED",$GW45))) -> 6109 | C45: =IF(C15="","",IF(C15<>"THERMAL",C15,IF($GW45="","THERMAL - NOT SPECIFIED",$GW45))) -> 6109 | D45: =IF(D15="","",IF(D15<>"THERMAL",D15,IF($GW45="","THERMAL - NOT SPECIFIED",$GW45))) -> 6109 | E45: =IF(E15="","",IF(E15<>"THERMAL",E15,IF($GW45="","THERMAL - NOT SPECIFIED",$GW45))) -> 6109 | F45: =IF(F15="","",IF(F15<>"THERMAL",F15,IF($GW45="","THERMAL - NOT SPECIFIED",$GW45))) -> 6109 | G45: =IF(G15="","",IF(G15<>"THERMAL",G15,IF($GW45="","THERMAL - NOT SPECIFIED",$GW45))) -> 6109 | H45: =IF(H15="","",IF(H15<>"THERMAL",H15,IF($GW45="","THERMAL - NOT SPECIFIED",$GW45))) -> 6109 | I45: =IF(I15="","",IF(I15<>"THERMAL",I15,IF($GW45="","THERMAL - NOT SPECIFIED",$GW45))) -> 6109 | ... GS45: =IF(GS15="","",IF(GS15<>"THERMAL",GS15,IF($GW45="","THERMAL - NOT SPECIFIED",$GW45))) | GW45: =IF($GY45="","",IFERROR(INDEX('MC MAP'!$L$5:$L$28,MATCH($GY45,'MC MAP'!$K$5:$K$28,0)),$GY45)) | HE45: 5543
A46: =$A16 -> 11 | B46: =IF(B16="","",IF(B16<>"THERMAL",B16,IF($GW46="","THERMAL - NOT SPECIFIED",$GW46))) -> 6108 | C46: =IF(C16="","",IF(C16<>"THERMAL",C16,IF($GW46="","THERMAL - NOT SPECIFIED",$GW46))) -> 6108 | D46: =IF(D16="","",IF(D16<>"THERMAL",D16,IF($GW46="","THERMAL - NOT SPECIFIED",$GW46))) -> 6108 | E46: =IF(E16="","",IF(E16<>"THERMAL",E16,IF($GW46="","THERMAL - NOT SPECIFIED",$GW46))) -> 6108 | F46: =IF(F16="","",IF(F16<>"THERMAL",F16,IF($GW46="","THERMAL - NOT SPECIFIED",$GW46))) -> 6108 | G46: =IF(G16="","",IF(G16<>"THERMAL",G16,IF($GW46="","THERMAL - NOT SPECIFIED",$GW46))) -> 6108 | H46: =IF(H16="","",IF(H16<>"THERMAL",H16,IF($GW46="","THERMAL - NOT SPECIFIED",$GW46))) -> 6108 | I46: =IF(I16="","",IF(I16<>"THERMAL",I16,IF($GW46="","THERMAL - NOT SPECIFIED",$GW46))) -> 6108 | ... GS46: =IF(GS16="","",IF(GS16<>"THERMAL",GS16,IF($GW46="","THERMAL - NOT SPECIFIED",$GW46))) | GW46: =IF($GY46="","",IFERROR(INDEX('MC MAP'!$L$5:$L$28,MATCH($GY46,'MC MAP'!$K$5:$K$28,0)),$GY46)) | HE46: TH-02
A47: =$A17 -> 12 | B47: =IF(B17="","",IF(B17<>"THERMAL",B17,IF($GW47="","THERMAL - NOT SPECIFIED",$GW47))) -> 6108 | C47: =IF(C17="","",IF(C17<>"THERMAL",C17,IF($GW47="","THERMAL - NOT SPECIFIED",$GW47))) -> 6108 | D47: =IF(D17="","",IF(D17<>"THERMAL",D17,IF($GW47="","THERMAL - NOT SPECIFIED",$GW47))) -> 6108 | E47: =IF(E17="","",IF(E17<>"THERMAL",E17,IF($GW47="","THERMAL - NOT SPECIFIED",$GW47))) -> 6108 | F47: =IF(F17="","",IF(F17<>"THERMAL",F17,IF($GW47="","THERMAL - NOT SPECIFIED",$GW47))) -> 6108 | G47: =IF(G17="","",IF(G17<>"THERMAL",G17,IF($GW47="","THERMAL - NOT SPECIFIED",$GW47))) -> 6108 | H47: =IF(H17="","",IF(H17<>"THERMAL",H17,IF($GW47="","THERMAL - NOT SPECIFIED",$GW47))) -> 6108 | I47: =IF(I17="","",IF(I17<>"THERMAL",I17,IF($GW47="","THERMAL - NOT SPECIFIED",$GW47))) -> 6108 | ... GS47: =IF(GS17="","",IF(GS17<>"THERMAL",GS17,IF($GW47="","THERMAL - NOT SPECIFIED",$GW47))) | GW47: =IF($GY47="","",IFERROR(INDEX('MC MAP'!$L$5:$L$28,MATCH($GY47,'MC MAP'!$K$5:$K$28,0)),$GY47)) | HE47: VACCANT
A48: =$A18 -> 13 | B48: =IF(B18="","",IF(B18<>"THERMAL",B18,IF($GW48="","THERMAL - NOT SPECIFIED",$GW48))) -> RS17 | C48: =IF(C18="","",IF(C18<>"THERMAL",C18,IF($GW48="","THERMAL - NOT SPECIFIED",$GW48))) -> RS17 | D48: =IF(D18="","",IF(D18<>"THERMAL",D18,IF($GW48="","THERMAL - NOT SPECIFIED",$GW48))) -> RS17 | E48: =IF(E18="","",IF(E18<>"THERMAL",E18,IF($GW48="","THERMAL - NOT SPECIFIED",$GW48))) -> RS17 | F48: =IF(F18="","",IF(F18<>"THERMAL",F18,IF($GW48="","THERMAL - NOT SPECIFIED",$GW48))) -> RS17 | G48: =IF(G18="","",IF(G18<>"THERMAL",G18,IF($GW48="","THERMAL - NOT SPECIFIED",$GW48))) -> RS17 | H48: =IF(H18="","",IF(H18<>"THERMAL",H18,IF($GW48="","THERMAL - NOT SPECIFIED",$GW48))) -> RS17 | I48: =IF(I18="","",IF(I18<>"THERMAL",I18,IF($GW48="","THERMAL - NOT SPECIFIED",$GW48))) -> RS17 | ... GS48: =IF(GS18="","",IF(GS18<>"THERMAL",GS18,IF($GW48="","THERMAL - NOT SPECIFIED",$GW48))) | GW48: =IF($GY48="","",IFERROR(INDEX('MC MAP'!$L$5:$L$28,MATCH($GY48,'MC MAP'!$K$5:$K$28,0)),$GY48))
